Workbook
Name UPDATE: 'Data Sheet'!$E$1

Sheet Cash Flow Data
B2: 42339 | C2: 42705 | D2: 43070 | E2: 43435 | F2: 43800 | G2: 44166 | H2: 44531 | I2: 44896 | J2: 45261 | K2: 45352 | L2: 45717 | M2: 46082
B3: Cash from Operating Activity - | C3: 1098 | D3: 1466 | E3: 1818 | F3: 2052 | G3: 2295 | H3: 2454 | I3: 2236 | J3: 2737 | K3: 3392 | L3: 4175 | M3: 2935 | N3: 5048
B4: Profit from operations | C4: 1109 | D4: 1765 | E4: 2047 | F4: 2521 | G4: 2805 | H4: 3061 | I4: 3136 | J4: 3609 | K4: 4388 | L4: 5722 | M4: 4672 | N4: 5326
B5: Receivables | C5: 21 | D5: -19 | E5: 8 | F5: -36 | G5: 0 | H5: -42 | I5: -2 | J5: -28 | K5: -11 | L5: -109 | M5: -70 | N5: 34
B6: Inventory | C6: 23 | D6: -119 | E6: 38 | F6: -63 | G6: -318 | H6: -133 | I6: -169 | J6: -336 | K6: 56 | L6: -161 | M6: -767 | N6: 281
B7: Payables | C7: 79 | D7: 50 | E7: 185 | F7: 257 | G7: 253 | H7: 23 | I7: 217 | J7: 178 | K7: 68 | L7: 310 | M7: 134 | N7: 588
B8: Loans Advances | C8: -3 | D8: 0 | E8: 0 | F8: 0 | G8: 0 | H8: 0 | I8: -40 | J8: -30 | K8: -30 | L8: -21 | M8: -199 | N8: -73
B9: Operating borrowings | C9: 2 | D9: 0 | E9: 0 | F9: 0 | G9: 0 | H9: 0 | I9: 0 | J9: 0 | K9: 0 | L9: 0 | M9: 0 | N9: 0
B10: Other WC items | C10: 210 | D10: 293 | E10: 144 | F10: 255 | G10: 227 | H10: 249 | I10: -179 | J10: 185 | K10: -19 | L10: -268 | M10: 155 | N10: -37
B11: Working capital changes | C11: 332 | D11: 204 | E11: 375 | F11: 413 | G11: 163 | H11: 97 | I11: -172 | J11: -30 | K11: 63 | L11: -249 | M11: -747 | N11: 793
B12: Direct taxes | C12: -342 | D12: -503 | E12: -604 | F12: -881 | G12: -673 | H12: -703 | I12: -729 | J12: -841 | K12: -1059 | L12: -1299 | M12: -990 | N12: -1071
B13: Cash from Investing Activity - | C13: -70 | D13: -126 | E13: -131 | F13: -52 | G13: 83 | H13: -321 | I13: -1920 | J13: -392 | K13: -927 | L13: -1237 | M13: -1811 | N13: -624
B14: Fixed assets purchased | C14: -151 | D14: -207 | E14: -199 | F14: -166 | G14: -155 | H14: -478 | I14: -735 | J14: -550 | K14: -1371 | L14: -1883 | M14: -2009 | N14: -830
... B32: CFO/OP | C32: 0.93 | D32: 1.06 | E32: 1.16 | F32: 1.12 | G32: 1.01 | H32: 0.99 | I32: 0.83 | J32: 0.97 | K32: 1 | L32: 0.94 | M32: 0.82 | N32: 1.15

Sheet Company Flows
B2: Valuation | D2: Financial Modeling Forecast | J2: Forecast Income Statement | N2: Forecast Balance Sheet | R2: Forecast Cash Flow | V2: calculate Free Cash Flow
AA3: Where Forecasting Actually Happens
N4: Revenue
B5: Choose a Company | D5: Annual Report | J5: Revenue | N5: │ | R5: Net Income | V5: EBIT
B6: │ | D6: │ | J6: │ | N6: ▼ | R6: │ | V6: │ | AA6: Financial Statement | AB6: Forecast Driver
B7: ▼ | D7: ▼ | J7: ▼ | N7: Accounts Receivable | R7: ▼ | V7: ▼ | AA7: Revenue | AB7: Growth %, Volume × Price
B8: Read Annual Report | D8: Understand the Business Model | J8: Revenue Growth Assumption | N8: (Receivable Days) | R8: Add: Depreciation | V8: Less Tax | AA8: COGS | AB8: % of Revenue
B9: │ | D9: (Revenue, Products, Industry, Risks, Competition) | J9: │ | V9: │ | AA9: Marketing | AB9: % of Revenue
B10: ▼ | D10: │ | J10: ▼ | N10: Revenue | R10: ± Working Capital Changes | V10: ▼ | AA10: Employee Cost | AB10: % of Revenue or Headcount
B11: Understand Business | D11: ▼ | J11: Forecast Revenue | N11: │ | V11: NOPAT | AA11: Depreciation | AB11: PPE Schedule
B12: • Revenue | D12: Collect Historical Financial Data | J12: │ | N12: ▼ | R12: − Capex | V12: │ | AA12: Interest | AB12: Debt Schedule
B13: • Products | D13: (Income Statement, BS, Cash Flow) | J13: ▼ | N13: Inventory | V13: ▼ | AA13: Tax | AB13: Effective Tax Rate
B14: • Risks | D14: │ | J14: COGS (% of Revenue) | N14: (Inventory Days) | R14: ± Debt Raised/Repaid | V14: Add: Depreciation | AA14: Accounts Receivable | AB14: Receivable Days
B15: • Industry | D15: ▼ | J15: │ | V15: │ | AA15: Inventory | AB15: Inventory Days
B16: │ | D16: Clean & Structure Data in Excel | J16: ▼ | N16: COGS | R16: ± Dividends | V16: ▼ | AA16: Accounts Payable | AB16: Payable Days
B17: ▼ | D17: │ | J17: Gross Profit | N17: │ | V17: − Capex | AA17: PPE | AB17: Capex − Depreciation
B18: Historical Financial Statements | D18: ▼ | J18: │ | N18: ▼ | R18: ─────────────── | V18: │ | AA18: Cash | AB18: Cash Flow Statement
B19: (IS, BS, CFS) | D19: Historical Ratio Analysis | J19: ▼ | N19: Accounts Payable | R19: Ending Cash | V19: ▼
B20: │ | D20: (Margins, Growth, Working Capital, | J20: Operating Expenses | N20: (Payable Days) | V20: − Increase in Working Capital
B21: ▼ | D21: Liquidity, Leverage, Efficiency) | J21: (SG&A, Marketing, R&D) | V21: │
B22: Financial Modeling | D22: │ | J22: │ | N22: Capex | V22: ▼ | AA22: The 10-Step Formula You Should Memorize
B23: Forecast next 5–10 years | D23: ▼ | J23: ▼ | N23: │ | V23: Free Cash Flow (FCFF)
B24: • Revenue | D24: Identify Forecast Drivers | J24: EBITDA | N24: ▼ | AA24: 1. Understand the Business
B25: • Expenses | J25: │ | N25: PPE | AA25: 2. Collect Historical Financial Statements
B26: • Capex | J26: ▼ | AA26: 3. Perform Ratio & Trend Analysis
B27: • Working Capital | J27: Depreciation | N27: Debt Schedule | AA27: 4. Identify Forecast Drivers
B28: • Taxes | J28: │ | N28: │ | AA28: 5. Forecast Income Statement
B29: │ | J29: ▼ | N29: ▼ | AA29: 6. Forecast Balance Sheet
B30: ▼ | J30: EBIT | N30: Short-term Debt | V30: 46212 | AA30: 7. Forecast Cash Flow Statement
B31: Calculate Free Cash Flow (FCFF) | J31: │ | AA31: 8. Calculate Free Cash Flow (FCFF)
B32: │ | J32: ▼ | N32: Long-term Debt | AA32: 9. Value the Company (CAPM → WACC → DCF)
B33: ▼ | J33: Interest Expense | AA33: 10. Present Investment Recommendation
B34: Now ask... | J34: (Based on Debt) | N34: Retained Earnings
B35: What discount rate should I use? | J35: │ | N35: (Net Income − Dividend)
B36: │ | J36: ▼
B37: ▼ | J37: EBT | N37: Everything balances
B38: Calculate WACC | J38: │
B39: │ | J39: ▼ | N39: Assets = Liabilities + Equity
B40: ├──────────────┐ | J40: Tax
B41: ▼ ▼ | J41: │
B42: Cost of Equity Cost of Debt | J42: ▼
B43: (CAPM) (Interest Rate) | J43: Net Income
B44: │ │
B45: ▼ ▼
B46: Expected Return Actual Borrowing Cost | I46: Dividend Timeline
B47: for Investors of Company | O47: Concept | P47: Meaning
B48: │ │ | O48: Dividend | P48: Profit paid to shareholders
B49: └──────┬───────┘ | I49: Company Declares Dividend | O49: Ex-Dividend Date | P49: Buy before this date to receive the dividend
B50: ▼ | I50: │ | O50: Record Date | P50: Company identifies eligible shareholders
B51: Weighted Average | I51: ▼ | O51: Payment Date | P51: Dividend is paid
B52: Cost of Capital (WACC) | I52: Declaration Date | O52: Dividend Yield | P52: Dividend earned relative to the current share price
B53: │ | I53: │
B54: ▼ | I54: ▼
B55: Discount FCFF | I55: Ex-Dividend Date
B56: using WACC | I56: (Buy before this date to receive dividend)
B57: │ | I57: │
B58: ▼ | I58: ▼
B59: Present Value of | I59: Record Date
B60: Future Cash Flows | I60: (Company checks shareholder records)
B61: │ | I61: │
B62: ▼ | I62: ▼
B63: Calculate Terminal Value | I63: Payment Date
B64: │ | I64: (Dividend is credited)
B65: ▼
B66: Enterprise Value
B67: │
B68: Less Net Debt
B69: (Debt − Cash)
B70: │
B71: ▼
B72: Equity Value
B73: │
B74: Divide by Shares Outstanding
B75: │
B76: ▼
... B83: BUY / HOLD / SELL

Sheet WACC (2)
B6: Nestlee - Weighted Average Cost of Capital
B8: All figures are in INR unless stated otherwise
B10: Peer Companies
G12: Debt/ | H12: Debt/ | I12: Levered | J12: Unlevered
B13: Name of the Company | C13: Country | D13: Total Debt | E13: Total Equity | F13: Tax Rate1 | G13: Equity | H13: Capital | I13: Beta2 | J13: Beta3
B15: Nestle India | C15: India | D15: 444.16 | E15: 280608.3 | F15: 0.3 | G15: =D15/E15 -> 0.001582847 | H15: =D15/(D15+E15) -> 0.0015803455 | I15: 0.788 | J15: =I15/(1+(1-F15)*G15) -> 0.78712787
B16: Hind. Unilever | C16: India | D16: 1478 | E16: 505303.1 | F16: 0.3 | G16: =D16/E16 -> 0.0029249771 | H16: =D16/(D16+E16) -> 0.0029164466 | I16: 0.504 | J16: =I16/(1+(1-F16)*G16) -> 0.50297018
B17: Britannia Inds. | C17: India | D17: 1380.28 | E17: 128936.8 | F17: 0.3 | G17: =D17/E17 -> 0.01070509 | H17: =D17/(D17+E17) -> 0.010591704 | I17: 0.372 | J17: =I17/(1+(1-F17)*G17) -> 0.36923313
B18: Godrej Consumer | C18: India | D18: 4415.81 | E18: 111376.51 | F18: 0.3 | G18: =D18/E18 -> 0.039647588 | H18: =D18/(D18+E18) -> 0.038135603 | I18: 1.04 | J18: =I18/(1+(1-F18)*G18) -> 1.011916
B19: Tata Consumer | C19: India | D19: 2819.51 | E19: 110039.4 | F19: 0.3 | G19: =D19/E19 -> 0.025622731 | H19: =D19/(D19+E19) -> 0.024982609 | I19: 0.426 | J19: =I19/(1+(1-F19)*G19) -> 0.41849393
B20: Dabur India | C20: India | D20: 1287.32 | E20: 78674.79 | F20: 0.3 | G20: =D20/E20 -> 0.016362548 | H20: =D20/(D20+E20) -> 0.016099125 | I20: 0.927 | J20: =I20/(1+(1-F20)*G20) -> 0.91650258
E23: Average | F23: =AVERAGE(F15:F20) -> 0.3 | G23: =AVERAGE(G16:G20) -> 0.019052587 | H23: =AVERAGE(H16:H20) -> 0.018545098 | I23: =AVERAGE(I15:I20) -> 0.67616667 | J23: =AVERAGE(J15:J20) -> 0.66770728
E24: Median | F24: =MEDIAN(F15:F20) -> 0.3 | G24: =MEDIAN(G16:G20) -> 0.016362548 | H24: =MEDIAN(H16:H20) -> 0.016099125 | I24: =MEDIAN(I15:I20) -> 0.646 | J24: =MEDIAN(J15:J20) -> 0.64504902
B27: Cost of Debt | G27: Cost of Equity ( CAPM or Ke)
B29: Pre Tax Cost of Debt | D29: =37/D15 -> 0.083303314 | E29: >> Interest/Total Debt | G29: Risk Free Rate | K29: 0.06716 | L29: >>> 10 years Govt bond return
B30: Tax Rate | D30: =F15 -> 0.3 | G30: Equity Risk Premium | K30: =Rm!I5-'WACC (2)'!K29 -> 0.084332308 | L30: >> Rm- Rf = Rewarded Return
B31: Actual debt after Tax | D31: =D29*(1-D30) -> 0.05831232 | G31: Levered Beta4 | K31: =K40 -> 0.653581
G32: Cost of Equity | K32: =K29+K30*K31 -> 0.12227799
B35: Capital Structure | G35: Levered Beta
D37: Current | E37: Targeted | G37: Comps median unlevered beta | K37: =J24 -> 0.64504902
B38: Total Debt | C38: =D15 -> 444.16 | D38: =C38/C40 -> 0.0015803455 | E38: =H23 -> 0.018545098 | G38: Targeted debt/Equity | K38: =E43 -> 0.018895517
B39: Market Capitalization | C39: =E15 -> 280608.3 | D39: =C39/C40 -> 0.99841965 | E39: =E40-E38 -> 0.9814549 | G39: Tax Rate | K39: =D30 -> 0.3
B40: Total Capital | C40: =SUM(C38:C39) -> 281052.46 | D40: =SUM(D38:D39) -> 1 | E40: =D40 -> 1 | G40: Levered Beta | K40: =K37*(1+(1-K39)*K38) -> 0.653581
B43: Debt/Equity | D43: =D38/D39 -> 0.001582847 | E43: =E38/E39 -> 0.018895517 | G43: WACC
G44: Cost of Debt | K44: =D31 -> 0.05831232 | L44: Notes:
B45: Unlevered beta means business risk only | G45: Weight of Debt | K45: =E38 -> 0.018545098 | L45: Nifty 50 From Prime Investors finding out Rm
B46: Levered beta means business risk and financial risk | G46: Cost of Equity | K46: =K32 -> 0.12227799 | L46: Companies + Beta 1 year weekly return in Top Stock Research
B47: 1. Tax Rate considered as Marginal Tax Rate for the country | G47: Weight of Equity | K47: =E39 -> 0.9814549 | L47: Peer Companies with same business model, market cap from Screener
B48: 2. Levered Beta is based on 5 year monthly data | G48: Final | K48: =(K44*K45)+(K46*K47) -> 0.12109174 | L48: WACC >> Cost of money used by company
B49: 3. Unlevered Beta = Levered Beta/(1+(1-Tax Rate) x Debt/Equity)
B50: 4. Levered Beta = Unlevered Beta*(1+(1-Tax Rate) x Debt/Equity)

Sheet Data Sheet
A1: COMPANY NAME | B1: NESTLE INDIA LTD | E1: =IF(B2<>B3, "A NEW VERSION OF THE WORKSHEET IS AVAILABLE", "")
A2: LATEST VERSION | B2: 2.1 | E2: PLEASE DO NOT MAKE ANY CHANGES TO THIS SHEET
A3: CURRENT VERSION | B3: 2.1
A5: META
A6: Number of shares | B6: =IF(B9>0, B9/B8, 0) -> 192.83146
A7: Face Value | B7: 1
A8: Current Price | B8: 1409
A9: Market Capitalization | B9: 271699.53
A15: PROFIT & LOSS
A16: Report Date | B16: 43100 | C16: 43465 | D16: 43830 | E16: 44196 | F16: 44561 | G16: 44926 | H16: 45291 | I16: 45382 | J16: 45747 | K16: 46112
A17: Sales | B17: 10009.6 | C17: 11292.27 | D17: 12368.9 | E17: 13350.03 | F17: 14740.59 | G17: 16896.96 | H17: 19126.3 | I17: 24393.89 | J17: 20201.56 | K17: 23154.6
A18: Raw Material Cost | B18: 3696.99 | C18: 3829.22 | D18: 4520.91 | E18: 4901.74 | F18: 5301.26 | G18: 6660.42 | H18: 8472.72 | I18: 9201.11 | J18: 7646.63 | K18: 9113.96
A19: Change in Inventory | B19: 79.56 | C19: 6.01 | D19: 144.19 | E19: 69.33 | F19: 67.59 | G19: 250.27 | H19: 40.01 | I19: 45.68 | J19: 139.66 | K19: 168.23
A20: Power and Fuel | B20: 288.44 | C20: 344.18 | D20: 340.53 | E20: 313.68 | F20: 408.06 | G20: 572.61 | I20: 674.83 | J20: 541.42 | K20: 587.21
A21: Other Mfr. Exp | B21: 897.84 | C21: 949.86 | D21: 1028.55 | E21: 1040.36 | F21: 1349.48 | G21: 1603.48 | I21: 1935.4 | J21: 1582.45 | K21: 1816.29
A22: Employee Cost | B22: 1017.45 | C22: 1124.15 | D22: 1258.17 | E22: 1500.95 | F22: 1529.94 | G22: 1635.46 | H22: 1849.18 | I22: 2336.06 | J22: 2062.02 | K22: 2278.41
A23: Selling and admin | B23: 1823.98 | C23: 2145.82 | D23: 2226.13 | E23: 2246.9 | F23: 2902.12 | G23: 3192.15 | I23: 4837.58 | J23: 4126.54 | K23: 4780.9
A24: Other Expenses | B24: 267.93 | C24: 287.4 | D24: 212.92 | E24: 214.23 | F24: -245.08 | G24: -223.18 | H24: 4373.42 | I24: -388.53 | J24: -389.17 | K24: -560.9
A25: Other Income | B25: 176.92 | C25: 258.92 | D25: 246.88 | E25: 145.85 | F25: -112.38 | G25: 107.26 | H25: 115.5 | I25: 158.99 | J25: 352.06 | K25: 160.23
A26: Depreciation | B26: 342.25 | C26: 335.67 | D26: 370.15 | E26: 370.38 | F26: 391.02 | G26: 403.01 | H26: 428.91 | I26: 567.75 | J26: 539.92 | K26: 699.23
A27: Interest | B27: 91.9 | C27: 111.95 | D27: 129.12 | E27: 164.18 | F27: 201.68 | G27: 154.57 | H27: 119.29 | I27: 145.49 | J27: 136 | K27: 158.31
A28: Profit before tax | B28: 1839.3 | C28: 2428.95 | D28: 2673.49 | E28: 2812.79 | F28: 2857.32 | G28: 3255.97 | H28: 4038.29 | I28: 5288.87 | J28: 4447.47 | K28: 4609.65
A29: Tax | B29: 614.11 | C29: 822.02 | D29: 705.05 | E29: 730.36 | F29: 738.91 | G29: 865.45 | H29: 1039.62 | I29: 1356.03 | J29: 1132.97 | K29: 1065.05
A30: Net profit | B30: 1225.19 | C30: 1606.93 | D30: 1968.44 | E30: 2082.43 | F30: 2118.41 | G30: 2390.52 | H30: 2998.67 | I30: 3932.84 | J30: 3314.5 | K30: 3544.6
A31: Dividend Amount | B31: 829.21 | C31: 1108.83 | D31: 3297.56 | E31: 1928.4 | F31: 1928.4 | G31: 2121.24 | H31: 1677.71 | I31: 3104.72 | J31: 2603.34 | K31: 2313.96
A40: Quarters
A41: Report Date | B41: 45291 | C41: 45382 | D41: 45473 | E41: 45565 | F41: 45657 | G41: 45747 | H41: 45838 | I41: 45930 | J41: 46022 | K41: 46112
A42: Sales | B42: 4600.42 | C42: 5267.59 | D42: 4813.95 | E42: 5104 | F42: 4779.73 | G42: 5503.88 | H42: 5096.16 | I42: 5643.61 | J42: 5667.04 | K42: 6747.79
A43: Expenses | B43: 3505.3 | C43: 3917.54 | D43: 3699.62 | E43: 3936.27 | F43: 3677.04 | G43: 4115.58 | H43: 3995.9 | I43: 4406.97 | J43: 4466.09 | K43: 4976.19
A44: Other Income | B44: -77 | C44: 36.83 | D44: 39.12 | E44: 297.68 | F44: 4.44 | G44: 9.1 | H44: 4.04 | I44: 1.64 | J44: 169.78 | K44: -17.72
A45: Depreciation | B45: 108.69 | C45: 110.1 | D45: 112.71 | E45: 121.6 | F45: 150.27 | G45: 155.34 | H45: 156.94 | I45: 163.35 | J45: 174.41 | K45: 204.53
A46: Interest | B46: 22.95 | C46: 26.2 | D46: 31.68 | E46: 32.22 | F46: 34.6 | G46: 37.5 | H46: 46.89 | I46: 46.41 | J46: 28.25 | K46: 36.76
A47: Profit before tax | B47: 886.48 | C47: 1250.58 | D47: 1009.06 | E47: 1311.59 | F47: 922.26 | G47: 1204.56 | H47: 900.47 | I47: 1028.52 | J47: 1168.07 | K47: 1512.59
A48: Tax | B48: 230.87 | C48: 316.41 | D48: 262.46 | E48: 325.23 | F48: 226.13 | G48: 319.15 | H48: 241.24 | I48: 275.32 | J48: 150.01 | K48: 398.48
A49: Net profit | B49: 655.61 | C49: 934.17 | D49: 746.6 | E49: 986.36 | F49: 696.13 | G49: 885.41 | H49: 659.23 | I49: 753.2 | J49: 1018.06 | K49: 1114.11
A50: Operating Profit | B50: 1095.12 | C50: 1350.05 | D50: 1114.33 | E50: 1167.73 | F50: 1102.69 | G50: 1388.3 | H50: 1100.26 | I50: 1236.64 | J50: 1200.95 | K50: 1771.6
A55: BALANCE SHEET
A56: Report Date | B56: 43100 | C56: 43465 | D56: 43830 | E56: 44196 | F56: 44561 | G56: 44926 | H56: 45291 | I56: 45382 | J56: 45747 | K56: 46112
A57: Equity Share Capital | B57: 96.42 | C57: 96.42 | D57: 96.42 | E57: 96.42 | F57: 96.42 | G57: 96.42 | H57: 96.42 | I57: 96.42 | J57: 96.42 | K57: 192.83
A58: Reserves | B58: 3324.17 | C58: 3577.32 | D58: 1822.45 | E58: 1922.92 | F58: 1849.96 | G58: 2362.75 | H58: 2362.75 | I58: 3244.47 | J58: 4020.73 | K58: 5116.41
A59: Borrowings | B59: 35.14 | C59: 35.14 | D59: 188.94 | E59: 147.49 | F59: 266.46 | G59: 270.52 | H59: 270.52 | I59: 344.53 | J59: 1166.85 | K59: 444.16
A60: Other Liabilities | B60: 3906.86 | C60: 4379.2 | D60: 5065.13 | E60: 5732.9 | F60: 6021.29 | G60: 6249.05 | H60: 6249.05 | I60: 6837.64 | J60: 7039.89 | K60: 7603.77
A61: Total | B61: 7362.59 | C61: 8088.08 | D61: 7172.94 | E61: 7899.73 | F61: 8234.13 | G61: 8978.74 | H61: 8978.74 | I61: 10523.06 | J61: 12323.89 | K61: 13357.17
A62: Net Block | B62: 2616.18 | C62: 2400.62 | D62: 2341.45 | E62: 2179.41 | F62: 2994.67 | G62: 3043.7 | H62: 3043.7 | I62: 3460.25 | J62: 5473.61 | K62: 6290.42
A63: Capital Work in Progress | B63: 94.16 | C63: 105.2 | D63: 143.3 | E63: 638.58 | F63: 246.23 | G63: 358.36 | H63: 358.36 | I63: 1741.71 | J63: 1172.56 | K63: 506.98
A64: Investments | B64: 1978.87 | C64: 2658.49 | D64: 1751.05 | E64: 1463.77 | F64: 773.98 | G64: 777.54 | H64: 777.54 | I64: 463.87 | J64: 705.6 | K64: 705.6
A65: Other Assets | B65: 2673.38 | C65: 2923.77 | D65: 2937.14 | E65: 3617.97 | F65: 4219.25 | G65: 4799.14 | H65: 4799.14 | I65: 4857.23 | J65: 4972.12 | K65: 5854.17
A66: Total | B66: 7362.59 | C66: 8088.08 | D66: 7172.94 | E66: 7899.73 | F66: 8234.13 | G66: 8978.74 | H66: 8978.74 | I66: 10523.06 | J66: 12323.89 | K66: 13357.17
A67: Receivables | B67: 88.97 | C67: 124.59 | D67: 124.33 | E67: 164.93 | F67: 165.97 | G67: 191.89 | H67: 191.89 | I67: 300.46 | J67: 363.15 | K67: 329.47
... A69: Cash & Bank | B69: 1457.42 | C69: 1610.06 | D69: 1308.05 | E69: 1769.87 | F69: 735.41 | G69: 945.55 | H69: 945.55 | I69: 778.85 | J69: 95.65 | K69: 1340.87
A70: No. of Equity Shares | B70: 96415716 | C70: 96415716 | D70: 96415716 | E70: 96415716 | F70: 96415716 | G70: 96415716 | I70: 964157160 | J70: 964157160 | K70: 1928314320
A71: New Bonus Shares
A72: Face value | B72: 10 | C72: 10 | D72: 10 | E72: 10 | F72: 10 | G72: 10 | H72: 10 | I72: 1 | J72: 1 | K72: 1
A80: CASH FLOW:
A81: Report Date | B81: 43100 | C81: 43465 | D81: 43830 | E81: 44196 | F81: 44561 | G81: 44926 | H81: 45291 | I81: 45382 | J81: 45747 | K81: 46112
A82: Cash from Operating Activity | B82: 1817.79 | C82: 2052.45 | D82: 2295.25 | E82: 2454.48 | F82: 2236 | G82: 2737.43 | H82: 3392.19 | I82: 4174.79 | J82: 2934.53 | K82: 5047.56
A83: Cash from Investing Activity | B83: -130.56 | C83: -52.41 | D83: 82.99 | E83: -321.46 | F83: -1920.33 | G83: -391.73 | H83: -926.99 | I83: -1237.42 | J83: -1810.9 | K83: -623.68
A84: Cash from Financing Activity | B84: -996.62 | C84: -1317.42 | D84: -3601.53 | E84: -1955.89 | F84: -2019.97 | G84: -2122.74 | H84: -2436.47 | I84: -3134.92 | J84: -1846.3 | K84: -3179.49
A85: Net Cash Flow | B85: 690.61 | C85: 682.62 | D85: -1223.29 | E85: 177.13 | F85: -1704.3 | G85: 222.96 | H85: 28.73 | I85: -197.55 | J85: -722.67 | K85: 1244.39
A90: PRICE: | B90: 393.55 | C90: 554.24 | D90: 739.27 | E90: 919.51 | F90: 985.29 | G90: 980.3 | H90: 1329.02 | I90: 1311.18 | J90: 1125.38 | K90: 1174.8
A92: DERIVED:
A93: Adjusted Equity Shares in Cr | B93: 192.8 | C93: 192.8 | D93: 192.8 | E93: 192.8 | F93: 192.8 | G93: 192.8 | H93: 192.8 | I93: 192.83 | J93: 192.83 | K93: 192.83

Sheet Historical Analysis
B7: =" Financial Statements - "&'Data Sheet'!B1 -> Financial Statements - NESTLE INDIA LTD
B8: Year | C8: ='Data Sheet'!B16 -> 43100 | D8: ='Data Sheet'!C16 -> 43465 | E8: ='Data Sheet'!D16 -> 43830 | F8: ='Data Sheet'!E16 -> 44196 | G8: ='Data Sheet'!F16 -> 44561 | H8: ='Data Sheet'!G16 -> 44926 | I8: ='Data Sheet'!H16 -> 45291 | J8: ='Data Sheet'!I16 -> 45382 | ... L8: ='Data Sheet'!K16 -> 46112
B9: wf
B10: Income Statement
A11: # | B11: Sales | C11: =IFERROR('Data Sheet'!B17,0) -> 10009.6 | D11: =IFERROR('Data Sheet'!C17,0) -> 11292.27 | E11: =IFERROR('Data Sheet'!D17,0) -> 12368.9 | F11: =IFERROR('Data Sheet'!E17,0) -> 13350.03 | G11: =IFERROR('Data Sheet'!F17,0) -> 14740.59 | H11: =IFERROR('Data Sheet'!G17,0) -> 16896.96 | I11: =IFERROR('Data Sheet'!H17,0) -> 19126.3 | J11: =IFERROR('Data Sheet'!I17,0) -> 24393.89 | ... L11: =IFERROR('Data Sheet'!K17,0) -> 23154.6
B12: Sales Growth | C12: - | D12: =D11/C11-1 -> 0.12814398 | E12: =E11/D11-1 -> 0.095342212 | F12: =F11/E11-1 -> 0.079322333 | G12: =G11/F11-1 -> 0.10416156 | H12: =H11/G11-1 -> 0.1462879 | I12: =I11/H11-1 -> 0.13193734 | J12: =J11/I11-1 -> 0.27541082 | K12: =K11/J11-1 -> -0.17185984 | L12: =L11/K11-1 -> 0.14617881
B13: COGS | C13: =IFERROR(SUM('Data Sheet'!B18,'Data Sheet'!B20:B22)-1*'Data Sheet'!B19,0) -> 5821.16 | D13: =IFERROR(SUM('Data Sheet'!C18,'Data Sheet'!C20:C22)-1*'Data Sheet'!C19,0) -> 6241.4 | E13: =IFERROR(SUM('Data Sheet'!D18,'Data Sheet'!D20:D22)-1*'Data Sheet'!D19,0) -> 7003.97 | F13: =IFERROR(SUM('Data Sheet'!E18,'Data Sheet'!E20:E22)-1*'Data Sheet'!E19,0) -> 7687.4 | G13: =IFERROR(SUM('Data Sheet'!F18,'Data Sheet'!F20:F22)-1*'Data Sheet'!F19,0) -> 8521.15 | H13: =IFERROR(SUM('Data Sheet'!G18,'Data Sheet'!G20:G22)-1*'Data Sheet'!G19,0) -> 10221.7 | I13: =IFERROR(SUM('Data Sheet'!H18,'Data Sheet'!H20:H22)-1*'Data Sheet'!H19,0) -> 10281.89 | J13: =IFERROR(SUM('Data Sheet'!I18,'Data Sheet'!I20:I22)-1*'Data Sheet'!I19,0) -> 14101.72 | ... L13: =IFERROR(SUM('Data Sheet'!K18,'Data Sheet'!K20:K22)-1*'Data Sheet'!K19,0) -> 13627.64
B14: COGS % Sales | C14: =C13/C11 -> 0.5815577 | D14: =D13/D11 -> 0.55271438 | E14: =E13/E11 -> 0.5662565 | F14: =F13/F11 -> 0.57583391 | G14: =G13/G11 -> 0.57807388 | H14: =H13/H11 -> 0.60494314 | I14: =I13/I11 -> 0.53757862 | J14: =J13/J11 -> 0.5780841 | ... L14: =L13/L11 -> 0.58855001
B16: Gross Profit | C16: =C11-C13 -> 4188.44 | D16: =D11-D13 -> 5050.87 | E16: =E11-E13 -> 5364.93 | F16: =F11-F13 -> 5662.63 | G16: =G11-G13 -> 6219.44 | H16: =H11-H13 -> 6675.26 | I16: =I11-I13 -> 8844.41 | J16: =J11-J13 -> 10292.17 | ... L16: =L11-L13 -> 9526.96
B18: Selling & General Exp | C18: =IFERROR('Data Sheet'!B23,0) -> 1823.98 | D18: =IFERROR('Data Sheet'!C23,0) -> 2145.82 | E18: =IFERROR('Data Sheet'!D23,0) -> 2226.13 | F18: =IFERROR('Data Sheet'!E23,0) -> 2246.9 | G18: =IFERROR('Data Sheet'!F23,0) -> 2902.12 | H18: =IFERROR('Data Sheet'!G23,0) -> 3192.15 | I18: =IFERROR('Data Sheet'!H23,0) -> 0 | J18: =IFERROR('Data Sheet'!I23,0) -> 4837.58 | ... L18: =IFERROR('Data Sheet'!K23,0) -> 4780.9
B19: S&G % on Sales | C19: =C18/C11 -> 0.18222307 | D19: =D18/D11 -> 0.19002557 | E19: =E18/E11 -> 0.17997801 | F19: =F18/F11 -> 0.16830674 | G19: =G18/G11 -> 0.1968795 | H19: =H18/H11 -> 0.1889186 | I19: =I18/I11 -> 0 | J19: =J18/J11 -> 0.19831113 | ... L19: =L18/L11 -> 0.20647733
B21: Other Exp | C21: =IFERROR('Data Sheet'!B24,0) -> 267.93 | D21: =IFERROR('Data Sheet'!C24,0) -> 287.4 | E21: =IFERROR('Data Sheet'!D24,0) -> 212.92 | F21: =IFERROR('Data Sheet'!E24,0) -> 214.23 | G21: =IFERROR('Data Sheet'!F24,0) -> -245.08 | H21: =IFERROR('Data Sheet'!G24,0) -> -223.18 | I21: =IFERROR('Data Sheet'!H24,0) -> 4373.42 | J21: =IFERROR('Data Sheet'!I24,0) -> -388.53 | ... L21: =IFERROR('Data Sheet'!K24,0) -> -560.9
B23: EBITDA | C23: =C16-C18-ABS(C21) -> 2096.53 | D23: =D16-D18-ABS(D21) -> 2617.65 | E23: =E16-E18-ABS(E21) -> 2925.88 | F23: =F16-F18-ABS(F21) -> 3201.5 | G23: =G16-G18-G21 -> 3562.4 | H23: =H16-H18-H21 -> 3706.29 | I23: =I16-I18-ABS(I21) -> 4470.99 | J23: =J16-J18-J21 -> 5843.12 | K23: =K16-K18-K21 -> 4771.33 | L23: =L16-L18-L21 -> 5306.96
B24: EBITDA % on sales | C24: =C23/C11 -> 0.20945193 | D24: =D23/D11 -> 0.23180902 | E24: =E23/E11 -> 0.23655135 | F24: =F23/F11 -> 0.2398122 | G24: =G23/G11 -> 0.24167282 | H24: =H23/H11 -> 0.21934656 | I24: =I23/I11 -> 0.23376137 | J24: =J23/J11 -> 0.23953211 | ... L24: =L23/L11 -> 0.22919679
B26: Other Income | C26: =IFERROR('Data Sheet'!B25,0) -> 176.92 | D26: =IFERROR('Data Sheet'!C25,0) -> 258.92 | E26: =IFERROR('Data Sheet'!D25,0) -> 246.88 | F26: =IFERROR('Data Sheet'!E25,0) -> 145.85 | G26: =IFERROR('Data Sheet'!F25,0) -> -112.38 | H26: =IFERROR('Data Sheet'!G25,0) -> 107.26 | I26: =IFERROR('Data Sheet'!H25,0) -> 115.5 | J26: =IFERROR('Data Sheet'!I25,0) -> 158.99 | ... L26: =IFERROR('Data Sheet'!K25,0) -> 160.23
B28: Depreciation | C28: =IFERROR('Data Sheet'!B26,0) -> 342.25 | D28: =IFERROR('Data Sheet'!C26,0) -> 335.67 | E28: =IFERROR('Data Sheet'!D26,0) -> 370.15 | F28: =IFERROR('Data Sheet'!E26,0) -> 370.38 | G28: =IFERROR('Data Sheet'!F26,0) -> 391.02 | H28: =IFERROR('Data Sheet'!G26,0) -> 403.01 | I28: =IFERROR('Data Sheet'!H26,0) -> 428.91 | J28: =IFERROR('Data Sheet'!I26,0) -> 567.75 | ... L28: =IFERROR('Data Sheet'!K26,0) -> 699.23
B29: Depreciation on sales | C29: =C28/C11 -> 0.034192176 | D29: =D28/D11 -> 0.029725644 | E29: =E28/E11 -> 0.029925862 | F29: =F28/F11 -> 0.027743758 | G29: =G28/G11 -> 0.026526754 | H29: =H28/H11 -> 0.023851036 | I29: =I28/I11 -> 0.022425142 | J29: =J28/J11 -> 0.023274271 | ... L29: =L28/L11 -> 0.030198319
B31: EBIT ( Operating Income) | C31: =C23+C26-C28 -> 1931.2 | D31: =D23+D26-D28 -> 2540.9 | E31: =E23+E26-E28 -> 2802.61 | F31: =F23+F26-F28 -> 2976.97 | G31: =G23+G26-G28 -> 3059 | H31: =H23+H26-H28 -> 3410.54 | I31: =I23+I26-I28 -> 4157.58 | J31: =J23+J26-J28 -> 5434.36 | ... L31: =L23+L26-L28 -> 4767.96
B33: Interest | C33: =IFERROR('Data Sheet'!B27,0) -> 91.9 | D33: =IFERROR('Data Sheet'!C27,0) -> 111.95 | E33: =IFERROR('Data Sheet'!D27,0) -> 129.12 | F33: =IFERROR('Data Sheet'!E27,0) -> 164.18 | G33: =IFERROR('Data Sheet'!F27,0) -> 201.68 | H33: =IFERROR('Data Sheet'!G27,0) -> 154.57 | I33: =IFERROR('Data Sheet'!H27,0) -> 119.29 | J33: =IFERROR('Data Sheet'!I27,0) -> 145.49 | ... L33: =IFERROR('Data Sheet'!K27,0) -> 158.31
B34: Interest % on sales | C34: =C33/C11 -> 0.0091811861 | D34: =D33/D11 -> 0.0099138614 | E34: =E33/E11 -> 0.010439085 | F34: =F33/F11 -> 0.0122981 | G34: =G33/G11 -> 0.013681949 | H34: =H33/H11 -> 0.0091477994 | I34: =I33/I11 -> 0.0062369617 | J34: =J33/J11 -> 0.0059641984 | ... L34: =L33/L11 -> 0.0068370864
B37: EBT | C37: =C31-C33 -> 1839.3 | D37: =D31-D33 -> 2428.95 | E37: =E31-E33 -> 2673.49 | F37: =F31-F33 -> 2812.79 | G37: =G31-G33 -> 2857.32 | H37: =H31-H33 -> 3255.97 | I37: =I31-I33 -> 4038.29 | J37: =J31-J33 -> 5288.87 | ... L37: =L31-L33 -> 4609.65
B38: EBT % on sales | C38: =C37/C11 -> 0.1837536 | D38: =D37/D11 -> 0.21509847 | E38: =E37/E11 -> 0.21614614 | F38: =F37/F11 -> 0.21069541 | G38: =G37/G11 -> 0.19384027 | H38: =H37/H11 -> 0.19269561 | I38: =I37/I11 -> 0.21113807 | J38: =J37/J11 -> 0.21681126 | ... L38: =L37/L11 -> 0.19908139
B41: TAX | C41: =IFERROR('Data Sheet'!B29,0) -> 614.11 | D41: =IFERROR('Data Sheet'!C29,0) -> 822.02 | E41: =IFERROR('Data Sheet'!D29,0) -> 705.05 | F41: =IFERROR('Data Sheet'!E29,0) -> 730.36 | G41: =IFERROR('Data Sheet'!F29,0) -> 738.91 | H41: =IFERROR('Data Sheet'!G29,0) -> 865.45 | I41: =IFERROR('Data Sheet'!H29,0) -> 1039.62 | J41: =IFERROR('Data Sheet'!I29,0) -> 1356.03 | ... L41: =IFERROR('Data Sheet'!K29,0) -> 1065.05
B42: Effective Tax Growth | C42: =C41/C37 -> 0.33388246 | D42: =D41/D37 -> 0.33842607 | E42: =E41/E37 -> 0.26371896 | F42: =F41/F37 -> 0.25965678 | G42: =G41/G37 -> 0.25860247 | H42: =H41/H37 -> 0.26580405 | I42: =I41/I37 -> 0.25744065 | J42: =J41/J37 -> 0.25639314 | ... L42: =L41/L37 -> 0.23104791
B44: Net Profit | C44: =IFERROR(C37-C41,0) -> 1225.19 | D44: =IFERROR(D37-D41,0) -> 1606.93 | E44: =IFERROR(E37-E41,0) -> 1968.44 | F44: =IFERROR(F37-F41,0) -> 2082.43 | G44: =IFERROR(G37-G41,0) -> 2118.41 | H44: =IFERROR(H37-H41,0) -> 2390.52 | I44: =IFERROR(I37-I41,0) -> 2998.67 | J44: =IFERROR(J37-J41,0) -> 3932.84 | ... L44: =IFERROR(L37-L41,0) -> 3544.6
B45: Net Profit % on sales/ Margins | C45: =C44/C11 -> 0.12240149 | D45: =D44/D11 -> 0.14230354 | E45: =E44/E11 -> 0.15914431 | F45: =F44/F11 -> 0.15598692 | G45: =G44/G11 -> 0.1437127 | H45: =H44/H11 -> 0.14147634 | I45: =I44/I11 -> 0.15678255 | J45: =J44/J11 -> 0.16122234 | ... L45: =L44/L11 -> 0.15308405
B47: No of Equity Shares | C47: =IFERROR('Data Sheet'!B93,0) -> 192.8 | D47: =IFERROR('Data Sheet'!C93,0) -> 192.8 | E47: =IFERROR('Data Sheet'!D93,0) -> 192.8 | F47: =IFERROR('Data Sheet'!E93,0) -> 192.8 | G47: =IFERROR('Data Sheet'!F93,0) -> 192.8 | H47: =IFERROR('Data Sheet'!G93,0) -> 192.8 | I47: =IFERROR('Data Sheet'!H93,0) -> 192.8 | J47: =IFERROR('Data Sheet'!I93,0) -> 192.83 | ... L47: =IFERROR('Data Sheet'!K93,0) -> 192.83
B49: EPS | C49: =IFERROR(C44/C47,0) -> 6.3547199 | D49: =IFERROR(D44/D47,0) -> 8.3346992 | E49: =IFERROR(E44/E47,0) -> 10.209751 | F49: =IFERROR(F44/F47,0) -> 10.800985 | G49: =IFERROR(G44/G47,0) -> 10.987604 | H49: =IFERROR(H44/H47,0) -> 12.398963 | I49: =IFERROR(I44/I47,0) -> 15.553268 | J49: =IFERROR(J44/J47,0) -> 20.395374 | ... L49: =IFERROR(L44/L47,0) -> 18.381995
B50: EPS Growth% | D50: =IFERROR(D49/C49-1,0) -> 0.31157616 | E50: =IFERROR(E49/D49-1,0) -> 0.22496935 | F50: =IFERROR(F49/E49-1,0) -> 0.057908801 | G50: =IFERROR(G49/F49-1,0) -> 0.017277892 | H50: =IFERROR(H49/G49-1,0) -> 0.12845011 | I50: =IFERROR(I49/H49-1,0) -> 0.25440072 | J50: =IFERROR(J49/I49-1,0) -> 0.31132407 | K50: =IFERROR(K49/J49-1,0) -> -0.1572248 | L50: =IFERROR(L49/K49-1,0) -> 0.069422236
B53: Dividend Per share | C53: =IFERROR('Data Sheet'!B31/'Historical Analysis'!C47,0) -> 4.3008817 | D53: =IFERROR('Data Sheet'!C31/'Historical Analysis'!D47,0) -> 5.7511929 | E53: =IFERROR('Data Sheet'!D31/'Historical Analysis'!E47,0) -> 17.103527 | F53: =IFERROR('Data Sheet'!E31/'Historical Analysis'!F47,0) -> 10.002075 | G53: =IFERROR('Data Sheet'!F31/'Historical Analysis'!G47,0) -> 10.002075 | H53: =IFERROR('Data Sheet'!G31/'Historical Analysis'!H47,0) -> 11.002282 | I53: =IFERROR('Data Sheet'!H31/'Historical Analysis'!I47,0) -> 8.7018154 | J53: =IFERROR('Data Sheet'!I31/'Historical Analysis'!J47,0) -> 16.100814 | ... L53: =IFERROR('Data Sheet'!K31/'Historical Analysis'!L47,0) -> 12
B54: Dividend Payout ratio | C54: =C53/C49 -> 0.67680115 | D54: =D53/D49 -> 0.69003006 | E54: =E53/E49 -> 1.6752149 | F54: =F53/F49 -> 0.92603353 | G54: =G53/G49 -> 0.91030537 | H54: =H53/H49 -> 0.88735505 | I54: =I53/I49 -> 0.5594847 | J54: =J53/J49 -> 0.78943461 | ... L54: =L53/L49 -> 0.65281273
C55: =IFERROR(C53/C49,0) -> 0.67680115 | D55: =IFERROR(D53/D49,0) -> 0.69003006 | E55: =IFERROR(E53/E49,0) -> 1.6752149 | F55: =IFERROR(F53/F49,0) -> 0.92603353 | G55: =IFERROR(G53/G49,0) -> 0.91030537 | H55: =IFERROR(H53/H49,0) -> 0.88735505 | I55: =IFERROR(I53/I49,0) -> 0.5594847 | J55: =IFERROR(J53/J49,0) -> 0.78943461 | ... L55: =IFERROR(L53/L49,0) -> 0.65281273
B57: Retained Earning ( Retention Ratio) | C57: =IFERROR(IF(C49>C53,1-C54,0),0) -> 0.32319885 | D57: =IFERROR(IF(D49>D53,1-D54,0),0) -> 0.30996994 | E57: =IFERROR(IF(E49>E53,1-E54,0),0) -> 0 | F57: =IFERROR(IF(F49>F53,1-F54,0),0) -> 0.073966472 | G57: =IFERROR(IF(G49>G53,1-G54,0),0) -> 0.089694629 | H57: =IFERROR(IF(H49>H53,1-H54,0),0) -> 0.11264495 | I57: =IFERROR(IF(I49>I53,1-I54,0),0) -> 0.4405153 | J57: =IFERROR(IF(J49>J53,1-J54,0),0) -> 0.21056539 | ... L57: =IFERROR(IF(L49>L53,1-L54,0),0) -> 0.34718727
C58: =C57+C55 -> 1 | D58: =D57+D55 -> 1 | E58: =E57+E55 -> 1.6752149 | F58: =F57+F55 -> 1 | G58: =G57+G55 -> 1 | H58: =H57+H55 -> 1 | I58: =I57+I55 -> 1 | J58: =J57+J55 -> 1 | ... L58: =L57+L55 -> 1
B59: Retention Ratio | C59: =1-C54 -> 0.32319885 | D59: =1-D54 -> 0.30996994 | E59: =1-E54 -> -0.67521489 | F59: =1-F54 -> 0.073966472 | G59: =1-G54 -> 0.089694629 | H59: =1-H54 -> 0.11264495 | I59: =1-I54 -> 0.4405153 | J59: =1-J54 -> 0.21056539 | ... L59: =1-L54 -> 0.34718727
A61: # | B61: Balance Sheet
B63: Equity Share Capital | C63: =IFERROR('Data Sheet'!B57,0) -> 96.42 | D63: =IFERROR('Data Sheet'!C57,0) -> 96.42 | E63: =IFERROR('Data Sheet'!D57,0) -> 96.42 | F63: =IFERROR('Data Sheet'!E57,0) -> 96.42 | G63: =IFERROR('Data Sheet'!F57,0) -> 96.42 | H63: =IFERROR('Data Sheet'!G57,0) -> 96.42 | I63: =IFERROR('Data Sheet'!H57,0) -> 96.42 | J63: =IFERROR('Data Sheet'!I57,0) -> 96.42 | ... L63: =IFERROR('Data Sheet'!K57,0) -> 192.83
B64: Reserves | C64: =IFERROR('Data Sheet'!B58,0) -> 3324.17 | D64: =IFERROR('Data Sheet'!C58,0) -> 3577.32 | E64: =IFERROR('Data Sheet'!D58,0) -> 1822.45 | F64: =IFERROR('Data Sheet'!E58,0) -> 1922.92 | G64: =IFERROR('Data Sheet'!F58,0) -> 1849.96 | H64: =IFERROR('Data Sheet'!G58,0) -> 2362.75 | I64: =IFERROR('Data Sheet'!H58,0) -> 2362.75 | J64: =IFERROR('Data Sheet'!I58,0) -> 3244.47 | ... L64: =IFERROR('Data Sheet'!K58,0) -> 5116.41
B65: Borrowings | C65: =IFERROR('Data Sheet'!B59,0) -> 35.14 | D65: =IFERROR('Data Sheet'!C59,0) -> 35.14 | E65: =IFERROR('Data Sheet'!D59,0) -> 188.94 | F65: =IFERROR('Data Sheet'!E59,0) -> 147.49 | G65: =IFERROR('Data Sheet'!F59,0) -> 266.46 | H65: =IFERROR('Data Sheet'!G59,0) -> 270.52 | I65: =IFERROR('Data Sheet'!H59,0) -> 270.52 | J65: =IFERROR('Data Sheet'!I59,0) -> 344.53 | ... L65: =IFERROR('Data Sheet'!K59,0) -> 444.16
B66: Other Liabilities | C66: =IFERROR('Data Sheet'!B60,0) -> 3906.86 | D66: =IFERROR('Data Sheet'!C60,0) -> 4379.2 | E66: =IFERROR('Data Sheet'!D60,0) -> 5065.13 | F66: =IFERROR('Data Sheet'!E60,0) -> 5732.9 | G66: =IFERROR('Data Sheet'!F60,0) -> 6021.29 | H66: =IFERROR('Data Sheet'!G60,0) -> 6249.05 | I66: =IFERROR('Data Sheet'!H60,0) -> 6249.05 | J66: =IFERROR('Data Sheet'!I60,0) -> 6837.64 | ... L66: =IFERROR('Data Sheet'!K60,0) -> 7603.77
B67: Total Liablities | C67: =IFERROR('Data Sheet'!B61,0) -> 7362.59 | D67: =IFERROR('Data Sheet'!C61,0) -> 8088.08 | E67: =IFERROR('Data Sheet'!D61,0) -> 7172.94 | F67: =IFERROR('Data Sheet'!E61,0) -> 7899.73 | G67: =IFERROR('Data Sheet'!F61,0) -> 8234.13 | H67: =IFERROR('Data Sheet'!G61,0) -> 8978.74 | I67: =IFERROR('Data Sheet'!H61,0) -> 8978.74 | J67: =IFERROR('Data Sheet'!I61,0) -> 10523.06 | ... L67: =IFERROR('Data Sheet'!K61,0) -> 13357.17
B69: Fixed Assets of net block | C69: =IFERROR('Data Sheet'!B62,0) -> 2616.18 | D69: =IFERROR('Data Sheet'!C62,0) -> 2400.62 | E69: =IFERROR('Data Sheet'!D62,0) -> 2341.45 | F69: =IFERROR('Data Sheet'!E62,0) -> 2179.41 | G69: =IFERROR('Data Sheet'!F62,0) -> 2994.67 | H69: =IFERROR('Data Sheet'!G62,0) -> 3043.7 | I69: =IFERROR('Data Sheet'!H62,0) -> 3043.7 | J69: =IFERROR('Data Sheet'!I62,0) -> 3460.25 | ... L69: =IFERROR('Data Sheet'!K62,0) -> 6290.42
B70: Capital Work in Progress | C70: =IFERROR('Data Sheet'!B63,0) -> 94.16 | D70: =IFERROR('Data Sheet'!C63,0) -> 105.2 | E70: =IFERROR('Data Sheet'!D63,0) -> 143.3 | F70: =IFERROR('Data Sheet'!E63,0) -> 638.58 | G70: =IFERROR('Data Sheet'!F63,0) -> 246.23 | H70: =IFERROR('Data Sheet'!G63,0) -> 358.36 | I70: =IFERROR('Data Sheet'!H63,0) -> 358.36 | J70: =IFERROR('Data Sheet'!I63,0) -> 1741.71 | ... L70: =IFERROR('Data Sheet'!K63,0) -> 506.98
B71: Investments | C71: =IFERROR('Data Sheet'!B64,0) -> 1978.87 | D71: =IFERROR('Data Sheet'!C64,0) -> 2658.49 | E71: =IFERROR('Data Sheet'!D64,0) -> 1751.05 | F71: =IFERROR('Data Sheet'!E64,0) -> 1463.77 | G71: =IFERROR('Data Sheet'!F64,0) -> 773.98 | H71: =IFERROR('Data Sheet'!G64,0) -> 777.54 | I71: =IFERROR('Data Sheet'!H64,0) -> 777.54 | J71: =IFERROR('Data Sheet'!I64,0) -> 463.87 | ... L71: =IFERROR('Data Sheet'!K64,0) -> 705.6
B72: Other Assets | C72: =IFERROR('Data Sheet'!B65-SUM('Data Sheet'!B67:B69),0) -> 224.52 | D72: =IFERROR('Data Sheet'!C65-SUM('Data Sheet'!C67:C69),0) -> 223.57 | E72: =IFERROR('Data Sheet'!D65-SUM('Data Sheet'!D67:D69),0) -> 221.69 | F72: =IFERROR('Data Sheet'!E65-SUM('Data Sheet'!E67:E69),0) -> 266.69 | G72: =IFERROR('Data Sheet'!F65-SUM('Data Sheet'!F67:F69),0) -> 1725.22 | H72: =IFERROR('Data Sheet'!G65-SUM('Data Sheet'!G67:G69),0) -> 1732.93 | I72: =IFERROR('Data Sheet'!H65-SUM('Data Sheet'!H67:H69),0) -> 1732.93 | J72: =IFERROR('Data Sheet'!I65-SUM('Data Sheet'!I67:I69),0) -> 1688.56 | ... L72: =IFERROR('Data Sheet'!K65-SUM('Data Sheet'!K67:K69),0) -> 1614.61
B73: Total Non Current Assets | C73: =SUM(C69:C72) -> 4913.73 | D73: =SUM(D69:D72) -> 5387.88 | E73: =SUM(E69:E72) -> 4457.49 | F73: =SUM(F69:F72) -> 4548.45 | G73: =SUM(G69:G72) -> 5740.1 | H73: =SUM(H69:H72) -> 5912.53 | I73: =SUM(I69:I72) -> 5912.53 | J73: =SUM(J69:J72) -> 7354.39 | ... L73: =SUM(L69:L72) -> 9117.61
B75: Receivables | C75: =IFERROR('Data Sheet'!B67,0) -> 88.97 | D75: =IFERROR('Data Sheet'!C67,0) -> 124.59 | E75: =IFERROR('Data Sheet'!D67,0) -> 124.33 | F75: =IFERROR('Data Sheet'!E67,0) -> 164.93 | G75: =IFERROR('Data Sheet'!F67,0) -> 165.97 | H75: =IFERROR('Data Sheet'!G67,0) -> 191.89 | I75: =IFERROR('Data Sheet'!H67,0) -> 191.89 | J75: =IFERROR('Data Sheet'!I67,0) -> 300.46 | ... L75: =IFERROR('Data Sheet'!K67,0) -> 329.47
B76: Inventory | C76: =IFERROR('Data Sheet'!B68,0) -> 902.47 | D76: =IFERROR('Data Sheet'!C68,0) -> 965.55 | E76: =IFERROR('Data Sheet'!D68,0) -> 1283.07 | F76: =IFERROR('Data Sheet'!E68,0) -> 1416.48 | G76: =IFERROR('Data Sheet'!F68,0) -> 1592.65 | H76: =IFERROR('Data Sheet'!G68,0) -> 1928.77 | I76: =IFERROR('Data Sheet'!H68,0) -> 1928.77 | J76: =IFERROR('Data Sheet'!I68,0) -> 2089.36 | ... L76: =IFERROR('Data Sheet'!K68,0) -> 2569.22
B77: Cash & Bank | C77: =IFERROR('Data Sheet'!B69,0) -> 1457.42 | D77: =IFERROR('Data Sheet'!C69,0) -> 1610.06 | E77: =IFERROR('Data Sheet'!D69,0) -> 1308.05 | F77: =IFERROR('Data Sheet'!E69,0) -> 1769.87 | G77: =IFERROR('Data Sheet'!F69,0) -> 735.41 | H77: =IFERROR('Data Sheet'!G69,0) -> 945.55 | I77: =IFERROR('Data Sheet'!H69,0) -> 945.55 | J77: =IFERROR('Data Sheet'!I69,0) -> 778.85 | ... L77: =IFERROR('Data Sheet'!K69,0) -> 1340.87
B78: Total Current Assets | C78: =SUM(C75:C77) -> 2448.86 | D78: =SUM(D75:D77) -> 2700.2 | E78: =SUM(E75:E77) -> 2715.45 | F78: =SUM(F75:F77) -> 3351.28 | G78: =SUM(G75:G77) -> 2494.03 | H78: =SUM(H75:H77) -> 3066.21 | I78: =SUM(I75:I77) -> 3066.21 | J78: =SUM(J75:J77) -> 3168.67 | ... L78: =SUM(L75:L77) -> 4239.56
B80: Total Assets | C80: =C73+C78 -> 7362.59 | D80: =D73+D78 -> 8088.08 | E80: =E73+E78 -> 7172.94 | F80: =F73+F78 -> 7899.73 | G80: =G73+G78 -> 8234.13 | H80: =H73+H78 -> 8978.74 | I80: =I73+I78 -> 8978.74 | J80: =J73+J78 -> 10523.06 | ... L80: =L73+L78 -> 13357.17
B82: CHECK | C82: =C80=C67 -> TRUE | D82: =D80=D67 -> TRUE | E82: =E80=E67 -> TRUE | F82: =F80=F67 -> TRUE | G82: =G80=G67 -> TRUE | H82: =H80=H67 -> TRUE | I82: =I80=I67 -> TRUE | J82: =J80=J67 -> TRUE | ... L82: =L80=L67 -> TRUE
C83: =IF(C80=C67, "OK", "Error") -> OK | D83: =IF(D80=D67, "OK", "Error") -> OK | E83: =IF(E80=E67, "OK", "Error") -> OK | F83: =IF(F80=F67, "OK", "Error") -> OK | G83: =IF(G80=G67, "OK", "Error") -> OK | H83: =IF(H80=H67, "OK", "Error") -> OK | I83: =IF(I80=I67, "OK", "Error") -> OK | J83: =IF(J80=J67, "OK", "Error") -> OK | ... L83: =IF(L80=L67, "OK", "Error") -> OK
A85: # | B85: Cash Flow Statement
B87: Cash from Operating Activity -
B88: Profit from operations | C88: =IFERROR('Cash Flow Data'!D4,0) -> 1765 | D88: =IFERROR('Cash Flow Data'!E4,0) -> 2047 | E88: =IFERROR('Cash Flow Data'!F4,0) -> 2521 | F88: =IFERROR('Cash Flow Data'!G4,0) -> 2805 | G88: =IFERROR('Cash Flow Data'!H4,0) -> 3061 | H88: =IFERROR('Cash Flow Data'!I4,0) -> 3136 | I88: =IFERROR('Cash Flow Data'!J4,0) -> 3609 | J88: =IFERROR('Cash Flow Data'!K4,0) -> 4388 | ... L88: =IFERROR('Cash Flow Data'!M4,0) -> 4672
B89: Receivables | C89: =IFERROR('Cash Flow Data'!D5,0) -> -19 | D89: =IFERROR('Cash Flow Data'!E5,0) -> 8 | E89: =IFERROR('Cash Flow Data'!F5,0) -> -36 | F89: =IFERROR('Cash Flow Data'!G5,0) -> 0 | G89: =IFERROR('Cash Flow Data'!H5,0) -> -42 | H89: =IFERROR('Cash Flow Data'!I5,0) -> -2 | I89: =IFERROR('Cash Flow Data'!J5,0) -> -28 | J89: =IFERROR('Cash Flow Data'!K5,0) -> -11 | ... L89: =IFERROR('Cash Flow Data'!M5,0) -> -70
B90: Inventory | C90: =IFERROR('Cash Flow Data'!D6,0) -> -119 | D90: =IFERROR('Cash Flow Data'!E6,0) -> 38 | E90: =IFERROR('Cash Flow Data'!F6,0) -> -63 | F90: =IFERROR('Cash Flow Data'!G6,0) -> -318 | G90: =IFERROR('Cash Flow Data'!H6,0) -> -133 | H90: =IFERROR('Cash Flow Data'!I6,0) -> -169 | I90: =IFERROR('Cash Flow Data'!J6,0) -> -336 | J90: =IFERROR('Cash Flow Data'!K6,0) -> 56 | ... L90: =IFERROR('Cash Flow Data'!M6,0) -> -767
B91: Payables | C91: =IFERROR('Cash Flow Data'!D7,0) -> 50 | D91: =IFERROR('Cash Flow Data'!E7,0) -> 185 | E91: =IFERROR('Cash Flow Data'!F7,0) -> 257 | F91: =IFERROR('Cash Flow Data'!G7,0) -> 253 | G91: =IFERROR('Cash Flow Data'!H7,0) -> 23 | H91: =IFERROR('Cash Flow Data'!I7,0) -> 217 | I91: =IFERROR('Cash Flow Data'!J7,0) -> 178 | J91: =IFERROR('Cash Flow Data'!K7,0) -> 68 | ... L91: =IFERROR('Cash Flow Data'!M7,0) -> 134
B92: Loans Advances | C92: =IFERROR('Cash Flow Data'!D8,0) -> 0 | D92: =IFERROR('Cash Flow Data'!E8,0) -> 0 | E92: =IFERROR('Cash Flow Data'!F8,0) -> 0 | F92: =IFERROR('Cash Flow Data'!G8,0) -> 0 | G92: =IFERROR('Cash Flow Data'!H8,0) -> 0 | H92: =IFERROR('Cash Flow Data'!I8,0) -> -40 | I92: =IFERROR('Cash Flow Data'!J8,0) -> -30 | J92: =IFERROR('Cash Flow Data'!K8,0) -> -30 | ... L92: =IFERROR('Cash Flow Data'!M8,0) -> -199
B93: Operating borrowings | C93: =IFERROR('Cash Flow Data'!D9,0) -> 0 | D93: =IFERROR('Cash Flow Data'!E9,0) -> 0 | E93: =IFERROR('Cash Flow Data'!F9,0) -> 0 | F93: =IFERROR('Cash Flow Data'!G9,0) -> 0 | G93: =IFERROR('Cash Flow Data'!H9,0) -> 0 | H93: =IFERROR('Cash Flow Data'!I9,0) -> 0 | I93: =IFERROR('Cash Flow Data'!J9,0) -> 0 | J93: =IFERROR('Cash Flow Data'!K9,0) -> 0 | ... L93: =IFERROR('Cash Flow Data'!M9,0) -> 0
B94: Other WC items | C94: =IFERROR('Cash Flow Data'!D10,0) -> 293 | D94: =IFERROR('Cash Flow Data'!E10,0) -> 144 | E94: =IFERROR('Cash Flow Data'!F10,0) -> 255 | F94: =IFERROR('Cash Flow Data'!G10,0) -> 227 | G94: =IFERROR('Cash Flow Data'!H10,0) -> 249 | H94: =IFERROR('Cash Flow Data'!I10,0) -> -179 | I94: =IFERROR('Cash Flow Data'!J10,0) -> 185 | J94: =IFERROR('Cash Flow Data'!K10,0) -> -19 | ... L94: =IFERROR('Cash Flow Data'!M10,0) -> 155
B95: Direct taxes | C95: =IFERROR('Cash Flow Data'!D11,0) -> 204 | D95: =IFERROR('Cash Flow Data'!E11,0) -> 375 | E95: =IFERROR('Cash Flow Data'!F11,0) -> 413 | F95: =IFERROR('Cash Flow Data'!G11,0) -> 163 | G95: =IFERROR('Cash Flow Data'!H11,0) -> 97 | H95: =IFERROR('Cash Flow Data'!I11,0) -> -172 | I95: =IFERROR('Cash Flow Data'!J11,0) -> -30 | J95: =IFERROR('Cash Flow Data'!K11,0) -> 63 | ... L95: =IFERROR('Cash Flow Data'!M11,0) -> -747
B96: Cash from Operating Activities | C96: =SUM(C87:C95) -> 2174 | D96: =SUM(D87:D95) -> 2797 | E96: =SUM(E87:E95) -> 3347 | F96: =SUM(F87:F95) -> 3130 | G96: =SUM(G87:G95) -> 3255 | H96: =SUM(H87:H95) -> 2791 | I96: =SUM(I87:I95) -> 3548 | J96: =SUM(J87:J95) -> 4515 | ... L96: =SUM(L87:L95) -> 3178
B98: Cash from Investing Activity -
B99: Fixed assets purchased | C99: =IFERROR('Cash Flow Data'!D14,0) -> -207 | D99: =IFERROR('Cash Flow Data'!E14,0) -> -199 | E99: =IFERROR('Cash Flow Data'!F14,0) -> -166 | F99: =IFERROR('Cash Flow Data'!G14,0) -> -155 | G99: =IFERROR('Cash Flow Data'!H14,0) -> -478 | H99: =IFERROR('Cash Flow Data'!I14,0) -> -735 | I99: =IFERROR('Cash Flow Data'!J14,0) -> -550 | J99: =IFERROR('Cash Flow Data'!K14,0) -> -1371 | ... L99: =IFERROR('Cash Flow Data'!M14,0) -> -2009
B100: Fixed assets sold | C100: =IFERROR('Cash Flow Data'!D15,0) -> 94 | D100: =IFERROR('Cash Flow Data'!E15,0) -> 3 | E100: =IFERROR('Cash Flow Data'!F15,0) -> 3 | F100: =IFERROR('Cash Flow Data'!G15,0) -> 2 | G100: =IFERROR('Cash Flow Data'!H15,0) -> 4 | H100: =IFERROR('Cash Flow Data'!I15,0) -> 4 | I100: =IFERROR('Cash Flow Data'!J15,0) -> 9 | J100: =IFERROR('Cash Flow Data'!K15,0) -> 7 | ... L100: =IFERROR('Cash Flow Data'!M15,0) -> 4
B101: Investments purchased | C101: =IFERROR('Cash Flow Data'!D16,0) -> -153 | D101: =IFERROR('Cash Flow Data'!E16,0) -> -112 | E101: =IFERROR('Cash Flow Data'!F16,0) -> -160 | F101: =IFERROR('Cash Flow Data'!G16,0) -> -16 | G101: =IFERROR('Cash Flow Data'!H16,0) -> 0 | H101: =IFERROR('Cash Flow Data'!I16,0) -> 0 | I101: =IFERROR('Cash Flow Data'!J16,0) -> 0 | J101: =IFERROR('Cash Flow Data'!K16,0) -> 0 | ... L101: =IFERROR('Cash Flow Data'!M16,0) -> 0
B102: Investments sold | C102: =IFERROR('Cash Flow Data'!D17,0) -> 0 | D102: =IFERROR('Cash Flow Data'!E17,0) -> 0 | E102: =IFERROR('Cash Flow Data'!F17,0) -> 0 | F102: =IFERROR('Cash Flow Data'!G17,0) -> 0 | G102: =IFERROR('Cash Flow Data'!H17,0) -> 0 | H102: =IFERROR('Cash Flow Data'!I17,0) -> 0 | I102: =IFERROR('Cash Flow Data'!J17,0) -> 25 | J102: =IFERROR('Cash Flow Data'!K17,0) -> 312 | ... L102: =IFERROR('Cash Flow Data'!M17,0) -> 424
B103: Interest received | C103: =IFERROR('Cash Flow Data'!D18,0) -> 126 | D103: =IFERROR('Cash Flow Data'!E18,0) -> 154 | E103: =IFERROR('Cash Flow Data'!F18,0) -> 237 | F103: =IFERROR('Cash Flow Data'!G18,0) -> 238 | G103: =IFERROR('Cash Flow Data'!H18,0) -> 148 | H103: =IFERROR('Cash Flow Data'!I18,0) -> 125 | I103: =IFERROR('Cash Flow Data'!J18,0) -> 103 | J103: =IFERROR('Cash Flow Data'!K18,0) -> 0 | ... L103: =IFERROR('Cash Flow Data'!M18,0) -> 76
B104: Dividends received | C104: =IFERROR('Cash Flow Data'!D19,0) -> 13 | D104: =IFERROR('Cash Flow Data'!E19,0) -> 16 | E104: =IFERROR('Cash Flow Data'!F19,0) -> 19 | F104: =IFERROR('Cash Flow Data'!G19,0) -> 13 | G104: =IFERROR('Cash Flow Data'!H19,0) -> 2 | H104: =IFERROR('Cash Flow Data'!I19,0) -> 0 | I104: =IFERROR('Cash Flow Data'!J19,0) -> 0 | J104: =IFERROR('Cash Flow Data'!K19,0) -> 0 | ... L104: =IFERROR('Cash Flow Data'!M19,0) -> 0
B105: Acquisition of companies | C105: =IFERROR('Cash Flow Data'!D20,0) -> 0 | D105: =IFERROR('Cash Flow Data'!E20,0) -> 0 | E105: =IFERROR('Cash Flow Data'!F20,0) -> 0 | F105: =IFERROR('Cash Flow Data'!G20,0) -> 0 | G105: =IFERROR('Cash Flow Data'!H20,0) -> 0 | H105: =IFERROR('Cash Flow Data'!I20,0) -> 0 | I105: =IFERROR('Cash Flow Data'!J20,0) -> 0 | J105: =IFERROR('Cash Flow Data'!K20,0) -> 0 | ... L105: =IFERROR('Cash Flow Data'!M20,0) -> -706
B106: Other investing items | C106: =IFERROR('Cash Flow Data'!D21,0) -> 1 | D106: =IFERROR('Cash Flow Data'!E21,0) -> 7 | E106: =IFERROR('Cash Flow Data'!F21,0) -> 15 | F106: =IFERROR('Cash Flow Data'!G21,0) -> 0 | G106: =IFERROR('Cash Flow Data'!H21,0) -> 3 | H106: =IFERROR('Cash Flow Data'!I21,0) -> -1314 | I106: =IFERROR('Cash Flow Data'!J21,0) -> 20 | J106: =IFERROR('Cash Flow Data'!K21,0) -> 126 | ... L106: =IFERROR('Cash Flow Data'!M21,0) -> 400
B107: Cash from Investing Activities | C107: =SUM(C99:C106) -> -126 | D107: =SUM(D99:D106) -> -131 | E107: =SUM(E99:E106) -> -52 | F107: =SUM(F99:F106) -> 82 | G107: =SUM(G99:G106) -> -321 | H107: =SUM(H99:H106) -> -1920 | I107: =SUM(I99:I106) -> -393 | J107: =SUM(J99:J106) -> -926 | ... L107: =SUM(L99:L106) -> -1811
B109: Cash from Financing Activity -
B110: Proceeds from borrowings | C110: =IFERROR('Cash Flow Data'!D23,0) -> 0 | D110: =IFERROR('Cash Flow Data'!E23,0) -> 0 | E110: =IFERROR('Cash Flow Data'!F23,0) -> 0 | F110: =IFERROR('Cash Flow Data'!G23,0) -> 0 | G110: =IFERROR('Cash Flow Data'!H23,0) -> 0 | H110: =IFERROR('Cash Flow Data'!I23,0) -> 24 | I110: =IFERROR('Cash Flow Data'!J23,0) -> 0 | J110: =IFERROR('Cash Flow Data'!K23,0) -> 0 | ... L110: =IFERROR('Cash Flow Data'!M23,0) -> 726
B111: Repayment of borrowings | C111: =IFERROR('Cash Flow Data'!D24,0) -> 0 | D111: =IFERROR('Cash Flow Data'!E24,0) -> 0 | E111: =IFERROR('Cash Flow Data'!F24,0) -> 0 | F111: =IFERROR('Cash Flow Data'!G24,0) -> 0 | G111: =IFERROR('Cash Flow Data'!H24,0) -> 0 | H111: =IFERROR('Cash Flow Data'!I24,0) -> -24 | I111: =IFERROR('Cash Flow Data'!J24,0) -> 0 | J111: =IFERROR('Cash Flow Data'!K24,0) -> 0 | ... L111: =IFERROR('Cash Flow Data'!M24,0) -> 0
B112: Investment subsidy | C112: =IFERROR('Cash Flow Data'!D25,0) -> 0 | D112: =IFERROR('Cash Flow Data'!E25,0) -> 0 | E112: =IFERROR('Cash Flow Data'!F25,0) -> 0 | F112: =IFERROR('Cash Flow Data'!G25,0) -> 0 | G112: =IFERROR('Cash Flow Data'!H25,0) -> 0 | H112: =IFERROR('Cash Flow Data'!I25,0) -> 0 | I112: =IFERROR('Cash Flow Data'!J25,0) -> 0 | J112: =IFERROR('Cash Flow Data'!K25,0) -> 0 | ... L112: =IFERROR('Cash Flow Data'!M25,0) -> 0
B113: Interest paid fin | C113: =IFERROR('Cash Flow Data'!D26,0) -> -4 | D113: =IFERROR('Cash Flow Data'!E26,0) -> -1 | E113: =IFERROR('Cash Flow Data'!F26,0) -> -4 | F113: =IFERROR('Cash Flow Data'!G26,0) -> -63 | G113: =IFERROR('Cash Flow Data'!H26,0) -> -69 | H113: =IFERROR('Cash Flow Data'!I26,0) -> -9 | I113: =IFERROR('Cash Flow Data'!J26,0) -> -18 | J113: =IFERROR('Cash Flow Data'!K26,0) -> -20 | ... L113: =IFERROR('Cash Flow Data'!M26,0) -> -34
B114: Dividends paid | C114: =IFERROR('Cash Flow Data'!D27,0) -> -564 | D114: =IFERROR('Cash Flow Data'!E27,0) -> -829 | E114: =IFERROR('Cash Flow Data'!F27,0) -> -1090 | F114: =IFERROR('Cash Flow Data'!G27,0) -> -2950 | G114: =IFERROR('Cash Flow Data'!H27,0) -> -1890 | H114: =IFERROR('Cash Flow Data'!I27,0) -> -1928 | I114: =IFERROR('Cash Flow Data'!J27,0) -> -2025 | J114: =IFERROR('Cash Flow Data'!K27,0) -> -2333 | ... L114: =IFERROR('Cash Flow Data'!M27,0) -> -2459
B115: Financial liabilities | C115: =IFERROR('Cash Flow Data'!D28,0) -> 0 | D115: =IFERROR('Cash Flow Data'!E28,0) -> 0 | E115: =IFERROR('Cash Flow Data'!F28,0) -> 0 | F115: =IFERROR('Cash Flow Data'!G28,0) -> 0 | G115: =IFERROR('Cash Flow Data'!H28,0) -> 0 | H115: =IFERROR('Cash Flow Data'!I28,0) -> -79 | I115: =IFERROR('Cash Flow Data'!J28,0) -> -73 | J115: =IFERROR('Cash Flow Data'!K28,0) -> -166 | ... L115: =IFERROR('Cash Flow Data'!M28,0) -> -76
B116: Other financing items | C116: =IFERROR('Cash Flow Data'!D29,0) -> -98 | D116: =IFERROR('Cash Flow Data'!E29,0) -> -167 | E116: =IFERROR('Cash Flow Data'!F29,0) -> -224 | F116: =IFERROR('Cash Flow Data'!G29,0) -> -588 | G116: =IFERROR('Cash Flow Data'!H29,0) -> 3 | H116: =IFERROR('Cash Flow Data'!I29,0) -> -3 | I116: =IFERROR('Cash Flow Data'!J29,0) -> -7 | J116: =IFERROR('Cash Flow Data'!K29,0) -> 83 | ... L116: =IFERROR('Cash Flow Data'!M29,0) -> -4
B117: Cash from Financial Activities | C117: =SUM(C110:C116) -> -666 | D117: =SUM(D110:D116) -> -997 | E117: =SUM(E110:E116) -> -1318 | F117: =SUM(F110:F116) -> -3601 | G117: =SUM(G110:G116) -> -1956 | H117: =SUM(H110:H116) -> -2019 | I117: =SUM(I110:I116) -> -2123 | J117: =SUM(J110:J116) -> -2436 | ... L117: =SUM(L110:L116) -> -1847
A120: # | B120: Net Cash Flow | C120: =IFERROR(C96+C107+C117,0) -> 1382 | D120: =IFERROR(D96+D107+D117,0) -> 1669 | E120: =IFERROR(E96+E107+E117,0) -> 1977 | F120: =IFERROR(F96+F107+F117,0) -> -389 | G120: =IFERROR(G96+G107+G117,0) -> 978 | H120: =IFERROR(H96+H107+H117,0) -> -1148 | I120: =IFERROR(I96+I107+I117,0) -> 1032 | J120: =IFERROR(J96+J107+J117,0) -> 1153 | ... L120: =IFERROR(L96+L107+L117,0) -> -480

Sheet Ratio Analysis
B7: =" Ratio Analysis - "&'Data Sheet'!B1 -> Ratio Analysis - NESTLE INDIA LTD
B8: Year | C8: ='Data Sheet'!B16 -> 43100 | D8: ='Data Sheet'!C16 -> 43465 | E8: ='Data Sheet'!D16 -> 43830 | F8: ='Data Sheet'!E16 -> 44196 | G8: ='Data Sheet'!F16 -> 44561 | H8: ='Data Sheet'!G16 -> 44926 | I8: ='Data Sheet'!H16 -> 45291 | J8: ='Data Sheet'!I16 -> 45382 | ... L8: ='Data Sheet'!K16 -> 46112 | M8: Trend Analysis | N8: Mean | O8: Median
B10: SalesGrowth | D10: =IFERROR('Historical Analysis'!D12,0) -> 0.12814398 | E10: =IFERROR('Historical Analysis'!E12,0) -> 0.095342212 | F10: =IFERROR('Historical Analysis'!F12,0) -> 0.079322333 | G10: =IFERROR('Historical Analysis'!G12,0) -> 0.10416156 | H10: =IFERROR('Historical Analysis'!H12,0) -> 0.1462879 | I10: =IFERROR('Historical Analysis'!I12,0) -> 0.13193734 | J10: =IFERROR('Historical Analysis'!J12,0) -> 0.27541082 | K10: =IFERROR('Historical Analysis'!K12,0) -> -0.17185984 | L10: =IFERROR('Historical Analysis'!L12,0) -> 0.14617881 | N10: =IFERROR(AVERAGE(D10:L10),0) -> 0.10388057 | O10: =MEDIAN(D10:L10) -> 0.12814398
B11: EBITDA Growth | D11: =IFERROR('Historical Analysis'!D23/'Historical Analysis'!C23-1,0) -> 0.2485631 | E11: =IFERROR('Historical Analysis'!E23/'Historical Analysis'!D23-1,0) -> 0.11775065 | F11: =IFERROR('Historical Analysis'!F23/'Historical Analysis'!E23-1,0) -> 0.094200719 | G11: =IFERROR('Historical Analysis'!G23/'Historical Analysis'!F23-1,0) -> 0.11272841 | H11: =IFERROR('Historical Analysis'!H23/'Historical Analysis'!G23-1,0) -> 0.040391309 | I11: =IFERROR('Historical Analysis'!I23/'Historical Analysis'!H23-1,0) -> 0.20632492 | J11: =IFERROR('Historical Analysis'!J23/'Historical Analysis'!I23-1,0) -> 0.30689624 | K11: =IFERROR('Historical Analysis'!K23/'Historical Analysis'!J23-1,0) -> -0.18342769 | L11: =IFERROR('Historical Analysis'!L23/'Historical Analysis'!K23-1,0) -> 0.1122601 | N11: =IFERROR(AVERAGE(D11:L11),0) -> 0.11729864 | O11: =MEDIAN(D11:L11) -> 0.11272841
B12: EBIT Growth | D12: =IFERROR('Historical Analysis'!D31/'Historical Analysis'!C31-1,0) -> 0.31571044 | E12: =IFERROR('Historical Analysis'!E31/'Historical Analysis'!D31-1,0) -> 0.10299894 | F12: =IFERROR('Historical Analysis'!F31/'Historical Analysis'!E31-1,0) -> 0.062213437 | G12: =IFERROR('Historical Analysis'!G31/'Historical Analysis'!F31-1,0) -> 0.027554863 | H12: =IFERROR('Historical Analysis'!H31/'Historical Analysis'!G31-1,0) -> 0.11491991 | I12: =IFERROR('Historical Analysis'!I31/'Historical Analysis'!H31-1,0) -> 0.21903863 | J12: =IFERROR('Historical Analysis'!J31/'Historical Analysis'!I31-1,0) -> 0.30709692 | K12: =IFERROR('Historical Analysis'!K31/'Historical Analysis'!J31-1,0) -> -0.15657594 | L12: =IFERROR('Historical Analysis'!L31/'Historical Analysis'!K31-1,0) -> 0.040251163 | N12: =IFERROR(AVERAGE(D12:L12),0) -> 0.11480093 | O12: =MEDIAN(D12:L12) -> 0.10299894
B13: Net Profit Growth | D13: =IFERROR('Historical Analysis'!D44/'Historical Analysis'!C44-1,0) -> 0.31157616 | E13: =IFERROR('Historical Analysis'!E44/'Historical Analysis'!D44-1,0) -> 0.22496935 | F13: =IFERROR('Historical Analysis'!F44/'Historical Analysis'!E44-1,0) -> 0.057908801 | G13: =IFERROR('Historical Analysis'!G44/'Historical Analysis'!F44-1,0) -> 0.017277892 | H13: =IFERROR('Historical Analysis'!H44/'Historical Analysis'!G44-1,0) -> 0.12845011 | I13: =IFERROR('Historical Analysis'!I44/'Historical Analysis'!H44-1,0) -> 0.25440072 | J13: =IFERROR('Historical Analysis'!J44/'Historical Analysis'!I44-1,0) -> 0.31152811 | K13: =IFERROR('Historical Analysis'!K44/'Historical Analysis'!J44-1,0) -> -0.1572248 | L13: =IFERROR('Historical Analysis'!L44/'Historical Analysis'!K44-1,0) -> 0.069422236 | N13: =IFERROR(AVERAGE(D13:L13),0) -> 0.13536762 | O13: =MEDIAN(D13:L13) -> 0.12845011
B14: Dividend Growth | D14: =IFERROR('Historical Analysis'!D53/'Historical Analysis'!C53-1,0) -> 0.33721253 | E14: =IFERROR('Historical Analysis'!E53/'Historical Analysis'!D53-1,0) -> 1.9739094 | F14: =IFERROR('Historical Analysis'!F53/'Historical Analysis'!E53-1,0) -> -0.41520397 | G14: =IFERROR('Historical Analysis'!G53/'Historical Analysis'!F53-1,0) -> 0 | H14: =IFERROR('Historical Analysis'!H53/'Historical Analysis'!G53-1,0) -> 0.1 | I14: =IFERROR('Historical Analysis'!I53/'Historical Analysis'!H53-1,0) -> -0.20908997 | J14: =IFERROR('Historical Analysis'!J53/'Historical Analysis'!I53-1,0) -> 0.85028222 | K14: =IFERROR('Historical Analysis'!K53/'Historical Analysis'!J53-1,0) -> -0.1614896 | L14: =IFERROR('Historical Analysis'!L53/'Historical Analysis'!K53-1,0) -> -0.11115721 | N14: =IFERROR(AVERAGE(D14:L14),0) -> 0.26271816
B16: Gross Margin | C16: =IFERROR('Historical Analysis'!C16/'Historical Analysis'!C11,0) -> 0.4184423 | D16: =IFERROR('Historical Analysis'!D16/'Historical Analysis'!D11,0) -> 0.44728562 | E16: =IFERROR('Historical Analysis'!E16/'Historical Analysis'!E11,0) -> 0.4337435 | F16: =IFERROR('Historical Analysis'!F16/'Historical Analysis'!F11,0) -> 0.42416609 | G16: =IFERROR('Historical Analysis'!G16/'Historical Analysis'!G11,0) -> 0.42192612 | H16: =IFERROR('Historical Analysis'!H16/'Historical Analysis'!H11,0) -> 0.39505686 | I16: =IFERROR('Historical Analysis'!I16/'Historical Analysis'!I11,0) -> 0.46242138 | J16: =IFERROR('Historical Analysis'!J16/'Historical Analysis'!J11,0) -> 0.4219159 | ... L16: =IFERROR('Historical Analysis'!L16/'Historical Analysis'!L11,0) -> 0.41144999 | N16: =IFERROR(AVERAGE(C16:L16),0) -> 0.4257598 | O16: =MEDIAN(C16:L16) -> 0.42192101
B17: EBITDA Margin | C17: =IFERROR('Historical Analysis'!C24,0) -> 0.20945193 | D17: =IFERROR('Historical Analysis'!D24,0) -> 0.23180902 | E17: =IFERROR('Historical Analysis'!E24,0) -> 0.23655135 | F17: =IFERROR('Historical Analysis'!F24,0) -> 0.2398122 | G17: =IFERROR('Historical Analysis'!G24,0) -> 0.24167282 | H17: =IFERROR('Historical Analysis'!H24,0) -> 0.21934656 | I17: =IFERROR('Historical Analysis'!I24,0) -> 0.23376137 | J17: =IFERROR('Historical Analysis'!J24,0) -> 0.23953211 | ... L17: =IFERROR('Historical Analysis'!L24,0) -> 0.22919679 | N17: =IFERROR(AVERAGE(C17:L17),0) -> 0.23173204 | O17: =MEDIAN(C17:L17) -> 0.23497379
B18: EBIT Margin | C18: =IFERROR('Historical Analysis'!C31/'Historical Analysis'!C11,0) -> 0.19293478 | D18: =IFERROR('Historical Analysis'!D31/'Historical Analysis'!D11,0) -> 0.22501233 | E18: =IFERROR('Historical Analysis'!E31/'Historical Analysis'!E11,0) -> 0.22658523 | F18: =IFERROR('Historical Analysis'!F31/'Historical Analysis'!F11,0) -> 0.22299351 | G18: =IFERROR('Historical Analysis'!G31/'Historical Analysis'!G11,0) -> 0.20752222 | H18: =IFERROR('Historical Analysis'!H31/'Historical Analysis'!H11,0) -> 0.20184341 | I18: =IFERROR('Historical Analysis'!I31/'Historical Analysis'!I11,0) -> 0.21737503 | J18: =IFERROR('Historical Analysis'!J31/'Historical Analysis'!J11,0) -> 0.22277546 | ... L18: =IFERROR('Historical Analysis'!L31/'Historical Analysis'!L11,0) -> 0.20591848 | N18: =IFERROR(AVERAGE(C18:L18),0) -> 0.21498474 | O18: =MEDIAN(C18:L18) -> 0.22007524
B19: EBT Margin (TAX ) | C19: =IFERROR('Historical Analysis'!C38,0) -> 0.1837536 | D19: =IFERROR('Historical Analysis'!D38,0) -> 0.21509847 | E19: =IFERROR('Historical Analysis'!E38,0) -> 0.21614614 | F19: =IFERROR('Historical Analysis'!F38,0) -> 0.21069541 | G19: =IFERROR('Historical Analysis'!G38,0) -> 0.19384027 | H19: =IFERROR('Historical Analysis'!H38,0) -> 0.19269561 | I19: =IFERROR('Historical Analysis'!I38,0) -> 0.21113807 | J19: =IFERROR('Historical Analysis'!J38,0) -> 0.21681126 | ... L19: =IFERROR('Historical Analysis'!L38,0) -> 0.19908139 | N19: =IFERROR(AVERAGE(C19:L19),0) -> 0.2059415 | O19: =MEDIAN(C19:L19) -> 0.21091674
B20: Net Profit Margin | C20: =IFERROR('Historical Analysis'!C45,0) -> 0.12240149 | D20: =IFERROR('Historical Analysis'!D45,0) -> 0.14230354 | E20: =IFERROR('Historical Analysis'!E45,0) -> 0.15914431 | F20: =IFERROR('Historical Analysis'!F45,0) -> 0.15598692 | G20: =IFERROR('Historical Analysis'!G45,0) -> 0.1437127 | H20: =IFERROR('Historical Analysis'!H45,0) -> 0.14147634 | I20: =IFERROR('Historical Analysis'!I45,0) -> 0.15678255 | J20: =IFERROR('Historical Analysis'!J45,0) -> 0.16122234 | ... L20: =IFERROR('Historical Analysis'!L45,0) -> 0.15308405 | N20: =IFERROR(AVERAGE(C20:L20),0) -> 0.15001857 | O20: =MEDIAN(C20:L20) -> 0.15453548
B22: SalesExpenses%Sales ( S& G Margin) | C22: =IFERROR('Historical Analysis'!C19,0) -> 0.18222307 | D22: =IFERROR('Historical Analysis'!D19,0) -> 0.19002557 | E22: =IFERROR('Historical Analysis'!E19,0) -> 0.17997801 | F22: =IFERROR('Historical Analysis'!F19,0) -> 0.16830674 | G22: =IFERROR('Historical Analysis'!G19,0) -> 0.1968795 | H22: =IFERROR('Historical Analysis'!H19,0) -> 0.1889186 | I22: =IFERROR('Historical Analysis'!I19,0) -> 0 | J22: =IFERROR('Historical Analysis'!J19,0) -> 0.19831113 | ... L22: =IFERROR('Historical Analysis'!L19,0) -> 0.20647733 | N22: =IFERROR(AVERAGE(C22:L22),0) -> 0.17153883 | O22: =MEDIAN(C22:L22) -> 0.18947208
B23: Depreciation%Sales | C23: =IFERROR('Historical Analysis'!C29,0) -> 0.034192176 | D23: =IFERROR('Historical Analysis'!D29,0) -> 0.029725644 | E23: =IFERROR('Historical Analysis'!E29,0) -> 0.029925862 | F23: =IFERROR('Historical Analysis'!F29,0) -> 0.027743758 | G23: =IFERROR('Historical Analysis'!G29,0) -> 0.026526754 | H23: =IFERROR('Historical Analysis'!H29,0) -> 0.023851036 | I23: =IFERROR('Historical Analysis'!I29,0) -> 0.022425142 | J23: =IFERROR('Historical Analysis'!J29,0) -> 0.023274271 | ... L23: =IFERROR('Historical Analysis'!L29,0) -> 0.030198319 | N23: =IFERROR(AVERAGE(C23:L23),0) -> 0.027458961 | O23: =MEDIAN(C23:L23) -> 0.027235203
B24: OperatingIncome%Sales | C24: =C18 -> 0.19293478 | D24: =D18 -> 0.22501233 | E24: =E18 -> 0.22658523 | F24: =F18 -> 0.22299351 | G24: =G18 -> 0.20752222 | H24: =H18 -> 0.20184341 | I24: =I18 -> 0.21737503 | J24: =J18 -> 0.22277546 | ... L24: =L18 -> 0.20591848 | N24: =IFERROR(AVERAGE(C24:L24),0) -> 0.21498474 | O24: =MEDIAN(C24:L24) -> 0.22007524
B26: Return on Capital Employed | C26: =IFERROR('Historical Analysis'!C31/SUM('Historical Analysis'!C63:C65),0) -> 0.55883996 | D26: =IFERROR('Historical Analysis'!D31/SUM('Historical Analysis'!D63:D65),0) -> 0.68508552 | E26: =IFERROR('Historical Analysis'!E31/SUM('Historical Analysis'!E63:E65),0) -> 1.3296312 | F26: =IFERROR('Historical Analysis'!F31/SUM('Historical Analysis'!F63:F65),0) -> 1.3738826 | G26: =IFERROR('Historical Analysis'!G31/SUM('Historical Analysis'!G63:G65),0) -> 1.3823864 | H26: =IFERROR('Historical Analysis'!H31/SUM('Historical Analysis'!H63:H65),0) -> 1.2494239 | I26: =IFERROR('Historical Analysis'!I31/SUM('Historical Analysis'!I63:I65),0) -> 1.523096 | J26: =IFERROR('Historical Analysis'!J31/SUM('Historical Analysis'!J63:J65),0) -> 1.4745565 | ... L26: =IFERROR('Historical Analysis'!L31/SUM('Historical Analysis'!L63:L65),0) -> 0.82872041 | N26: =IFERROR(AVERAGE(C26:L26),0) -> 1.1273047 | O26: =MEDIAN(C26:L26) -> 1.2895276
B27: Retained Earnings% | C27: =IFERROR('Historical Analysis'!C57,0) -> 0.32319885 | D27: =IFERROR('Historical Analysis'!D57,0) -> 0.30996994 | E27: =IFERROR('Historical Analysis'!E57,0) -> 0 | F27: =IFERROR('Historical Analysis'!F57,0) -> 0.073966472 | G27: =IFERROR('Historical Analysis'!G57,0) -> 0.089694629 | H27: =IFERROR('Historical Analysis'!H57,0) -> 0.11264495 | I27: =IFERROR('Historical Analysis'!I57,0) -> 0.4405153 | J27: =IFERROR('Historical Analysis'!J57,0) -> 0.21056539 | ... L27: =IFERROR('Historical Analysis'!L57,0) -> 0.34718727 | N27: =IFERROR(AVERAGE(C27:L27),0) -> 0.21223031 | O27: =MEDIAN(C27:L27) -> 0.21256283
B28: Return on Equity% | C28: =IFERROR('Historical Analysis'!C44/SUM('Historical Analysis'!C63:C64),0) -> 0.3581809 | D28: =IFERROR('Historical Analysis'!D44/SUM('Historical Analysis'!D63:D64),0) -> 0.43740983 | E28: =IFERROR('Historical Analysis'!E44/SUM('Historical Analysis'!E63:E64),0) -> 1.0258329 | F28: =IFERROR('Historical Analysis'!F44/SUM('Historical Analysis'!F63:F64),0) -> 1.0312429 | G28: =IFERROR('Historical Analysis'!G44/SUM('Historical Analysis'!G63:G64),0) -> 1.0883846 | H28: =IFERROR('Historical Analysis'!H44/SUM('Historical Analysis'!H63:H64),0) -> 0.97208408 | I28: =IFERROR('Historical Analysis'!I44/SUM('Historical Analysis'!I63:I64),0) -> 1.219383 | J28: =IFERROR('Historical Analysis'!J44/SUM('Historical Analysis'!J63:J64),0) -> 1.1771833 | K28: =IFERROR('Historical Analysis'!K44/SUM('Historical Analysis'!K63:K64),0) -> 0.80504718 | L28: =IFERROR('Historical Analysis'!L44/'Historical Analysis'!L63,0) -> 18.381995 | N28: =IFERROR(AVERAGE(C28:L28),0) -> 2.6496743 | O28: =MEDIAN(C28:L28) -> 1.0285379
B29: Self Sustained Growth Rate | C29: =IFERROR(C28*(1-'Historical Analysis'!C54),0) -> 0.11576365 | D29: =IFERROR(D28*(1-'Historical Analysis'!D54),0) -> 0.1355839 | E29: =IFERROR(E28*(1-'Historical Analysis'!E54),0) -> -0.69265766 | F29: =IFERROR(F28*(1-'Historical Analysis'!F54),0) -> 0.076277398 | G29: =IFERROR(G28*(1-'Historical Analysis'!G54),0) -> 0.097622253 | H29: =IFERROR(H28*(1-'Historical Analysis'!H54),0) -> 0.10950036 | I29: =IFERROR(I28*(1-'Historical Analysis'!I54),0) -> 0.53715685 | J29: =IFERROR(J28*(1-'Historical Analysis'!J54),0) -> 0.24787407 | ... L29: =IFERROR(L28*(1-'Historical Analysis'!L54),0) -> 6.3819945 | N29: =IFERROR(AVERAGE(C29:L29),0) -> 0.71818465 | O29: =MEDIAN(C29:L29) -> 0.12567378
B30: Interest Coverage Ratio ( Ctrl1> custom>0.0"X" | C30: =IFERROR('Historical Analysis'!C31/'Historical Analysis'!C33,0) -> 21.014146 | D30: =IFERROR('Historical Analysis'!D31/'Historical Analysis'!D33,0) -> 22.69674 | E30: =IFERROR('Historical Analysis'!E31/'Historical Analysis'!E33,0) -> 21.705468 | F30: =IFERROR('Historical Analysis'!F31/'Historical Analysis'!F33,0) -> 18.132355 | G30: =IFERROR('Historical Analysis'!G31/'Historical Analysis'!G33,0) -> 15.167592 | H30: =IFERROR('Historical Analysis'!H31/'Historical Analysis'!H33,0) -> 22.064696 | I30: =IFERROR('Historical Analysis'!I31/'Historical Analysis'!I33,0) -> 34.852712 | J30: =IFERROR('Historical Analysis'!J31/'Historical Analysis'!J33,0) -> 37.35212 | ... L30: =IFERROR('Historical Analysis'!L31/'Historical Analysis'!L33,0) -> 30.11787 | N30: =IFERROR(AVERAGE(C30:L30),0) -> 25.680568 | O30: =MEDIAN(C30:L30) -> 22.380718
B31: Self Sustained Growth Rate | C31: =C28*C27 -> 0.11576365 | D31: =D28*D27 -> 0.1355839 | E31: =E28*E27 -> 0 | F31: =F28*F27 -> 0.076277398 | G31: =G28*G27 -> 0.097622253 | H31: =H28*H27 -> 0.10950036 | I31: =I28*I27 -> 0.53715685 | J31: =J28*J27 -> 0.24787407 | ... L31: =L28*L27 -> 6.3819945 | N31: =IFERROR(AVERAGE(C31:L31),0) -> 0.78745041 | O31: =MEDIAN(C31:L31) -> 0.12567378
B33: Debtor Turnover Ratio X - Times payment recived | C33: =IFERROR('Historical Analysis'!C11/'Historical Analysis'!C75,0) -> 112.50534 | D33: =IFERROR('Historical Analysis'!D11/'Historical Analysis'!D75,0) -> 90.635444 | E33: =IFERROR('Historical Analysis'!E11/'Historical Analysis'!E75,0) -> 99.484437 | F33: =IFERROR('Historical Analysis'!F11/'Historical Analysis'!F75,0) -> 80.943612 | G33: =IFERROR('Historical Analysis'!G11/'Historical Analysis'!G75,0) -> 88.814786 | H33: =IFERROR('Historical Analysis'!H11/'Historical Analysis'!H75,0) -> 88.055448 | I33: =IFERROR('Historical Analysis'!I11/'Historical Analysis'!I75,0) -> 99.67325 | J33: =IFERROR('Historical Analysis'!J11/'Historical Analysis'!J75,0) -> 81.188478 | ... L33: =IFERROR('Historical Analysis'!L11/'Historical Analysis'!L75,0) -> 70.278326 | N33: =IFERROR(AVERAGE(C33:L33),0) -> 86.720781 | O33: =MEDIAN(C33:L33) -> 88.435117
B34: Creditor Turnover Ratio | C34: =IFERROR('Historical Analysis'!C11/'Historical Analysis'!C66,0) -> 2.5620575 | D34: =IFERROR('Historical Analysis'!D11/'Historical Analysis'!D66,0) -> 2.5786148 | E34: =IFERROR('Historical Analysis'!E11/'Historical Analysis'!E66,0) -> 2.4419709 | F34: =IFERROR('Historical Analysis'!F11/'Historical Analysis'!F66,0) -> 2.3286696 | G34: =IFERROR('Historical Analysis'!G11/'Historical Analysis'!G66,0) -> 2.4480784 | H34: =IFERROR('Historical Analysis'!H11/'Historical Analysis'!H66,0) -> 2.7039246 | I34: =IFERROR('Historical Analysis'!I11/'Historical Analysis'!I66,0) -> 3.0606732 | J34: =IFERROR('Historical Analysis'!J11/'Historical Analysis'!J66,0) -> 3.5675891 | ... L34: =IFERROR('Historical Analysis'!L11/'Historical Analysis'!L66,0) -> 3.0451473 | N34: =IFERROR(AVERAGE(C34:L34),0) -> 2.760631 | O34: =MEDIAN(C34:L34) -> 2.6412697
B35: Inventory Turnover | C35: =IFERROR('Historical Analysis'!C11/'Historical Analysis'!C76,0) -> 11.091338 | D35: =IFERROR('Historical Analysis'!D11/'Historical Analysis'!D76,0) -> 11.695169 | E35: =IFERROR('Historical Analysis'!E11/'Historical Analysis'!E76,0) -> 9.640082 | F35: =IFERROR('Historical Analysis'!F11/'Historical Analysis'!F76,0) -> 9.4247924 | G35: =IFERROR('Historical Analysis'!G11/'Historical Analysis'!G76,0) -> 9.2553857 | H35: =IFERROR('Historical Analysis'!H11/'Historical Analysis'!H76,0) -> 8.7604847 | I35: =IFERROR('Historical Analysis'!I11/'Historical Analysis'!I76,0) -> 9.9163197 | J35: =IFERROR('Historical Analysis'!J11/'Historical Analysis'!J76,0) -> 11.675293 | ... L35: =IFERROR('Historical Analysis'!L11/'Historical Analysis'!L76,0) -> 9.0123072 | N35: =IFERROR(AVERAGE(C35:L35),0) -> 9.755909 | O35: =MEDIAN(C35:L35) -> 9.5324372
B36: Fixed Asset Turnover | C36: =IFERROR('Historical Analysis'!C11/'Historical Analysis'!C69,0) -> 3.8260364 | D36: =IFERROR('Historical Analysis'!D11/'Historical Analysis'!D69,0) -> 4.7038973 | E36: =IFERROR('Historical Analysis'!E11/'Historical Analysis'!E69,0) -> 5.2825813 | F36: =IFERROR('Historical Analysis'!F11/'Historical Analysis'!F69,0) -> 6.1255248 | G36: =IFERROR('Historical Analysis'!G11/'Historical Analysis'!G69,0) -> 4.9222752 | H36: =IFERROR('Historical Analysis'!H11/'Historical Analysis'!H69,0) -> 5.5514538 | I36: =IFERROR('Historical Analysis'!I11/'Historical Analysis'!I69,0) -> 6.2838979 | J36: =IFERROR('Historical Analysis'!J11/'Historical Analysis'!J69,0) -> 7.0497479 | ... L36: =IFERROR('Historical Analysis'!L11/'Historical Analysis'!L69,0) -> 3.6809307 | N36: =IFERROR(AVERAGE(C36:L36),0) -> 5.1117065 | O36: =MEDIAN(C36:L36) -> 5.1024283
B37: Capital Turnover Ratio | C37: =IFERROR('Historical Analysis'!C11/SUM('Historical Analysis'!C63:C64),0) -> 2.9262788 | D37: =IFERROR('Historical Analysis'!D11/SUM('Historical Analysis'!D63:D64),0) -> 3.0737804 | E37: =IFERROR('Historical Analysis'!E11/SUM('Historical Analysis'!E63:E64),0) -> 6.4459291 | F37: =IFERROR('Historical Analysis'!F11/SUM('Historical Analysis'!F63:F64),0) -> 6.6110858 | G37: =IFERROR('Historical Analysis'!G11/SUM('Historical Analysis'!G63:G64),0) -> 7.5733361 | H37: =IFERROR('Historical Analysis'!H11/SUM('Historical Analysis'!H63:H64),0) -> 6.8710012 | I37: =IFERROR('Historical Analysis'!I11/SUM('Historical Analysis'!I63:I64),0) -> 7.7775428 | J37: =IFERROR('Historical Analysis'!J11/SUM('Historical Analysis'!J63:J64),0) -> 7.3016142 | ... L37: =IFERROR('Historical Analysis'!L11/SUM('Historical Analysis'!L63:L64),0) -> 4.3611892 | N37: =IFERROR(AVERAGE(C37:L37),0) -> 5.7848443 | O37: =MEDIAN(C37:L37) -> 6.5285075
B39: In Days
B40: Debtor Days ( Recievables) | C40: =IFERROR(365/C33,0) -> 3.2442905 | D40: =IFERROR(365/D33,0) -> 4.0271221 | E40: =IFERROR(365/E33,0) -> 3.6689156 | F40: =IFERROR(365/F33,0) -> 4.509312 | G40: =IFERROR(365/G33,0) -> 4.1096761 | H40: =IFERROR(365/H33,0) -> 4.1451155 | I40: =IFERROR(365/I33,0) -> 3.6619655 | J40: =IFERROR(365/J33,0) -> 4.4957118 | ... L40: =IFERROR(365/L33,0) -> 5.1936354 | N40: =IFERROR(AVERAGE(C40:L40),0) -> 4.3617106 | O40: =MEDIAN(C40:L40) -> 4.1273958
B41: Payable Days ( Creditors) | C41: =IFERROR(365/C34,0) -> 142.46362 | D41: =IFERROR(365/D34,0) -> 141.54886 | E41: =IFERROR(365/E34,0) -> 149.46943 | F41: =IFERROR(365/F34,0) -> 156.74186 | G41: =IFERROR(365/G34,0) -> 149.09653 | H41: =IFERROR(365/H34,0) -> 134.98897 | I41: =IFERROR(365/I34,0) -> 119.25481 | J41: =IFERROR(365/J34,0) -> 102.30999 | ... L41: =IFERROR(365/L34,0) -> 119.86284 | N41: =IFERROR(AVERAGE(C41:L41),0) -> 134.2933 | O41: =MEDIAN(C41:L41) -> 138.26892
B42: Inventory Days | C42: =IFERROR(365/C35,0) -> 32.908563 | D42: =IFERROR(365/D35,0) -> 31.209469 | E42: =IFERROR(365/E35,0) -> 37.862749 | F42: =IFERROR(365/F35,0) -> 38.727643 | G42: =IFERROR(365/G35,0) -> 39.436498 | H42: =IFERROR(365/H35,0) -> 41.664362 | I42: =IFERROR(365/I35,0) -> 36.80801 | J42: =IFERROR(365/J35,0) -> 31.262599 | ... L42: =IFERROR(365/L35,0) -> 40.500173 | N42: =IFERROR(AVERAGE(C42:L42),0) -> 38.187614 | O42: =MEDIAN(C42:L42) -> 38.295196
B43: Cash Conversion Cycle (in days) | C43: =SUM(C42,C40)-C41 -> -106.31077 | D43: =SUM(D42,D40)-D41 -> -106.31227 | E43: =SUM(E42,E40)-E41 -> -107.93777 | F43: =SUM(F42,F40)-F41 -> -113.5049 | G43: =SUM(G42,G40)-G41 -> -105.55036 | H43: =SUM(H42,H40)-H41 -> -89.179494 | I43: =SUM(I42,I40)-I41 -> -78.784833 | J43: =SUM(J42,J40)-J41 -> -66.551677 | ... L43: =SUM(L42,L40)-L41 -> -74.169029 | N43: =IFERROR(AVERAGE(C43:L43),0) -> -91.743978 | O43: =MEDIAN(C43:L43) -> -97.364926
B45: Cash from Operations - Cash flow
B46: CFO/Sales | C46: =IFERROR('Historical Analysis'!C96/'Historical Analysis'!C11,0) -> 0.2171915 | D46: =IFERROR('Historical Analysis'!D96/'Historical Analysis'!D11,0) -> 0.24769156 | E46: =IFERROR('Historical Analysis'!E96/'Historical Analysis'!E11,0) -> 0.27059803 | F46: =IFERROR('Historical Analysis'!F96/'Historical Analysis'!F11,0) -> 0.2344564 | G46: =IFERROR('Historical Analysis'!G96/'Historical Analysis'!G11,0) -> 0.22081884 | H46: =IFERROR('Historical Analysis'!H96/'Historical Analysis'!H11,0) -> 0.16517764 | I46: =IFERROR('Historical Analysis'!I96/'Historical Analysis'!I11,0) -> 0.18550373 | J46: =IFERROR('Historical Analysis'!J96/'Historical Analysis'!J11,0) -> 0.18508733 | ... L46: =IFERROR('Historical Analysis'!L96/'Historical Analysis'!L11,0) -> 0.13725135 | N46: =IFERROR(AVERAGE(C46:L46),0) -> 0.21223703 | O46: =MEDIAN(C46:L46) -> 0.21900517
B47: CFO/Total Assets | C47: =IFERROR('Historical Analysis'!C96/'Historical Analysis'!C80,0) -> 0.29527653 | D47: =IFERROR('Historical Analysis'!D96/'Historical Analysis'!D80,0) -> 0.34581755 | E47: =IFERROR('Historical Analysis'!E96/'Historical Analysis'!E80,0) -> 0.46661481 | F47: =IFERROR('Historical Analysis'!F96/'Historical Analysis'!F80,0) -> 0.39621607 | G47: =IFERROR('Historical Analysis'!G96/'Historical Analysis'!G80,0) -> 0.39530588 | H47: =IFERROR('Historical Analysis'!H96/'Historical Analysis'!H80,0) -> 0.3108454 | I47: =IFERROR('Historical Analysis'!I96/'Historical Analysis'!I80,0) -> 0.39515567 | J47: =IFERROR('Historical Analysis'!J96/'Historical Analysis'!J80,0) -> 0.42905771 | ... L47: =IFERROR('Historical Analysis'!L96/'Historical Analysis'!L80,0) -> 0.23792465 | N47: =IFERROR(AVERAGE(C47:L47),0) -> 0.36961064 | O47: =MEDIAN(C47:L47) -> 0.39523077
B48: CFO/Total Debt | C48: =IFERROR('Historical Analysis'!C96/'Historical Analysis'!C65,0) -> 61.866818 | D48: =IFERROR('Historical Analysis'!D96/'Historical Analysis'!D65,0) -> 79.595902 | E48: =IFERROR('Historical Analysis'!E96/'Historical Analysis'!E65,0) -> 17.714618 | F48: =IFERROR('Historical Analysis'!F96/'Historical Analysis'!F65,0) -> 21.221778 | G48: =IFERROR('Historical Analysis'!G96/'Historical Analysis'!G65,0) -> 12.215717 | H48: =IFERROR('Historical Analysis'!H96/'Historical Analysis'!H65,0) -> 10.317167 | I48: =IFERROR('Historical Analysis'!I96/'Historical Analysis'!I65,0) -> 13.115481 | J48: =IFERROR('Historical Analysis'!J96/'Historical Analysis'!J65,0) -> 13.104809 | ... L48: =IFERROR('Historical Analysis'!L96/'Historical Analysis'!L65,0) -> 7.1550793 | N48: =IFERROR(AVERAGE(C48:L48),0) -> 24.078438 | O48: =MEDIAN(C48:L48) -> 13.110145

Sheet Nestle - Forecasting
B7: ='Data Sheet'!B1&" - " &'Data Sheet'!A17 &" Forecasting" -> NESTLE INDIA LTD - Sales Forecasting | H7: ='Data Sheet'!B1 &" - " &'Data Sheet'!A18&" Forecasting" -> NESTLE INDIA LTD - Raw Material Cost Forecasting | M7: ='Data Sheet'!B1& " - " &'Data Sheet'!A28& " Forecasting" -> NESTLE INDIA LTD - Profit before tax Forecasting
A8: # | B8: Year Weight | C8: Year | D8: Sales | E8: Sales Growth | H8: Year Weight | I8: Year | J8: COGS | K8: COGS Growth | M8: Year Weight | N8: Year | O8: PBT | P8: PBT Growth
B9: 1 | C9: ='Data Sheet'!B16 -> 43100 | D9: {=TRANSPOSE('Data Sheet'!B17:K17)} -> 10009.6 | H9: 1 | I9: 43100 | J9: {=TRANSPOSE('Data Sheet'!B18:K18)} -> 3696.99 | M9: 1 | N9: 43100 | O9: {=TRANSPOSE('Data Sheet'!B28:K28)} -> 1839.3
B10: =B9+1 -> 2 | C10: =365+C9 -> 43465 | D10: 11292.27 | E10: =D10/D9-1 -> 0.12814398 | H10: 2 | I10: 43465 | J10: 3829.22 | K10: =J10/J9-1 -> 0.035766935 | M10: 2 | N10: 43465 | O10: 2428.95 | P10: =O10/O9-1 -> 0.32058392
B11: =B10+1 -> 3 | C11: =365+C10 -> 43830 | D11: 12368.9 | E11: =D11/D10-1 -> 0.095342212 | H11: 3 | I11: 43830 | J11: 4520.91 | K11: =J11/J10-1 -> 0.1806347 | M11: 3 | N11: 43830 | O11: 2673.49 | P11: =O11/O10-1 -> 0.10067725
B12: =B11+1 -> 4 | C12: =365+C11 -> 44195 | D12: 13350.03 | E12: =D12/D11-1 -> 0.079322333 | H12: 4 | I12: 44195 | J12: 4901.74 | K12: =J12/J11-1 -> 0.084237465 | M12: 4 | N12: 44195 | O12: 2812.79 | P12: =O12/O11-1 -> 0.052104178
B13: =B12+1 -> 5 | C13: =365+C12 -> 44560 | D13: 14740.59 | E13: =D13/D12-1 -> 0.10416156 | H13: 5 | I13: 44560 | J13: 5301.26 | K13: =J13/J12-1 -> 0.081505751 | M13: 5 | N13: 44560 | O13: 2857.32 | P13: =O13/O12-1 -> 0.015831257
B14: =B13+1 -> 6 | C14: =365+C13 -> 44925 | D14: 16896.96 | E14: =D14/D13-1 -> 0.1462879 | H14: 6 | I14: 44925 | J14: 6660.42 | K14: =J14/J13-1 -> 0.25638433 | M14: 6 | N14: 44925 | O14: 3255.97 | P14: =O14/O13-1 -> 0.13951885
B15: =B14+1 -> 7 | C15: =365+C14 -> 45290 | D15: 19126.3 | E15: =D15/D14-1 -> 0.13193734 | H15: 7 | I15: 45290 | J15: 8472.72 | K15: =J15/J14-1 -> 0.27209996 | M15: 7 | N15: 45290 | O15: 4038.29 | P15: =O15/O14-1 -> 0.24027248
B16: =B15+1 -> 8 | C16: =365+C15 -> 45655 | D16: 24393.89 | E16: =D16/D15-1 -> 0.27541082 | H16: 8 | I16: 45655 | J16: 9201.11 | K16: =J16/J15-1 -> 0.085968851 | M16: 8 | N16: 45655 | O16: 5288.87 | P16: =O16/O15-1 -> 0.30968058
B17: =B16+1 -> 9 | C17: =365+C16 -> 46020 | D17: 20201.56 | E17: =D17/D16-1 -> -0.17185984 | H17: 9 | I17: 46020 | J17: 7646.63 | K17: =J17/J16-1 -> -0.16894483 | M17: 9 | N17: 46020 | O17: 4447.47 | P17: =O17/O16-1 -> -0.1590888
B18: =B17+1 -> 10 | C18: =365+C17 -> 46385 | D18: 23154.6 | E18: =D18/D17-1 -> 0.14617881 | H18: 10 | I18: 46385 | J18: 9113.96 | K18: =J18/J17-1 -> 0.19189238 | M18: 10 | N18: 46385 | O18: 4609.65 | P18: =O18/O17-1 -> 0.036465676
B19: =B18+1 -> 11 | C19: =365+C18 -> 46750 | D19: =FORECAST(B19,$D$9:$D$18,$B$9:$B$18) -> 25229.475 | E19: =D19/D18-1 -> 0.089609638 | H19: 11 | I19: 46750 | J19: =FORECAST(H19,$J$9:$J$18,$H$9:$H$18) -> 10032.753 | K19: =J19/J18-1 -> 0.10081158 | M19: 11 | N19: 46750 | O19: =FORECAST(M19,$O$9:$O$18,$M$9:$M$18) -> 5299.038 | P19: =O19/O18-1 -> 0.14955322
B20: =B19+1 -> 12 | C20: =365+C19 -> 47115 | D20: =FORECAST(B20,$D$9:$D$18,$B$9:$B$18) -> 26806.931 | E20: =D20/D19-1 -> 0.062524309 | H20: 12 | I20: 47115 | J20: =FORECAST(H20,$J$9:$J$18,$H$9:$H$18) -> 10705.163 | K20: =J20/J19-1 -> 0.067021517 | M20: 12 | N20: 47115 | O20: =FORECAST(M20,$O$9:$O$18,$M$9:$M$18) -> 5639.734 | P20: =O20/O19-1 -> 0.064293934
B21: =B20+1 -> 13 | C21: =365+C20 -> 47480 | D21: =FORECAST(B21,$D$9:$D$18,$B$9:$B$18) -> 28384.386 | E21: =D21/D20-1 -> 0.058845062 | H21: 13 | I21: 47480 | J21: =FORECAST(H21,$J$9:$J$18,$H$9:$H$18) -> 11377.573 | K21: =J21/J20-1 -> 0.062811776 | M21: 13 | N21: 47480 | O21: =FORECAST(M21,$O$9:$O$18,$M$9:$M$18) -> 5980.43 | P21: =O21/O20-1 -> 0.060409941
B22: =B21+1 -> 14 | C22: =365+C21 -> 47845 | D22: =FORECAST(B22,$D$9:$D$18,$B$9:$B$18) -> 29961.842 | E22: =D22/D21-1 -> 0.055574762 | H22: 14 | I22: 47845 | J22: =FORECAST(H22,$J$9:$J$18,$H$9:$H$18) -> 12049.984 | K22: =J22/J21-1 -> 0.059099624 | M22: 14 | N22: 47845 | O22: =FORECAST(M22,$O$9:$O$18,$M$9:$M$18) -> 6321.126 | P22: =O22/O21-1 -> 0.056968479
B23: =B22+1 -> 15 | C23: =365+C22 -> 48210 | D23: =FORECAST(B23,$D$9:$D$18,$B$9:$B$18) -> 31539.297 | E23: =D23/D22-1 -> 0.052648817 | H23: 15 | I23: 48210 | J23: =FORECAST(H23,$J$9:$J$18,$H$9:$H$18) -> 12722.394 | K23: =J23/J22-1 -> 0.055801761 | M23: 15 | N23: 48210 | O23: =FORECAST(M23,$O$9:$O$18,$M$9:$M$18) -> 6661.822 | P23: =O23/O22-1 -> 0.053897992
A27: #

Sheet Beta - FMCG
B5: Nestlee Weekly Returns | G5: Nifty 50 Weekly Returns
B7: Date | C7: Price | D7: Weekly returns | G7: Date | H7: Price | I7: Weekly returns
B8: 46208 | C8: 1455.2 | G8: 46208 | H8: 49350.15 | L8: 3 Ways to calculate Beta:
B9: 46201 | C9: 1457.8 | D9: =C9/C8-1 -> 0.001786696 | G9: 46201 | H9: 50096.4 | I9: =H9/H8-1 -> 0.015121535
B10: 46194 | C10: 1400.68 | D10: =C10/C9-1 -> -0.03918233 | G10: 46194 | H10: 49419.25 | I10: =H10/H9-1 -> -0.013516939 | L10: Beta1 | M10: =SLOPE(D9:D59,I9:I59) -> 1.162631
B11: 46187 | C11: 1412.87 | D11: =C11/C10-1 -> 0.0087029157 | G11: 46187 | H11: 49558.7 | I11: =H11/H10-1 -> 0.0028217749 | L11: Beta2 | M11: =M32 -> 1.162631
B12: 46180 | C12: 1373.82 | D12: =C12/C11-1 -> -0.027638778 | G12: 46180 | H12: 48827.6 | I12: =H12/H11-1 -> -0.014752203 | L12: Beta3 | M12: =_xlfn.COVARIANCE.S(D9:D59,I9:I59)/_xlfn.VAR.P(I9:I59) -> 1.1858836
B13: 46173 | C13: 1386.2 | D13: =C13/C12-1 -> 0.0090113698 | G13: 46173 | H13: 48302.45 | I13: =H13/H12-1 -> -0.010755188
B14: 46166 | C14: 1421.5 | D14: =C14/C13-1 -> 0.025465301 | G14: 46166 | H14: 49383.35 | I14: =H14/H13-1 -> 0.022377747
B15: 46159 | C15: 1423.1 | D15: =C15/C14-1 -> 0.0011255716 | G15: 46159 | H15: 50249.8 | I15: =H15/H14-1 -> 0.017545387 | L15: SUMMARY OUTPUT
B16: 46152 | C16: 1430.5 | D16: =C16/C15-1 -> 0.0051999157 | G16: 46152 | H16: 51051.35 | I16: =H16/H15-1 -> 0.015951307
B17: 46145 | C17: 1482.4 | D17: =C17/C16-1 -> 0.036281021 | G17: 46145 | H17: 51165.9 | I17: =H17/H16-1 -> 0.0022438192 | L17: Regression Statistics
B18: 46138 | C18: 1458.6 | D18: =C18/C17-1 -> -0.016055046 | G18: 46138 | H18: 51072.1 | I18: =H18/H17-1 -> -0.0018332522 | L18: Multiple R | M18: 0.68042859
B19: 46131 | C19: 1421.3 | D19: =C19/C18-1 -> -0.025572467 | G19: 46131 | H19: 50766.25 | I19: =H19/H18-1 -> -0.0059885926 | L19: R Square | M19: 0.46298306
B20: 46124 | C20: 1285.6 | D20: =C20/C19-1 -> -0.095475973 | G20: 46124 | H20: 49657.75 | I20: =H20/H19-1 -> -0.021835373 | L20: Adjusted R Square | M20: 0.45202353
B21: 46117 | C21: 1249.3 | D21: =C21/C20-1 -> -0.028235843 | G21: 46117 | H21: 48194.05 | I21: =H21/H20-1 -> -0.029475762 | L21: Standard Error | M21: 0.022218089
B22: 46110 | C22: 1191.3 | D22: =C22/C21-1 -> -0.046425999 | G22: 46110 | H22: 46232.15 | I22: =H22/H21-1 -> -0.040708345 | L22: Observations | M22: 51
B23: 46103 | C23: 1193.2 | D23: =C23/C22-1 -> 0.0015948963 | G23: 46103 | H23: 46427.2 | I23: =H23/H22-1 -> 0.0042189256
B24: 46096 | C24: 1193.6 | D24: =C24/C23-1 -> 0.00033523299 | G24: 46096 | H24: 47007.55 | I24: =H24/H23-1 -> 0.012500215 | L24: ANOVA
B25: 46089 | C25: 1202.2 | D25: =C25/C24-1 -> 0.0072050938 | G25: 46089 | H25: 47924.15 | I25: =H25/H24-1 -> 0.019498995 | M25: df | N25: SS | O25: MS | P25: F | Q25: Significance F
B26: 46082 | C26: 1252.4 | D26: =C26/C25-1 -> 0.041756779 | G26: 46082 | H26: 49970.6 | I26: =H26/H25-1 -> 0.042701853 | L26: Regression | M26: 1 | N26: 0.020853867 | O26: 0.020853867 | P26: 42.244794 | Q26: 3.9551217e-08
B27: 46075 | C27: 1291.7 | D27: =C27/C26-1 -> 0.031379751 | G27: 46075 | H27: 51142.2 | I27: =H27/H26-1 -> 0.023445786 | L27: Residual | M27: 49 | N27: 0.02418853 | O27: 0.00049364347
B28: 46068 | C28: 1293.8 | D28: =C28/C27-1 -> 0.0016257645 | G28: 46068 | H28: 51772.7 | I28: =H28/H27-1 -> 0.012328371 | L28: Total | M28: 50 | N28: 0.045042397
B29: 46061 | C29: 1282.6 | D29: =C29/C28-1 -> -0.0086566703 | G29: 46061 | H29: 50902.15 | I29: =H29/H28-1 -> -0.016814846
B30: 46054 | C30: 1303.3 | D30: =C30/C29-1 -> 0.016139092 | G30: 46054 | H30: 51882.75 | I30: =H30/H29-1 -> 0.019264412 | M30: Coefficients | N30: Standard Error | O30: t Stat | P30: P-value | Q30: Lower 95% | R30: Upper 95% | S30: Lower 95.0% | T30: Upper 95.0%
B31: 46047 | C31: 1332.4 | D31: =C31/C30-1 -> 0.022327937 | G31: 46047 | H31: 51215.2 | I31: =H31/H30-1 -> -0.012866512 | L31: Intercept | M31: -0.0060143709 | N31: 0.0031514959 | O31: -1.9084178 | P31: 0.062204484 | Q31: -0.012347539 | R31: 0.00031879718 | S31: -0.012347539 | T31: 0.00031879718
B32: 46040 | C32: 1293.8 | D32: =C32/C31-1 -> -0.028970279 | G32: 46040 | H32: 51662.05 | I32: =H32/H31-1 -> 0.0087249488 | L32: X Variable 1 | M32: 1.162631 | N32: 0.17887733 | O32: 6.4995995 | P32: 3.9551217e-08 | Q32: 0.80316357 | R32: 1.5220985 | S32: 0.80316357 | T32: 1.5220985
B33: 46033 | C33: 1315.9 | D33: =C33/C32-1 -> 0.017081465 | G33: 46033 | H33: 52142.5 | I33: =H33/H32-1 -> 0.0092998632
B34: 46026 | C34: 1299.1 | D34: =C34/C33-1 -> -0.012766928 | G34: 46026 | H34: 52438.15 | I34: =H34/H33-1 -> 0.0056700388
B35: 46019 | C35: 1279.7 | D35: =C35/C34-1 -> -0.014933415 | G35: 46019 | H35: 53078.8 | I35: =H35/H34-1 -> 0.01221725 | L35: Beta Drifting
B36: 46012 | C36: 1272.6 | D36: =C36/C35-1 -> -0.0055481754 | G36: 46012 | H36: 55132.05 | I36: =H36/H35-1 -> 0.038683052
B37: 46005 | C37: 1244.4 | D37: =C37/C36-1 -> -0.022159359 | G37: 46005 | H37: 54781.35 | I37: =H37/H36-1 -> -0.0063610912 | L37: Levered Beta | M37: =M10 -> 1.162631
B38: 45998 | C38: 1238.3 | D38: =C38/C37-1 -> -0.0049019608 | G38: 45998 | H38: 54490.8 | I38: =H38/H37-1 -> -0.0053038123 | L38: Raw Beta weight | M38: 0.75
B39: 45991 | C39: 1246.9 | D39: =C39/C38-1 -> 0.0069450052 | G39: 45991 | H39: 55202.85 | I39: =H39/H38-1 -> 0.013067343 | L39: Market beta | M39: 1
B40: 45984 | C40: 1261.1 | D40: =C40/C39-1 -> 0.011388243 | G40: 45984 | H40: 55595.8 | I40: =H40/H39-1 -> 0.0071182919 | L40: Mean/Market Beta weight | M40: 0.25
B41: 45977 | C41: 1280.7 | D41: =C41/C40-1 -> 0.015541987 | G41: 45977 | H41: 55504.7 | I41: =H41/H40-1 -> -0.001638613
B42: 45970 | C42: 1271.6 | D42: =C42/C41-1 -> -0.0071054892 | G42: 45970 | H42: 55560.8 | I42: =H42/H41-1 -> 0.0010107252 | L42: Adjusted Beta | M42: =(M37*M38)+(M39*M40) -> 1.1219733
B43: 45963 | C43: 1262.7 | D43: =C43/C42-1 -> -0.0069990563 | G43: 45963 | H43: 55437.2 | I43: =H43/H42-1 -> -0.00222459
B44: 45956 | C44: 1271.6 | D44: =C44/C43-1 -> 0.0070483884 | G44: 45956 | H44: 56208.5 | I44: =H44/H43-1 -> 0.01391304
B45: 45949 | C45: 1282 | D45: =C45/C44-1 -> 0.0081786725 | G45: 45949 | H45: 56348.1 | I45: =H45/H44-1 -> 0.0024836101
B46: 45942 | C46: 1289.5 | D46: =C46/C45-1 -> 0.005850234 | G46: 45942 | H46: 56616.4 | I46: =H46/H45-1 -> 0.0047614738
B47: 45935 | C47: 1199.5 | D47: =C47/C46-1 -> -0.069794494 | G47: 45935 | H47: 54966.45 | I47: =H47/H46-1 -> -0.029142616
B48: 45928 | C48: 1169.9 | D48: =C48/C47-1 -> -0.024676949 | G48: 45928 | H48: 55170.6 | I48: =H48/H47-1 -> 0.0037140838
B49: 45921 | C49: 1162.6 | D49: =C49/C48-1 -> -0.0062398496 | G49: 45921 | H49: 54847.55 | I49: =H49/H48-1 -> -0.0058554737
B50: 45914 | C50: 1194.5 | D50: =C50/C49-1 -> 0.0274385 | G50: 45914 | H50: 56273.05 | I50: =H50/H49-1 -> 0.025990222
B51: 45907 | C51: 1217.6 | D51: =C51/C50-1 -> 0.019338635 | G51: 45907 | H51: 56557.15 | I51: =H51/H50-1 -> 0.0050485979
B52: 45900 | C52: 1208.5 | D52: =C52/C51-1 -> -0.0074737188 | G52: 45900 | H52: 56292.1 | I52: =H52/H51-1 -> -0.0046864101
B53: 45893 | C53: 1156.2 | D53: =C53/C52-1 -> -0.043276789 | G53: 45893 | H53: 56141.85 | I53: =H53/H52-1 -> -0.0026691134
B54: 45886 | C54: 1162.9 | D54: =C54/C53-1 -> 0.0057948452 | G54: 45886 | H54: 55737.45 | I54: =H54/H53-1 -> -0.0072031827
... B59: 45851 | C59: 1236.1 | D59: =C59/C58-1 -> 0.086872417 | G59: 45851 | H59: 56506.9 | I59: =H59/H58-1 -> 0.035305089
B66: Collected data from the Investing.com of Nestlee Historical data with 1 year , weekly returns.

Sheet Regression
B2: Nestle India LTD - Forecasting
C3: AM, GM | D3: Is not preferable data to forecast because the fluctuations in between may happened. Not suggestable to Forecast
B5: Year Weight | C5: Year | D5: Sales | E5: Sales Growth
B6: 1 | C6: 2015 | D6: 8175 | H6: Arthemetic Mean | J6: =AVERAGE(E7:E17) -> 0.10437516 | N6: SUMMARY OUTPUT
B7: =B6+1 -> 2 | C7: =C6+1 -> 2016 | D7: 9141 | E7: =D7/D6-1 -> 0.11816514
B8: =B7+1 -> 3 | C8: =C7+1 -> 2017 | D8: 10010 | E8: =D8/D7-1 -> 0.095066185 | H8: Geometric Mean | J8: =(D17/D6)^(1/B17)-1 -> 0.090635807 | N8: Regression Statistics
B9: =B8+1 -> 4 | C9: =C8+1 -> 2018 | D9: 11292 | E9: =D9/D8-1 -> 0.12807193 | H9: Geometric Mean | J9: =_xlfn.RRI(B17,D6,D17) -> 0.090635807 | N9: Multiple R | O9: 0.96328016
B10: =B9+1 -> 5 | C10: =C9+1 -> 2019 | D10: 12369 | E10: =D10/D9-1 -> 0.095377258 | N10: R Square | O10: 0.92790867 | P10: >>>> | Q10: Strength of the resgression idle 0.4 is good
B11: =B10+1 -> 6 | C11: =C10+1 -> 2020 | D11: 13350 | E11: =D11/D10-1 -> 0.079311181 | H11: Standard Devaiation | J11: =_xlfn.STDEV.S(E7:E17) -> 0.10553072 | N11: Adjusted R Square | O11: 0.92069953
B12: =B11+1 -> 7 | C12: =C11+1 -> 2021 | D12: 14741 | E12: =D12/D11-1 -> 0.10419476 | N12: Standard Error | O12: 1544.8019
B13: =B12+1 -> 8 | C13: =C12+1 -> 2022 | D13: 16897 | E13: =D13/D12-1 -> 0.14625873 | N13: Observations | O13: 12
B14: =B13+1 -> 9 | C14: =C13+1 -> 2023 | D14: 19126 | E14: =D14/D13-1 -> 0.13191691
B15: =B14+1 -> 10 | C15: =C14+1 -> 2024 | D15: 24394 | E15: =D15/D14-1 -> 0.27543658 | N15: ANOVA
B16: =B15+1 -> 11 | C16: =C15+1 -> 2025 | D16: 20202 | E16: =D16/D15-1 -> -0.17184554 | O16: df | P16: SS | Q16: MS | R16: F | S16: Significance F
B17: =B16+1 -> 12 | C17: =C16+1 -> 2026 | D17: 23155 | E17: =D17/D16-1 -> 0.14617365 | N17: Regression | O17: 1 | P17: 3.0716221e+08 | Q17: 3.0716221e+08 | R17: 128.71293 | S17: 4.9429742e-07
B18: =B17+1 -> 13 | C18: =C17+1 -> 2027 | D18: =FORECAST(B18,$D$6:$D$17,$B$6:$B$17) -> 24764.076 | E18: =D18/D17-1 -> 0.069491503 | N18: Residual | O18: 10 | P18: 23864130 | Q18: 2386413
B19: =B18+1 -> 14 | C19: =C18+1 -> 2028 | D19: =FORECAST(B19,$D$6:$D$17,$B$6:$B$17) -> 26229.677 | E19: =D19/D18-1 -> 0.05918256 | N19: Total | O19: 11 | P19: 3.3102634e+08
B20: =B19+1 -> 15 | C20: =C19+1 -> 2029 | D20: =FORECAST(B20,$D$6:$D$17,$B$6:$B$17) -> 27695.279 | E20: =D20/D19-1 -> 0.055875693
B21: =B20+1 -> 16 | C21: =C20+1 -> 2030 | D21: =FORECAST(B21,$D$6:$D$17,$B$6:$B$17) -> 29160.88 | E21: =D21/D20-1 -> 0.052918818 | O21: Coefficients | P21: Standard Error | Q21: t Stat | R21: P-value | S21: Lower 95% | T21: Upper 95% | U21: Lower 95.0% | V21: Upper 95.0%
B22: =B21+1 -> 17 | C22: =C21+1 -> 2031 | D22: =FORECAST(B22,$D$6:$D$17,$B$6:$B$17) -> 30626.481 | E22: =D22/D21-1 -> 0.050259162 | N22: Intercept | O22: 5711.2576 | P22: 950.75986 | Q22: 6.0070453 | R22: 0.00013087394 | S22: 3592.8326 | T22: 7829.6826 | U22: 3592.8326 | V22: 7829.6826
N23: Year Weight | O23: 1465.6014 | P23: 129.18283 | Q23: 11.345172 | R23: 4.9429742e-07 | S23: 1177.7641 | T23: 1753.4387 | U23: 1177.7641 | V23: 1753.4387
B27: 13 | C27: 2027 | D27: =$O$22+B18*$O$23 -> 24764.076 | E27: 0.069491503
B28: 14 | C28: 2028 | D28: =$O$22+B19*$O$23 -> 26229.677 | E28: =D28/D27-1 -> 0.05918256
B29: 15 | C29: 2029 | D29: =$O$22+B20*$O$23 -> 27695.279 | E29: =D29/D28-1 -> 0.055875693
B30: 16 | C30: 2030 | D30: =$O$22+B21*$O$23 -> 29160.88 | E30: =D30/D29-1 -> 0.052918818
B31: 17 | C31: 2031 | D31: =$O$22+B22*$O$23 -> 30626.481 | E31: =D31/D30-1 -> 0.050259162

Sheet Forecasting
B3: Nestle India LTD - Forecasting | K3: HUL - Forecasting
C4: AM, GM | D4: Is not preferable data to forecast because the fluctuations in between may happened. Not suggestable to Forecast
B6: Year Weight | C6: Year | D6: Sales | E6: Sales Growth | K6: Year Weight | L6: Year | M6: Sales | N6: Sales Growth
B7: 1 | C7: 2015 | D7: 8175 | K7: 1 | L7: 2015 | M7: 31972 | R7: AM assumes every year has equal importance and ignores the sequence and volatility of growth.
B8: =B7+1 -> 2 | C8: =C7+1 -> 2016 | D8: 9141 | E8: =D8/D7-1 -> 0.11816514 | K8: =K7+1 -> 2 | L8: =L7+1 -> 2016 | M8: 32186 | N8: =M8/M7-1 -> 0.0066933567 | R8: GM is generally better than AM when measuring long-term growth because it accounts for compounding.
B9: =B8+1 -> 3 | C9: =C8+1 -> 2017 | D9: 10010 | E9: =D9/D8-1 -> 0.095066185 | K9: =K8+1 -> 3 | L9: =L8+1 -> 2017 | M9: 33162 | N9: =M9/M8-1 -> 0.030323743
B10: =B9+1 -> 4 | C10: =C9+1 -> 2018 | D10: 11292 | E10: =D10/D9-1 -> 0.12807193 | K10: =K9+1 -> 4 | L10: =L9+1 -> 2018 | M10: 35545 | N10: =M10/M9-1 -> 0.071859357 | R10: Are AM and GM good for forecasting?
B11: =B10+1 -> 5 | C11: =C10+1 -> 2019 | D11: 12369 | E11: =D11/D10-1 -> 0.095377258 | K11: =K10+1 -> 5 | L11: =L10+1 -> 2019 | M11: 39310 | N11: =M11/M10-1 -> 0.10592207
B12: =B11+1 -> 6 | C12: =C11+1 -> 2020 | D12: 13350 | E12: =D12/D11-1 -> 0.079311181 | K12: =K11+1 -> 6 | L12: =L11+1 -> 2020 | M12: 39783 | N12: =M12/M11-1 -> 0.012032562 | R12: Yes, but only in stable businesses.
B13: =B12+1 -> 7 | C13: =C12+1 -> 2021 | D13: 14741 | E13: =D13/D12-1 -> 0.10419476 | K13: =K12+1 -> 7 | L13: =L12+1 -> 2021 | M13: 47028 | N13: =M13/M12-1 -> 0.18211296
B14: =B13+1 -> 8 | C14: =C13+1 -> 2022 | D14: 16897 | E14: =D14/D13-1 -> 0.14625873 | K14: =K13+1 -> 8 | L14: =L13+1 -> 2022 | M14: 52446 | N14: =M14/M13-1 -> 0.11520796 | R14: Examples:
B15: =B14+1 -> 9 | C15: =C14+1 -> 2023 | D15: 19126 | E15: =D15/D14-1 -> 0.13191691 | K15: =K14+1 -> 9 | L15: =L14+1 -> 2023 | M15: 60580 | N15: =M15/M14-1 -> 0.15509286
B16: =B15+1 -> 10 | C16: =C15+1 -> 2024 | D16: 24394 | E16: =D16/D15-1 -> 0.27543658 | K16: =K15+1 -> 10 | L16: =L15+1 -> 2024 | M16: 61896 | N16: =M16/M15-1 -> 0.021723341 | R16: FMCG (Nestlé)
B17: =B16+1 -> 11 | C17: =C16+1 -> 2025 | D17: 20202 | E17: =D17/D16-1 -> -0.17184554 | K17: =K16+1 -> 11 | L17: =L16+1 -> 2025 | M17: 61328 | N17: =M17/M16-1 -> -0.0091766835 | R17: Utilities
B18: =B17+1 -> 12 | C18: =C17+1 -> 2026 | D18: 23155 | E18: =D18/D17-1 -> 0.14617365 | K18: =K17+1 -> 12 | L18: =L17+1 -> 2026 | M18: 64468 | N18: =M18/M17-1 -> 0.051200104 | R18: Consumer Staples
R20: Historical averages may be reasonable starting points.
B21: Arthemetic Mean | D21: =AVERAGE(E8:E18) -> 0.10437516 | K21: Arthemetic Mean | M21: =AVERAGE(N8:N18) -> 0.067544694
R22: No, if the business is highly volatile.
B23: Geometric Mean | D23: =(D18/D7)^(1/B18)-1 -> 0.090635807 | K23: Geometric Mean | M23: =(M18/M7)^(1/K18)-1 -> 0.060183887
B24: Geometric Mean | D24: =_xlfn.RRI(B18,D7,D18) -> 0.090635807 | K24: Geometric Mean | M24: =_xlfn.RRI(K18,M7,M18) -> 0.060183887 | R24: Examples:
B26: Standard Devaiation | D26: =_xlfn.STDEV.S(E8:E18) -> 0.10553072 | K26: Standard Deviation | M26: =_xlfn.STDEV.S(N8:N18) -> 0.064012958 | R26: Airlines
R27: Startups
R28: Commodity companies
R29: Oil & Gas
R30: Semiconductor companies
R32: Here, historical averages can be misleading because future performance depends on changing business conditions.

Sheet Beta - Retailer
V2: Concept | W2: Meaning | X2: Purpose
B3: Avenue Super Market Weekly Returns | G3: Nifty Weekly Returns | V3: Regression | W3: Finds the relationship between two variables | X3: Forecasting
V4: Regression Line | W4: Best-fit trend line | X4: Predict future values
B5: Date | C5: Closing Price | D5: Weekly Returns | G5: Closing Price | H5: Weekly Returns | V5: Slope | W5: Change in Y for a change in X | X5: Measures sensitivity
B6: 44249 | C6: 2994.2 | G6: 14529.15 | L6: Beta 1 | M6: =SLOPE(D6:D110,H6:H110) -> 1.2421196 | V6: Beta | W6: Slope of stock return vs market return | X6: Measures market risk
B7: 44256 | C7: 3286.1001 | D7: =C7/C6-1 -> 0.097488528 | G7: 14938.1 | H7: =G7/G6-1 -> 0.028146809 | L7: Beta 2 | M7: =_xlfn.COVARIANCE.S(D7:D110,H7:H110)/_xlfn.VAR.P(H7:H110) -> 1.254179 | V7: Beta Regression | W7: Regression used to estimate Beta | X7: Input to CAPM
B8: 44263 | C8: 3129.3501 | D8: =C8/C7-1 -> -0.047700921 | G8: 15030.95 | H8: =G8/G7-1 -> 0.0062156893 | V8: CAPM | W8: Calculates Cost of Equity | X8: Input to WACC
B9: 44270 | C9: 2960.3 | D9: =C9/C8-1 -> -0.054020817 | G9: 14744 | H9: =G9/G8-1 -> -0.019090622 | L9: Beta 3 | M9: =M30 -> 1.2421196 | V9: WACC | W9: Discount Rate | X9: Input to DCF
B10: 44277 | C10: 2855.2 | D10: =C10/C9-1 -> -0.035503191 | G10: 14507.3 | H10: =G10/G9-1 -> -0.016054001
B11: 44284 | C11: 2912.7 | D11: =C11/C10-1 -> 0.020138695 | G11: 14867.35 | H11: =G11/G10-1 -> 0.024818526 | V11: Formula | W11: Symbol | X11: Business Logic
B12: 44291 | C12: 2947.75 | D12: =C12/C11-1 -> 0.012033525 | G12: 14834.85 | H12: =G12/G11-1 -> -0.0021859982 | V12: Beta | W12: ÷ | X12: Compare company movement with market movement
B13: 44298 | C13: 2919.8999 | D13: =C13/C12-1 -> -0.0094479172 | G13: 14617.85 | H13: =G13/G12-1 -> -0.014627718 | L13: SUMMARY OUTPUT | V13: Market Premium | W13: − | X13: Remove the risk-free return to get the extra reward for risk
B14: 44305 | C14: 2713.7 | D14: =C14/C13-1 -> -0.070618842 | G14: 14341.35 | H14: =G14/G13-1 -> -0.018915231 | V14: Beta × Premium | W14: × | X14: Adjust the premium based on the company's risk
B15: 44312 | C15: 2852.8999 | D15: =C15/C14-1 -> 0.051295262 | G15: 14631.1 | H15: =G15/G14-1 -> 0.020203817 | L15: Regression Statistics | V15: Cost of Equity | W15: + | X15: Safe return + Risk premium
B16: 44319 | C16: 2895.5 | D16: =C16/C15-1 -> 0.014932209 | G16: 14823.15 | H16: =G16/G15-1 -> 0.013126203 | L16: Multiple R | M16: 0.51108084 | V16: After-tax Debt | W16: − | X16: Reduce debt cost by the tax benefit
B17: 44326 | C17: 2844.6499 | D17: =C17/C16-1 -> -0.017561768 | G17: 14677.8 | H17: =G17/G16-1 -> -0.0098056474 | L17: R Square | M17: 0.26120363 | V17: WACC | W17: × then + | X17: Weight each funding source, then combine them
B18: 44333 | C18: 3034.1499 | D18: =C18/C17-1 -> 0.066616282 | G18: 15175.3 | H18: =G18/G17-1 -> 0.033894726 | L18: Adjusted R Square | M18: 0.25396053
B19: 44340 | C19: 3022.1001 | D19: =C19/C18-1 -> -0.0039713938 | G19: 15435.65 | H19: =G19/G18-1 -> 0.017156207 | L19: Standard Error | M19: 0.042285169
B20: 44347 | C20: 3197 | D20: =C20/C19-1 -> 0.05787363 | G20: 15670.25 | H20: =G20/G19-1 -> 0.015198557 | L20: Observations | M20: 104
B21: 44354 | C21: 3175.55 | D21: =C21/C20-1 -> -0.0067093997 | G21: 15799.35 | H21: =G21/G20-1 -> 0.0082385162
B22: 44361 | C22: 3317.7 | D22: =C22/C21-1 -> 0.044763868 | G22: 15683.35 | H22: =G22/G21-1 -> -0.0073420744 | L22: ANOVA
B23: 44368 | C23: 3315.3501 | D23: =C23/C22-1 -> -0.00070827773 | G23: 15860.35 | H23: =G23/G22-1 -> 0.011285854 | M23: df | N23: SS | O23: MS | P23: F | Q23: Significance F
B24: 44375 | C24: 3314.3 | D24: =C24/C23-1 -> -0.00031672341 | G24: 15722.2 | H24: =G24/G23-1 -> -0.0087103637 | L24: Regression | M24: 1 | N24: 0.064480852 | O24: 0.064480852 | P24: 36.0624 | Q24: 2.9630302e-08
B25: 44382 | C25: 3377.6001 | D25: =C25/C24-1 -> 0.01909907 | G25: 15689.8 | H25: =G25/G24-1 -> -0.0020608051 | L25: Residual | M25: 102 | N25: 0.18237962 | O25: 0.0017880355
B26: 44389 | C26: 3349.2 | D26: =C26/C25-1 -> -0.0084083806 | G26: 15923.4 | H26: =G26/G25-1 -> 0.014888691 | L26: Total | M26: 103 | N26: 0.24686047
B27: 44396 | C27: 3413.2 | D27: =C27/C26-1 -> 0.019109041 | G27: 15856.05 | H27: =G27/G26-1 -> -0.004229661
B28: 44403 | C28: 3500.8 | D28: =C28/C27-1 -> 0.025665094 | G28: 15763.05 | H28: =G28/G27-1 -> -0.0058652692 | M28: Coefficients | N28: Standard Error | O28: t Stat | P28: P-value | Q28: Lower 95% | R28: Upper 95% | S28: Lower 95.0% | T28: Upper 95.0%
B29: 44410 | C29: 3529.2 | D29: =C29/C28-1 -> 0.0081124033 | G29: 16238.2 | H29: =G29/G28-1 -> 0.030143303 | L29: Intercept | M29: 0.00010669116 | N29: 0.0041708465 | O29: 0.025580217 | P29: 0.97964214 | Q29: -0.008166163 | R29: 0.0083795453 | S29: -0.008166163 | T29: 0.0083795453
B30: 44417 | C30: 3594.55 | D30: =C30/C29-1 -> 0.018516972 | G30: 16529.1 | H30: =G30/G29-1 -> 0.017914511 | L30: X Variable 1 | M30: 1.2421196 | N30: 0.20684075 | O30: 6.0051978 | P30: 2.9630302e-08 | Q30: 0.83185198 | R30: 1.6523873 | S30: 0.83185198 | T30: 1.6523873
B31: 44424 | C31: 3643.1001 | D31: =C31/C30-1 -> 0.013506572 | G31: 16450.5 | H31: =G31/G30-1 -> -0.0047552263
B32: 44431 | C32: 3833.05 | D32: =C32/C31-1 -> 0.052139646 | G32: 16705.199 | H32: =G32/G31-1 -> 0.015482765
B33: 44438 | C33: 3938.8999 | D33: =C33/C32-1 -> 0.027615046 | G33: 17323.6 | H33: =G33/G32-1 -> 0.037018439 | L33: Beta Drifting
B34: 44445 | C34: 3950.5 | D34: =C34/C33-1 -> 0.0029450096 | G34: 17369.25 | H34: =G34/G33-1 -> 0.0026351562
B35: 44452 | C35: 4239.6499 | D35: =C35/C34-1 -> 0.073193242 | G35: 17585.15 | H35: =G35/G34-1 -> 0.012430035
B36: 44459 | C36: 4422.3501 | D36: =C36/C35-1 -> 0.043093227 | G36: 17853.199 | H36: =G36/G35-1 -> 0.015242908 | L36: Levered Beta | M36: =1.24 -> 1.24
B37: 44466 | C37: 4235.6001 | D37: =C37/C36-1 -> -0.042228678 | G37: 17532.051 | H37: =G37/G36-1 -> -0.017988285 | L37: Raw Beta weight | M37: 0.75
B38: 44473 | C38: 4407.9502 | D38: =C38/C37-1 -> 0.040690833 | G38: 17895.199 | H38: =G38/G37-1 -> 0.020713403 | L38: Market beta | M38: 1
B39: 44480 | C39: 5323.75 | D39: =C39/C38-1 -> 0.20776092 | G39: 18338.551 | H39: =G39/G38-1 -> 0.024774888 | L39: Mean/Market Beta weight | M39: 0.25
B40: 44487 | C40: 4521.4502 | D40: =C40/C39-1 -> -0.15070201 | G40: 18114.9 | H40: =G40/G39-1 -> -0.012195641
B41: 44494 | C41: 4635.4502 | D41: =C41/C40-1 -> 0.02521315 | G41: 17671.65 | H41: =G41/G40-1 -> -0.024468807 | L41: Adjusted Beta | M41: =((M36*M37)+(M38*M39)) -> 1.18
B42: 44501 | C42: 4783.7002 | D42: =C42/C41-1 -> 0.031981791 | G42: 17916.801 | H42: =G42/G41-1 -> 0.013872524
B43: 44508 | C43: 5078.5498 | D43: =C43/C42-1 -> 0.061636306 | G43: 18102.75 | H43: =G43/G42-1 -> 0.010378483
B44: 44515 | C44: 5080.8999 | D44: =C44/C43-1 -> 0.00046274962 | G44: 17764.801 | H44: =G44/G43-1 -> -0.018668391
B45: 44522 | C45: 4718.75 | D45: =C45/C44-1 -> -0.071276724 | G45: 17026.449 | H45: =G45/G44-1 -> -0.041562614
B46: 44529 | C46: 4799.0498 | D46: =C46/C45-1 -> 0.017017177 | G46: 17196.699 | H46: =G46/G45-1 -> 0.0099991488
B47: 44536 | C47: 4796.6001 | D47: =C47/C46-1 -> -0.00051045667 | G47: 17511.301 | H47: =G47/G46-1 -> 0.018294299
B48: 44543 | C48: 4697.7998 | D48: =C48/C47-1 -> -0.020597984 | G48: 16985.199 | H48: =G48/G47-1 -> -0.030043546
B49: 44550 | C49: 4628.8999 | D49: =C49/C48-1 -> -0.01466642 | G49: 17003.75 | H49: =G49/G48-1 -> 0.0010921733
B50: 44557 | C50: 4671.4502 | D50: =C50/C49-1 -> 0.0091923122 | G50: 17354.051 | H50: =G50/G49-1 -> 0.020601384
B51: 44564 | C51: 4731.3501 | D51: =C51/C50-1 -> 0.01282255 | G51: 17812.699 | H51: =G51/G50-1 -> 0.026428898
B52: 44571 | C52: 4322.7002 | D52: =C52/C51-1 -> -0.086370675 | G52: 18255.75 | H52: =G52/G51-1 -> 0.024872748
B53: 44578 | C53: 4299.7998 | D53: =C53/C52-1 -> -0.0052977049 | G53: 17617.15 | H53: =G53/G52-1 -> -0.034980738
... B110: 44977 | C110: 3552.8501 | D110: =C110/C109-1 -> 0.0022144141 | G110: 17844.6 | H110: =G110/G109-1 -> -0.0055505185

Sheet WACC
B6: Nestlee - Weighted Average Cost of Capital
B8: All figures are in INR unless stated otherwise
B10: Peer Companies
G12: Debt/ | H12: Debt/ | I12: Levered | J12: Unlevered
B13: Name of the Company | C13: Country | D13: Total Debt | E13: Total Equity | F13: Tax Rate1 | G13: Equity | H13: Capital | I13: Beta2 | J13: Beta3
B15: Nestle India | C15: India | D15: 444.16 | E15: 280608.3 | F15: 0.3 | G15: =D15/E15 -> 0.001582847 | H15: =D15/(D15+E15) -> 0.0015803455 | I15: 0.788 | J15: =I15/(1+(1-F15)*G15) -> 0.78712787
B16: Hind. Unilever | C16: India | D16: 1478 | E16: 505303.1 | F16: 0.3 | G16: =D16/E16 -> 0.0029249771 | H16: =D16/(D16+E16) -> 0.0029164466 | I16: 0.504 | J16: =I16/(1+(1-F16)*G16) -> 0.50297018
B17: Britannia Inds. | C17: India | D17: 1380.28 | E17: 128936.8 | F17: 0.3 | G17: =D17/E17 -> 0.01070509 | H17: =D17/(D17+E17) -> 0.010591704 | I17: 0.372 | J17: =I17/(1+(1-F17)*G17) -> 0.36923313
B18: Godrej Consumer | C18: India | D18: 4415.81 | E18: 111376.51 | F18: 0.3 | G18: =D18/E18 -> 0.039647588 | H18: =D18/(D18+E18) -> 0.038135603 | I18: 1.04 | J18: =I18/(1+(1-F18)*G18) -> 1.011916
B19: Tata Consumer | C19: India | D19: 2819.51 | E19: 110039.4 | F19: 0.3 | G19: =D19/E19 -> 0.025622731 | H19: =D19/(D19+E19) -> 0.024982609 | I19: 0.426 | J19: =I19/(1+(1-F19)*G19) -> 0.41849393
B20: Dabur India | C20: India | D20: 1287.32 | E20: 78674.79 | F20: 0.3 | G20: =D20/E20 -> 0.016362548 | H20: =D20/(D20+E20) -> 0.016099125 | I20: 0.927 | J20: =I20/(1+(1-F20)*G20) -> 0.91650258
E23: Average | F23: =AVERAGE(F15:F20) -> 0.3 | G23: =AVERAGE(G16:G20) -> 0.019052587 | H23: =AVERAGE(H16:H20) -> 0.018545098 | I23: =AVERAGE(I15:I20) -> 0.67616667 | J23: =AVERAGE(J15:J20) -> 0.66770728
E24: Median | F24: =MEDIAN(F15:F20) -> 0.3 | G24: =MEDIAN(G16:G20) -> 0.016362548 | H24: =MEDIAN(H16:H20) -> 0.016099125 | I24: =MEDIAN(I15:I20) -> 0.646 | J24: =MEDIAN(J15:J20) -> 0.64504902
B27: Cost of Debt | G27: Cost of Equity ( CAPM or Ke)
B29: Pre Tax Cost of Debt | D29: =37/D15 -> 0.083303314 | E29: >> Interest/Total Debt | G29: Risk Free Rate | K29: 0.06716 | L29: >>> 10 years Govt bond return
B30: Tax Rate | D30: =F15 -> 0.3 | G30: Equity Risk Premium | K30: =Rm!I5-WACC!K29 -> 0.084332308 | L30: >> Rm- Rf = Rewarded Return
B31: Actual debt after Tax | D31: =D29*(1-D30) -> 0.05831232 | G31: Levered Beta4 | K31: =K40 -> 0.653581
G32: Cost of Equity | K32: =K29+K30*K31 -> 0.12227799
B35: Capital Structure | G35: Levered Beta
D37: Current | E37: Targeted | G37: Comps median unlevered beta | K37: =J24 -> 0.64504902
B38: Total Debt | C38: =D15 -> 444.16 | D38: =C38/C40 -> 0.0015803455 | E38: =H23 -> 0.018545098 | G38: Targeted debt/Equity | K38: =E43 -> 0.018895517
B39: Market Capitalization | C39: =E15 -> 280608.3 | D39: =C39/C40 -> 0.99841965 | E39: =E40-E38 -> 0.9814549 | G39: Tax Rate | K39: =D30 -> 0.3
B40: Total Capital | C40: =SUM(C38:C39) -> 281052.46 | D40: =SUM(D38:D39) -> 1 | E40: =D40 -> 1 | G40: Levered Beta | K40: =K37*(1+(1-K39)*K38) -> 0.653581
B43: Debt/Equity | D43: =D38/D39 -> 0.001582847 | E43: =E38/E39 -> 0.018895517 | G43: WACC
G44: Cost of Debt | K44: =D31 -> 0.05831232
G45: Weight of Debt | K45: =E38 -> 0.018545098
G46: Cost of Equity | K46: =K32 -> 0.12227799
G47: Weight of Equity | K47: =E39 -> 0.9814549
G48: Final | K48: =(K44*K45)+(K46*K47) -> 0.12109174

Sheet Rm
B2: Year | C2: Annual
B3: 2000 | C3: -0.1465 | G3: Average Return | I3: =AVERAGE(C3:C28) -> 0.15149231 | J3: 100
B4: 2001 | C4: -0.1618 | G4: Dividend Yield | I4: 1.3%1
B5: 2002 | C5: 0.0325 | G5: Total Market Return | I5: =SUM(I3:I4) -> 0.15149231
B6: 2003 | C6: 0.719
B7: 2004 | C7: 0.1068
B8: 2005 | C8: 0.3634
B9: 2006 | C9: 0.3983
B10: 2007 | C10: 0.5477
B11: 2008 | C11: -0.5179
B12: 2009 | C12: 0.7576
B13: 2010 | C13: 0.1795
B14: 2011 | C14: -0.2462
B15: 2012 | C15: 0.277
B16: 2013 | C16: 0.0676
B17: 2014 | C17: 0.3139
... B28: 2025 | C28: 0.1051

Sheet Beta comparable companies
D2: FMCG | K2: Retailing
C4: S.No. | D4: Name | E4: CMP Rs. | F4: Mar Cap Rs.Cr. | G4: Debt / Eq | H4: Debt Rs.Cr. | K4: S.No. | L4: Name | M4: CMP Rs. | N4: Mar Cap Rs.Cr. | O4: Debt / Eq | P4: Debt Rs.Cr. | U4: Choose Retail Peer Companies | AA4: Beta Regression measures how sensitive a company's stock returns are relative to the market by regressing the company's historical returns against market returns. To estimate a more stable beta for valuation, analysts often use a bottom-up beta by selecting comparable companies, unlevering their betas to remove financing effects, averaging the business risk, and then relevering the beta using the target company's capital structure. The resulting beta is then used in CAPM to estimate the Cost of Equity, which feeds into WACC and ultimately DCF valuation.
C5: 1 | D5: Hind. Unilever | E5: 2150.6 | F5: 505303.1 | G5: 0.03 | H5: 1478 | K5: 1 | L5: Eternal | M5: 289.65 | N5: 279522.41 | O5: 0.15 | P5: 4592 | U5: │
C6: 2 | D6: ITC | E6: 281.75 | F6: 353017.77 | G6: 0.03 | H6: 2399.06 | K6: 2 | L6: Avenue Super. | M6: 4081.1 | N6: 266188.11 | O6: 0.1 | P6: 2424.99 | U6: ▼
C7: 3 | D7: Nestle India | E7: 1455.2 | F7: 280608.3 | G7: 0.08 | H7: 444.16 | K7: 3 | L7: Trent | M7: 2902.8 | N7: 154786.67 | O7: 0.37 | P7: 2561.25 | U7: Collect Levered Betas
C8: 4 | D8: Varun Beverages | E8: 478.1 | F8: 161715.65 | G8: 0.13 | H8: 2508.18 | K8: 4 | L8: FSN E-Commerce | M8: 330.1 | N8: 94534.83 | O8: 0.86 | P8: 1237.81 | U8: │
C9: 5 | D9: Britannia Inds. | E9: 5353 | F9: 128936.8 | G9: 0.27 | H9: 1380.28 | K9: 5 | L9: Lenskart Solut. | M9: 543.65 | N9: 94525.55 | O9: 0.35 | P9: 3096.6 | U9: ▼
C10: 6 | D10: Godrej Consumer | E10: 1088.4 | F10: 111376.51 | G10: 0.35 | H10: 4415.81 | K10: 6 | L10: Meesho | M10: 194.11 | N10: 89719.81 | O10: 0.01 | P10: 62.63 | U10: Remove Debt Effect
C11: 7 | D11: Marico | E11: 852.5 | F11: 110687.44 | G11: 0.13 | H11: 557 | K11: 7 | L11: Info Edg.(India) | M11: 1204.05 | N11: 78073.08 | O11: 0.01 | P11: 258.53 | U11: (Unlever Beta)
C12: 8 | D12: Tata Consumer | E12: 1111.9 | F12: 110039.4 | G12: 0.13 | H12: 2819.51 | K12: 8 | L12: Swiggy | M12: 273.25 | N12: 75425.57 | O12: 0.14 | P12: 2551 | U12: │
C13: 9 | D13: United Spirits | E13: 1385.7 | F13: 100789.01 | G13: 0.05 | H13: 413 | K13: 9 | L13: Vishal Mega Mart | M13: 118.79 | N13: 55644.9 | O13: 0.27 | P13: 1987.98 | U13: ▼
C14: 10 | D14: Dabur India | E14: 443.5 | F14: 78674.79 | G14: 0.11 | H14: 1287.32 | K14: 10 | L14: Urban Company | M14: 132.75 | N14: 20472.45 | O14: 0.06 | P14: 135.79 | U14: Average Industry Beta
C15: 11 | D15: Colgate-Palmoliv | E15: 2052.4 | F15: 55822.33 | G15: 0.03 | H15: 47.41 | K15: 11 | L15: Cartrade Tech | M15: 2809.9 | N15: 13493.99 | O15: 0.06 | P15: 140.43 | U15: │
C16: 12 | D16: Radico Khaitan | E16: 4073.7 | F16: 54580.41 | G16: 0.15 | H16: 498.44 | K16: 12 | L16: A B Lifestyle | M16: 95.55 | N16: 11662.08 | O16: 2.14 | P16: 3018.1 | U16: ▼
... C19: 15 | D19: Godfrey Phillips | E19: 2115.3 | F19: 32994.82 | G19: 0.04 | H19: 233.68 | K19: 15 | L19: Medplus Health | M19: 826.1 | N19: 9924.52 | O19: 0.72 | P19: 1424.38 | U19: │
U20: ▼
U21: Final Beta
U22: │
D23: Criteria | E23: Why? | U23: ▼
D24: Same Industry | E24: Retail | U24: CAPM → WACC → DCF
D25: Similar Business Model | E25: Grocery/Supermarket
D26: Similar Customers | E26: Mass retail consumers
D27: Similar Revenue Source | E27: Store sales
D28: Similar Geography | E28: Mainly India
D29: Similar Risk | E29: Consumer retail
D30: Similar Growth Stage | E30: Mature listed companies
D31: Similar Capital Structure | E31: Not extremely debt-heavy

Sheet Bajaj Finserve -Raw Data
B1: Bajaj Finserve Raw BS Data
A3: # | B3: Particulars | C3: 42064 | D3: 42430 | E3: 42795 | F3: 43160 | G3: 43525 | H3: 43891 | I3: 44256 | J3: 44621 | K3: 44986 | L3: 45352 | M3: 45717 | N3: 46082
B4: Equity Capital | C4: 80 | D4: 80 | E4: 80 | F4: 80 | G4: 80 | H4: 80 | I4: 80 | J4: 80 | K4: 159 | L4: 159 | M4: 160 | N4: 160
B5: Reserves | C5: 11009 | D5: 13519 | E5: 16071 | F5: 20403 | G5: 23660 | H5: 31222 | I5: 35750 | J5: 40167 | K5: 46248 | L5: 60169 | M5: 72236 | N5: 77755
B6: Borrowings -
B7: Long term Borrowings | C7: 17931 | D7: 24549 | E7: 32388 | F7: 58912 | G7: 87251 | H7: 0 | I7: 0 | J7: 0 | K7: 0 | L7: 0 | M7: 0 | N7: 0
B8: Short term Borrowings | C8: 4278 | D8: 5538 | E8: 8897 | F8: 6783 | G8: 12503 | H8: 0 | I8: 0 | J8: 0 | K8: 0 | L8: 0 | M8: 0 | N8: 0
B9: Other Borrowings | C9: 4103 | D9: 5974 | E9: 6996 | F9: 0 | G9: 0 | H9: 127212 | I9: 128461 | J9: 161179 | K9: 212265 | L9: 288933 | M9: 355855 | N9: 429914
B10: Other Liabilities -
B11: Non controlling int | C11: 4226 | D11: 5877 | E11: 7201 | F11: 10774 | G11: 12808 | H11: 19560 | I11: 22464 | J11: 26073 | K11: 31191 | L11: 43447 | M11: 56039 | N11: 63051
B12: Trade Payables | C12: 5365 | D12: 5984 | E12: 7451 | F12: 2834 | G12: 1700 | H12: 1927 | I12: 4178 | J12: 4009 | K12: 5205 | L12: 6277 | M12: 7965 | N12: 9052
B13: Other liability items | C13: 41236 | D13: 42430 | E13: 49530 | F13: 61728 | G13: 70426 | H13: 71303 | I13: 88912 | J13: 101905 | K13: 110333 | L13: 138429 | M13: 159265 | N13: 178563
A14: # | B14: Total Liabilities | C14: 88228 | D14: 103951 | E14: 128614 | F14: 161514 | G14: 208428 | H14: 251304 | I14: 279845 | J14: 333413 | K14: 405401 | L14: 537415 | M14: 651519 | N14: 758495
B16: Fixed Assets -
B17: Land | C17: 23 | D17: 31 | E17: 31 | F17: 30 | G17: 30 | H17: 312 | I17: 325 | J17: 476 | K17: 673 | L17: 674 | M17: 675 | N17: 675
B18: Building | C18: 763 | D18: 760 | E18: 755 | F18: 767 | G18: 876 | H18: 1005 | I18: 1020 | J18: 1065 | K18: 1090 | L18: 1140 | M18: 1153 | N18: 1188
B19: Equipments | C19: 80 | D19: 91 | E19: 108 | F19: 141 | G19: 202 | H19: 269 | I19: 264 | J19: 272 | K19: 320 | L19: 352 | M19: 446 | N19: 492
B20: Computers | C20: 267 | D20: 293 | E20: 343 | F20: 321 | G20: 363 | H20: 451 | I20: 465 | J20: 546 | K20: 702 | L20: 978 | M20: 1043 | N20: 1155
B21: Furniture n fittings | C21: 132 | D21: 141 | E21: 171 | F21: 222 | G21: 281 | H21: 342 | I21: 335 | J21: 308 | K21: 342 | L21: 461 | M21: 486 | N21: 535
B22: Vehicles | C22: 18 | D22: 25 | E22: 35 | F22: 52 | G22: 71 | H22: 109 | I22: 129 | J22: 187 | K22: 302 | L22: 464 | M22: 641 | N22: 754
B23: Intangible Assets | C23: 429 | D23: 429 | E23: 689 | F23: 689 | G23: 689 | H23: 689 | I23: 689 | J23: 689 | K23: 689 | L23: 689 | M23: 803 | N23: 803
B24: Other fixed assets | C24: 366 | D24: 376 | E24: 477 | F24: 592 | G24: 745 | H24: 1612 | I24: 1887 | J24: 2276 | K24: 2931 | L24: 4078 | M24: 4988 | N24: 5977
B25: Gross Block | C25: 2077 | D25: 2146 | E25: 2608 | F25: 2816 | G25: 3258 | H25: 4789 | I25: 5115 | J25: 5819 | K25: 7048 | L25: 8837 | M25: 10235 | N25: 11579
A26: # | B26: Accumulated Depreciation | C26: 816 | D26: 872 | E26: 963 | F26: 1024 | G26: 1161 | H26: 1573 | I26: 1933 | J26: 2234 | K26: 2712 | L26: 3381 | M26: 3938 | N26: 4850
B27: Net Block | C27: =C25-C26 -> 1261 | D27: =D25-D26 -> 1274 | E27: =E25-E26 -> 1645 | F27: =F25-F26 -> 1792 | G27: =G25-G26 -> 2097 | H27: =H25-H26 -> 3216 | I27: =I25-I26 -> 3182 | J27: =J25-J26 -> 3585 | ... N27: =N25-N26 -> 6729
B29: CWIP | C29: 3 | D29: 11 | E29: 4 | F29: 28 | G29: 66 | H29: 45 | I29: 129 | J29: 113 | K29: 191 | L29: 220 | M29: 314 | N29: 321
B30: Investments | C30: 51367 | D30: 53698 | E30: 62658 | F30: 69428 | G30: 81679 | H30: 91821 | I30: 113654 | J30: 119222 | K30: 136176 | L30: 170127 | M30: 190130 | N30: 194414
B32: Other Assets -
B33: Trade receivables | C33: 541 | D33: 681 | E33: 1253 | F33: 1753 | G33: 2273 | H33: 2658 | I33: 2753 | J33: 3005 | K33: 3459 | L33: 5974 | M33: 8319 | N33: 9332
B34: Cash Equivalents | C34: 1409 | D34: 2168 | E34: 1499 | F34: 1606 | G34: 1589 | H34: 2525 | I34: 3410 | J34: 4403 | K34: 5377 | L34: 12387 | M34: 15737 | N34: 17618
B35: Loans n Advances | C35: 13345 | D35: 18897 | E35: 26232 | F35: 142 | G35: 295 | H35: 635 | I35: 604 | J35: 721 | K35: 318 | L35: 436 | M35: 676 | N35: 419
B36: Other asset items | C36: 20303 | D36: 27223 | E36: 35322 | F36: 86764 | G36: 120429 | H36: 150404 | I36: 156112 | J36: 202364 | K36: 255544 | L36: 342817 | M36: 430046 | N36: 529662
A38: # | B38: Total Assets | C38: 88228 | D38: 103951 | E38: 128614 | F38: 161514 | G38: 208428 | H38: 251304 | I38: 279845 | J38: 333413 | K38: 405401 | L38: 537415 | M38: 651519 | N38: 758495
B41: INCOME STATEMENT
A42: # | B42: PARTICULARS | C42: 42064 | D42: 42430 | E42: 42795 | F42: 43160 | G42: 43525 | H42: 43891 | I42: 44256 | J42: 44621 | K42: 44986 | L42: 45352 | M42: 45717 | N42: 46082
B43: Sales + | C43: 11335 | D43: 20533 | E43: 24507 | F43: 32862 | G43: 42605 | H43: 54351 | I43: 60592 | J43: 68406 | K43: 82072 | L43: 110382 | M43: 132944 | N43: 150530
B44: Expenses + | C44: 5823 | D44: 13795 | E44: 15794 | F44: 22074 | G44: 27569 | H44: 36094 | I44: 40950 | J44: 46951 | K44: 52204 | L44: 69497 | M44: 83420 | N44: 93433
B45: GROSS Profit | C45: =C43-C44 -> 5512 | D45: =D43-D44 -> 6738 | E45: =E43-E44 -> 8713 | F45: =F43-F44 -> 10788 | G45: =G43-G44 -> 15036 | H45: =H43-H44 -> 18257 | I45: =I43-I44 -> 19642 | J45: =J43-J44 -> 21455 | ... N45: =N43-N44 -> 57097
B46: Other Income + | C46: 8 | D46: 0 | E46: 0 | F46: 1 | G46: 2 | H46: 0 | I46: -7 | J46: 8 | K46: 1 | L46: -4 | M46: -18 | N46: -382
B47: EBITDA | C47: =C45+C46 -> 5520 | D47: =D45+D46 -> 6738 | E47: =E45+E46 -> 8713 | F47: =F45+F46 -> 10789 | G47: =G45+G46 -> 15038 | H47: =H45+H46 -> 18257 | I47: =I45+I46 -> 19635 | J47: =J45+J46 -> 21463 | ... N47: =N45+N46 -> 56715
B48: Depreciation | C48: 38 | D48: 58 | E48: 73 | F48: 160 | G48: 226 | H48: 457 | I48: 498 | J48: 563 | K48: 678 | L48: 900 | M48: 1170 | N48: 1291
B49: EBIT | C49: =C47-C48 -> 5482 | D49: =D47-D48 -> 6680 | E49: =E47-E48 -> 8640 | F49: =F47-F48 -> 10629 | G49: =G47-G48 -> 14812 | H49: =H47-H48 -> 17800 | I49: =I47-I48 -> 19137 | J49: =J47-J48 -> 20900 | ... N49: =N47-N48 -> 55424
B50: Interest | C50: 2230 | D50: 2877 | E50: 3716 | F50: 4531 | G50: 6657 | H50: 9500 | I50: 9274 | J50: 9629 | K50: 12380 | L50: 18607 | M50: 24587 | N50: 28541
B51: PBT | C51: =C49-C50 -> 3252 | D51: =D49-D50 -> 3803 | E51: =E49-E50 -> 4924 | F51: =F49-F50 -> 6098 | G51: =G49-G50 -> 8155 | H51: =H49-H50 -> 8300 | I51: =I49-I50 -> 9863 | J51: =J49-J50 -> 11271 | ... N51: =N49-N50 -> 26883
B52: Profit before tax | C52: 3251 | D52: 3804 | E52: 4925 | F52: 6099 | G52: 8155 | H52: 8302 | I52: 9862 | J52: 11271 | K52: 16811 | L52: 21375 | M52: 23748 | N52: 26883
A55: # | B55: Particulars | C55: 42064 | D55: 42430 | E55: 42795 | F55: 43160 | G55: 43525 | H55: 43891 | I55: 44256 | J55: 44621 | K55: 44986 | L55: 45352 | M55: 45717 | N55: 46082
B56: Cash from Operating Activity - | C56: -10731 | D56: -9795 | E56: -10922 | F56: -19580 | G56: -27076 | H56: -23369 | I56: 4547 | J56: -33670 | K56: -39480 | L56: -65502 | M56: -61750 | N56: -55301
B57: Profit from operations | C57: 0 | D57: 0 | E57: 0 | F57: 3549 | G57: 5529 | H57: 9600 | I57: 5703 | J57: 12222 | K57: 14593 | L57: 18236 | M57: 24314 | N57: 34561
B58: Receivables | C58: 0 | D58: 0 | E58: 0 | F58: -100 | G58: -581 | H58: -491 | I58: 252 | J58: -425 | K58: -511 | L58: -2598 | M58: -2378 | N58: -1299
B59: Payables | C59: 0 | D59: 0 | E59: 0 | F59: 1260 | G59: -92 | H59: -73 | I59: 1142 | J59: 65 | K59: 1706 | L59: 264 | M59: 117 | N59: 1174
B60: Loans Advances | C60: 0 | D60: 0 | E60: 0 | F60: -24378 | G60: -34684 | H60: -32488 | I60: -9007 | J60: -49594 | K60: -53635 | L60: -87355 | M60: -89191 | N60: -102868
B61: Operating investments | C61: 0 | D61: 0 | E61: 0 | F61: 0 | G61: 0 | H61: 0 | I61: 0 | J61: 0 | K61: 0 | L61: 1973 | M61: -1429 | N61: 6213
B62: Operating borrowings | C62: 0 | D62: 0 | E62: 0 | F62: 0 | G62: 0 | H62: 0 | I62: 0 | J62: 0 | K62: 0 | L62: -25 | M62: 57 | N62: 105
B63: Other WC items | C63: 0 | D63: 0 | E63: 0 | F63: 2185 | G63: 5581 | H63: 2738 | I63: 8579 | J63: 7237 | K63: 2994 | L63: 9978 | M63: 13403 | N63: 14204
B64: Working capital changes | C64: 0 | D64: 0 | E64: 0 | F64: -21032 | G64: -29776 | H64: -30313 | I64: 965 | J64: -42717 | K64: -49446 | L64: -77763 | M64: -79423 | N64: -82471
B65: Direct taxes | C65: 0 | D65: 0 | E65: 0 | F65: -2098 | G65: -2830 | H65: -2656 | I65: -2121 | J65: -3176 | K65: -4627 | L65: -5975 | M65: -6642 | N65: -7392
B66: Other operating items | C66: -10731 | D66: -9795 | E66: -10922 | F66: 0 | G66: 0 | H66: 0 | I66: 0 | J66: 0 | K66: 0 | L66: 0 | M66: 0 | N66: 0
A68: # | B68: Cash from Investing Activity - | C68: 3709 | D68: -886 | E68: 151 | F68: -922 | G68: -6903 | H68: -9948 | I68: -3684 | J68: 1445 | K68: -13945 | L68: -14132 | M68: -7987 | N68: -12635
B69: Fixed assets purchased | C69: 0 | D69: 0 | E69: 0 | F69: -341 | G69: -647 | H69: -879 | I69: -471 | J69: -910 | K69: -1220 | L69: -1435 | M69: -1864 | N69: -1448
B70: Fixed assets sold | C70: 0 | D70: 0 | E70: 0 | F70: 38 | G70: 77 | H70: 9 | I70: 19 | J70: 160 | K70: 97 | L70: 126 | M70: 148 | N70: 131
B71: Investments purchased | C71: 0 | D71: 0 | E71: 0 | F71: -319723 | G71: -544269 | H71: -614784 | I71: -335077 | J71: -341682 | K71: -397673 | L71: -157405 | M71: -210973 | N71: -225505
B72: Investments sold | C72: 0 | D72: 0 | E72: 0 | F72: 315455 | G72: 534143 | H72: 601648 | I72: 326905 | J72: 338498 | K72: 378876 | L72: 139160 | M72: 198576 | N72: 208090
B73: Interest received | C73: 0 | D73: 0 | E73: 0 | F73: 104 | G73: 120 | H73: 135 | I73: 227 | J73: 401 | K73: 635 | L73: 0 | M73: 0 | N73: 0
B74: Acquisition of companies | C74: 0 | D74: 0 | E74: 0 | F74: 0 | G74: 0 | H74: 0 | I74: 0 | J74: 0 | K74: -93 | L74: -267 | M74: 0 | N74: 0
B75: Other investing items | C75: 3709 | D75: -886 | E75: 151 | F75: 3546 | G75: 3673 | H75: 3922 | I75: 4713 | J75: 4979 | K75: 5432 | L75: 5690 | M75: 6126 | N75: 6098
A77: # | B77: Cash from Financing Activity - | C77: 6839 | D77: 11602 | E77: 12513 | F77: 19590 | G77: 34535 | H77: 34479 | I77: 1687 | J77: 32326 | K77: 51016 | L77: 82709 | M77: 69828 | N77: 66610
B78: Proceeds from shares | C78: 0 | D78: 0 | E78: 0 | F78: 4538 | G78: 58 | H78: 8568 | I78: 103 | J78: 173 | K78: 227 | L78: 9169 | M78: 515 | N78: 698
B79: Proceeds from debentures | C79: 0 | D79: 0 | E79: 0 | F79: 8147 | G79: 12923 | H79: 1973 | I79: 0 | J79: 0 | K79: 0 | L79: 0 | M79: 0 | N79: 0
B80: Proceeds from borrowings | C80: 0 | D80: 0 | E80: 0 | F80: 3644 | G80: 16564 | H80: 16906 | I80: 4937 | J80: 45869 | K80: 74758 | L80: 94690 | M80: 99852 | N80: 126601
B81: Repayment of borrowings | C81: 0 | D81: 0 | E81: 0 | F81: 0 | G81: 0 | H81: 0 | I81: -7371 | J81: -17890 | K81: -36474 | L81: -34376 | M81: -39124 | N81: -52124
B82: Proceeds from deposits | C82: 0 | D82: 0 | E82: 0 | F82: 3441 | G82: 5264 | H82: 7988 | I82: 4246 | J82: 4784 | K82: 13557 | L82: 14760 | M82: 10527 | N82: 0
B83: Dividends paid | C83: 0 | D83: 0 | E83: 0 | F83: -110 | G83: -182 | H83: -683 | I83: -82 | J83: -400 | K83: -745 | L83: -1183 | M83: -1542 | N83: -1848
B84: Financial liabilities | C84: 0 | D84: 0 | E84: 0 | F84: 0 | G84: 0 | H84: -112 | I84: -146 | J84: -210 | K84: -305 | L84: -316 | M84: -399 | N84: -442
B85: Other financing items | C85: 6839 | D85: 11602 | E85: 12513 | F85: -70 | G85: -92 | H85: -161 | I85: 0 | J85: 0 | K85: -2 | L85: -35 | M85: 0 | N85: -6275
B86: Net Cash Flow | C86: -183 | D86: 921 | E86: 1742 | F86: -911 | G86: 555 | H86: 1162 | I86: 2551 | J86: 101 | K86: -2409 | L86: 3075 | M86: 92 | N86: -1326
B87: Free Cash Flow | C87: -10731 | D87: -9795 | E87: -10922 | F87: -19883 | G87: -27646 | H87: -24239 | I87: 4096 | J87: -34420 | K87: -40603 | L87: -66811 | M87: -63466 | N87: -56619
B88: CFO/OP | C88: -1.95 | D88: -1.45 | E88: -1.25 | F88: -1.62 | G88: -1.61 | H88: -1.13 | I88: 0.34 | J88: -1.42 | K88: -1.17 | L88: -1.46 | M88: -1.11 | N88: -0.84

Sheet Intrinsic Growth
B2: Intrinsic Growth> Focuses On Business Growth
B4: Intrinsic Growth > Company can achieve using its own profits, with out using any debt or issuing new shares in market.
B6: Calculation on Return on Invested Capital ( Instead of ROE doing ROIC) | E6: 44256 | F6: 44621 | G6: 44986 | H6: 45352 | I6: 45717 | J6: 46082 | L6: NOTES:
B8: Current Assets
B9: ='Bajaj Finserve -Raw Data'!B33 -> Trade receivables | E9: ='Bajaj Finserve -Raw Data'!I33 -> 2753 | F9: ='Bajaj Finserve -Raw Data'!J33 -> 3005 | G9: ='Bajaj Finserve -Raw Data'!K33 -> 3459 | H9: ='Bajaj Finserve -Raw Data'!L33 -> 5974 | I9: ='Bajaj Finserve -Raw Data'!M33 -> 8319 | J9: ='Bajaj Finserve -Raw Data'!N33 -> 9332 | L9: Net Non-Current Assets = capital locked in long-term assets.
B10: ='Bajaj Finserve -Raw Data'!B35 -> Loans n Advances | E10: ='Bajaj Finserve -Raw Data'!I35 -> 604 | F10: ='Bajaj Finserve -Raw Data'!J35 -> 721 | G10: ='Bajaj Finserve -Raw Data'!K35 -> 318 | H10: ='Bajaj Finserve -Raw Data'!L35 -> 436 | I10: ='Bajaj Finserve -Raw Data'!M35 -> 676 | J10: ='Bajaj Finserve -Raw Data'!N35 -> 419
B11: ='Bajaj Finserve -Raw Data'!B36 -> Other asset items | E11: ='Bajaj Finserve -Raw Data'!I36 -> 156112 | F11: ='Bajaj Finserve -Raw Data'!J36 -> 202364 | G11: ='Bajaj Finserve -Raw Data'!K36 -> 255544 | H11: ='Bajaj Finserve -Raw Data'!L36 -> 342817 | I11: ='Bajaj Finserve -Raw Data'!M36 -> 430046 | J11: ='Bajaj Finserve -Raw Data'!N36 -> 529662 | L11: Net Working Capital = capital locked in day-to-day operations.
A12: # | B12: Total Current Assets | E12: =SUM(E9:E11) -> 159469 | F12: =SUM(F9:F11) -> 206090 | G12: =SUM(G9:G11) -> 259321 | H12: =SUM(H9:H11) -> 349227 | I12: =SUM(I9:I11) -> 439041 | J12: =SUM(J9:J11) -> 539413
L13: Invested Capital = total capital tied up in operating activities.
B14: Current Liabilities
B15: ='Bajaj Finserve -Raw Data'!B12 -> Trade Payables | E15: ='Bajaj Finserve -Raw Data'!I12 -> 4178 | F15: ='Bajaj Finserve -Raw Data'!J12 -> 4009 | G15: ='Bajaj Finserve -Raw Data'!K12 -> 5205 | H15: ='Bajaj Finserve -Raw Data'!L12 -> 6277 | I15: ='Bajaj Finserve -Raw Data'!M12 -> 7965 | J15: ='Bajaj Finserve -Raw Data'!N12 -> 9052 | L15: Net Capital Expenditure (Net CapEx) = Capital Expenditure − Depreciation
B16: ='Bajaj Finserve -Raw Data'!B13 -> Other liability items | E16: ='Bajaj Finserve -Raw Data'!I13 -> 88912 | F16: ='Bajaj Finserve -Raw Data'!J13 -> 101905 | G16: ='Bajaj Finserve -Raw Data'!K13 -> 110333 | H16: ='Bajaj Finserve -Raw Data'!L13 -> 138429 | I16: ='Bajaj Finserve -Raw Data'!M13 -> 159265 | J16: ='Bajaj Finserve -Raw Data'!N13 -> 178563 | L16: Change in Working Capital = Current Year's Working Capital − Previous Year's Working Capital
A17: # | B17: Total Current Liabilities | E17: =SUM(E15:E16) -> 93090 | F17: =SUM(F15:F16) -> 105914 | G17: =SUM(G15:G16) -> 115538 | H17: =SUM(H15:H16) -> 144706 | I17: =SUM(I15:I16) -> 167230 | J17: =SUM(J15:J16) -> 187615 | L17: Net Capex= Assets purchased + sold
A19: # | B19: Net Working Capital | E19: =E12-E17 -> 66379 | F19: =F12-F17 -> 100176 | G19: =G12-G17 -> 143783 | H19: =H12-H17 -> 204521 | I19: =I12-I17 -> 271811 | J19: =J12-J17 -> 351798 | L19: Intrinsic Growth>>> Reinvestment Rate * ROIC
B20: >Current Assets- Current Liabilities
B22: Non Current Assets/ Fixed Assets
B23: ='Bajaj Finserve -Raw Data'!B17 -> Land | E23: ='Bajaj Finserve -Raw Data'!I17 -> 325 | F23: ='Bajaj Finserve -Raw Data'!J17 -> 476 | G23: ='Bajaj Finserve -Raw Data'!K17 -> 673 | H23: ='Bajaj Finserve -Raw Data'!L17 -> 674 | I23: ='Bajaj Finserve -Raw Data'!M17 -> 675 | J23: ='Bajaj Finserve -Raw Data'!N17 -> 675
B24: ='Bajaj Finserve -Raw Data'!B18 -> Building | E24: ='Bajaj Finserve -Raw Data'!I18 -> 1020 | F24: ='Bajaj Finserve -Raw Data'!J18 -> 1065 | G24: ='Bajaj Finserve -Raw Data'!K18 -> 1090 | H24: ='Bajaj Finserve -Raw Data'!L18 -> 1140 | I24: ='Bajaj Finserve -Raw Data'!M18 -> 1153 | J24: ='Bajaj Finserve -Raw Data'!N18 -> 1188
B25: ='Bajaj Finserve -Raw Data'!B19 -> Equipments | E25: ='Bajaj Finserve -Raw Data'!I19 -> 264 | F25: ='Bajaj Finserve -Raw Data'!J19 -> 272 | G25: ='Bajaj Finserve -Raw Data'!K19 -> 320 | H25: ='Bajaj Finserve -Raw Data'!L19 -> 352 | I25: ='Bajaj Finserve -Raw Data'!M19 -> 446 | J25: ='Bajaj Finserve -Raw Data'!N19 -> 492
B26: ='Bajaj Finserve -Raw Data'!B20 -> Computers | E26: ='Bajaj Finserve -Raw Data'!I20 -> 465 | F26: ='Bajaj Finserve -Raw Data'!J20 -> 546 | G26: ='Bajaj Finserve -Raw Data'!K20 -> 702 | H26: ='Bajaj Finserve -Raw Data'!L20 -> 978 | I26: ='Bajaj Finserve -Raw Data'!M20 -> 1043 | J26: ='Bajaj Finserve -Raw Data'!N20 -> 1155
B27: ='Bajaj Finserve -Raw Data'!B21 -> Furniture n fittings | E27: ='Bajaj Finserve -Raw Data'!I21 -> 335 | F27: ='Bajaj Finserve -Raw Data'!J21 -> 308 | G27: ='Bajaj Finserve -Raw Data'!K21 -> 342 | H27: ='Bajaj Finserve -Raw Data'!L21 -> 461 | I27: ='Bajaj Finserve -Raw Data'!M21 -> 486 | J27: ='Bajaj Finserve -Raw Data'!N21 -> 535
B28: ='Bajaj Finserve -Raw Data'!B22 -> Vehicles | E28: ='Bajaj Finserve -Raw Data'!I22 -> 129 | F28: ='Bajaj Finserve -Raw Data'!J22 -> 187 | G28: ='Bajaj Finserve -Raw Data'!K22 -> 302 | H28: ='Bajaj Finserve -Raw Data'!L22 -> 464 | I28: ='Bajaj Finserve -Raw Data'!M22 -> 641 | J28: ='Bajaj Finserve -Raw Data'!N22 -> 754
B29: ='Bajaj Finserve -Raw Data'!B23 -> Intangible Assets | E29: ='Bajaj Finserve -Raw Data'!I23 -> 689 | F29: ='Bajaj Finserve -Raw Data'!J23 -> 689 | G29: ='Bajaj Finserve -Raw Data'!K23 -> 689 | H29: ='Bajaj Finserve -Raw Data'!L23 -> 689 | I29: ='Bajaj Finserve -Raw Data'!M23 -> 803 | J29: ='Bajaj Finserve -Raw Data'!N23 -> 803
B30: ='Bajaj Finserve -Raw Data'!B24 -> Other fixed assets | E30: ='Bajaj Finserve -Raw Data'!I24 -> 1887 | F30: ='Bajaj Finserve -Raw Data'!J24 -> 2276 | G30: ='Bajaj Finserve -Raw Data'!K24 -> 2931 | H30: ='Bajaj Finserve -Raw Data'!L24 -> 4078 | I30: ='Bajaj Finserve -Raw Data'!M24 -> 4988 | J30: ='Bajaj Finserve -Raw Data'!N24 -> 5977
B31: Gross Block | E31: =SUM(E23:E30) -> 5114 | F31: =SUM(F23:F30) -> 5819 | G31: =SUM(G23:G30) -> 7049 | H31: =SUM(H23:H30) -> 8836 | I31: =SUM(I23:I30) -> 10235 | J31: =SUM(J23:J30) -> 11579
B32: Accumulated Dep | E32: ='Bajaj Finserve -Raw Data'!I26 -> 1933 | F32: ='Bajaj Finserve -Raw Data'!J26 -> 2234 | G32: ='Bajaj Finserve -Raw Data'!K26 -> 2712 | H32: ='Bajaj Finserve -Raw Data'!L26 -> 3381 | I32: ='Bajaj Finserve -Raw Data'!M26 -> 3938 | J32: ='Bajaj Finserve -Raw Data'!N26 -> 4850
A33: # | B33: Net Non Current Assets | E33: =E31-E32 -> 3181 | F33: =F31-F32 -> 3585 | G33: =G31-G32 -> 4337 | H33: =H31-H32 -> 5455 | I33: =I31-I32 -> 6297 | J33: =J31-J32 -> 6729
A35: # | B35: Invested Capital | E35: =E33+E19 -> 69560 | F35: =F33+F19 -> 103761 | G35: =G33+G19 -> 148120 | H35: =H33+H19 -> 209976 | I35: =I33+I19 -> 278108 | J35: =J33+J19 -> 358527
B36: >>Net Non current Assets+ Net working capital
B37: EBIT | E37: ='Bajaj Finserve -Raw Data'!I49 -> 19137 | F37: ='Bajaj Finserve -Raw Data'!J49 -> 20900 | G37: ='Bajaj Finserve -Raw Data'!K49 -> 29191 | H37: ='Bajaj Finserve -Raw Data'!L49 -> 39981 | I37: ='Bajaj Finserve -Raw Data'!M49 -> 48336 | J37: ='Bajaj Finserve -Raw Data'!N49 -> 55424
A39: # | B39: Return on Invested capital | E39: =E37/E35 -> 0.27511501 | F39: =F37/F35 -> 0.20142443 | G39: =G37/G35 -> 0.19707669 | H39: =H37/H35 -> 0.19040748 | I39: =I37/I35 -> 0.17380298 | J39: =J37/J35 -> 0.15458808
B40: NOPAT or EBIT/Invested capital
A42: # | B42: Calculation of Reinvestment Rate | E42: 44256 | F42: 44621 | G42: 44986 | H42: 45352 | I42: 45717 | J42: 46082
B44: NET Capex | E44: =-SUM('Bajaj Finserve -Raw Data'!I69:I70) -> 452 | F44: =-SUM('Bajaj Finserve -Raw Data'!J69:J70) -> 750 | G44: =-SUM('Bajaj Finserve -Raw Data'!K69:K70) -> 1123 | H44: =-SUM('Bajaj Finserve -Raw Data'!L69:L70) -> 1309 | I44: =-SUM('Bajaj Finserve -Raw Data'!M69:M70) -> 1716 | J44: =-SUM('Bajaj Finserve -Raw Data'!N69:N70) -> 1317
B45: Change in working capital | F45: =F19-E19 -> 33797 | G45: =G19-F19 -> 43607 | H45: =H19-G19 -> 60738 | I45: =I19-H19 -> 67290 | J45: =J19-I19 -> 79987
B47: EBIT | E47: =E37 -> 19137 | F47: =F37 -> 20900 | G47: =G37 -> 29191 | H47: =H37 -> 39981 | I47: =I37 -> 48336 | J47: =J37 -> 55424
B48: Marginal Tax Rate | E48: 0.25 | F48: 0.25 | G48: 0.25 | H48: 0.25 | I48: 0.25 | J48: 0.25
B49: EBIT (1-TAX) | E49: =E47*(1-E48) -> 14352.75 | F49: =F47*(1-F48) -> 15675 | G49: =G47*(1-G48) -> 21893.25 | H49: =H47*(1-H48) -> 29985.75 | I49: =I47*(1-I48) -> 36252 | J49: =J47*(1-J48) -> 41568
A50: # | B50: Reinvestment Amt | E50: =SUM(E44:E45) -> 452 | F50: =SUM(F44:F45) -> 34547 | G50: =SUM(G44:G45) -> 44730 | H50: =SUM(H44:H45) -> 62047 | I50: =SUM(I44:I45) -> 69006 | J50: =SUM(J44:J45) -> 81304
B51: Reinvestment Rate | E51: =E50/E49 -> 0.031492223 | F51: =F50/F49 -> 2.2039553 | G51: =G50/G49 -> 2.0430955 | H51: =H50/H49 -> 2.0692162 | I51: =I50/I49 -> 1.9035088 | J51: =J50/J49 -> 1.9559276
H53: 4 Yr Average | I53: =AVERAGE(E51:J51) -> 1.7011993
H54: 4 Yr Median | I54: =MEDIAN(E51:J51) -> 1.9995116
A57: # | B57: Calculation of Intrinsic Growth Rate | E57: 44256 | F57: 44621 | G57: 44986 | H57: 45352 | I57: 45717 | J57: 46082
B59: Reinvestment Rate | E59: =E51 -> 0.031492223 | F59: =F51 -> 2.2039553 | G59: =G51 -> 2.0430955 | H59: =H51 -> 2.0692162 | I59: =I51 -> 1.9035088 | J59: =J51 -> 1.9559276
B60: ROIC | E60: =E39 -> 0.27511501 | F60: =F39 -> 0.20142443 | G60: =G39 -> 0.19707669 | H60: =H39 -> 0.19040748 | I60: =I39 -> 0.17380298 | J60: =J39 -> 0.15458808
A61: # | B61: Intrinsic Growth Rate | E61: =E59*E60 -> 0.0086639831 | F61: =F59*F60 -> 0.44393044 | G61: =G59*G60 -> 0.4026465 | H61: =H59*H60 -> 0.39399423 | I61: =I59*I60 -> 0.3308355 | J61: =J59*J60 -> 0.30236309

Sheet DCF
B3: Calculation of PV of Free cash flow Firm
B5: Particulars | D5: ='Intrinsic Growth'!J6 -> 46082 | E5: =D5+365 -> 46447 | F5: =E5+366 -> 46813 | G5: =F5+365 -> 47178 | H5: =G5+365 -> 47543 | I5: =H5+365 -> 47908 | J5: =I5+366 -> 48274
B7: EBIT | D7: ='Bajaj Finserve -Raw Data'!N49 -> 55424 | E7: =D7*(1+$C$17) -> 72182.172 | F7: =E7*(1+$C$17) -> 94007.397 | G7: =F7*(1+$C$17) -> 122431.76 | H7: =G7*(1+$C$17) -> 159450.61 | I7: =H7*(1+$C$17) -> 207662.59 | J7: =I7*(1+$C$17) -> 270452.1
B8: TAX Rate | D8: 0.3 | E8: =D8 -> 0.3 | F8: =E8 -> 0.3 | G8: =F8 -> 0.3 | H8: =G8 -> 0.3 | I8: =H8 -> 0.3 | J8: =I8 -> 0.3 | N8: Notes:
B9: EBIT (1-TAX) | D9: =D7*(1-D8) -> 38796.8 | E9: =E7*(1-E8) -> 50527.521 | F9: =F7*(1-F8) -> 65805.178 | G9: =G7*(1-G8) -> 85702.235 | H9: =H7*(1-H8) -> 111615.43 | I9: =I7*(1-I8) -> 145363.81 | J9: =J7*(1-J8) -> 189316.47 | N9: EBIT × (1 − Tax) × (1 − Reinvestment)
B10: Less: Reinvestment Rate | D10: ='Intrinsic Growth'!$J$51 -> 1.9559276 | E10: =$D$10+(($J$10-$D$10)-4) -> 5.6511 | F10: =E10+(($J$10-$D$10)-4) -> 9.3462724 | G10: =F10+(($J$10-$D$10)-4) -> 13.041445 | H10: =G10+(($J$10-$D$10)-4) -> 16.736617 | I10: =H10+(($J$10-$D$10)-4) -> 20.431789 | J10: =965.11% -> 9.6511 | K10: >> Sector wise rate | N10: Instead ask:
B11: Free Cash Flow Firm | D11: =D9*(1-D10) -> -37086.933 | E11: =E9*(1-E10) -> -235008.55 | F11: =F9*(1-F10) -> -549227.94 | G11: =G9*(1-G10) -> -1031978.7 | H11: =H9*(1-H10) -> -1756449.3 | I11: =I9*(1-I10) -> -2824679 | J11: =J9*(1-J10) -> -1637795.7 | N11: 1. Who gets the first share? → Government (taxes).
B12: Mid year convention | E12: 0.5 | F12: =E12+1 -> 1.5 | G12: =F12+1 -> 2.5 | H12: =G12+1 -> 3.5 | I12: =H12+1 -> 4.5 | J12: =I12+1 -> 5.5 | N12: 2. Who gets the second share? → Business (reinvestment).
B13: Discounting Factor | E13: =1/(1+$C$19^E12) -> 0.73499411 | F13: =1/(1+$C$19^F12) -> 0.95522647 | G13: =1/(1+$C$19^G12) -> 0.99394352 | H13: =1/(1+$C$19^H12) -> 0.99920849 | I13: =1/(1+$C$19^I12) -> 0.99989703 | J13: =1/(1+$C$19^J12) -> 0.99998661 | N13: 3. Who gets what's left? → Investors (free cash flow).
B15: PV OF FCFF | E15: =E11*E13 -> -172729.9 | F15: =F11*F13 -> -524637.06 | G15: =G11*G13 -> -1025728.6 | H15: =H11*H13 -> -1755059 | I15: =I11*I13 -> -2824388.2 | J15: =J11*J13 -> -1637773.8 | N15: Terminal Growth Rate ≈ Long-term inflation + Real GDP growth
B17: Expected Growth | C17: ='Intrinsic Growth'!J59*'Intrinsic Growth'!J60 -> 0.30236309 | N17: Expected Growth:
B18: Terminal Growth | C18: 0.05 | N18: Growth comes from two things:
B19: WACC | C19: 0.13
N20: 1. How much the company reinvests (Reinvestment Rate).
N21: 2. How efficiently it earns returns on those investments (ROIC).
B22: If the Present Value (PV) of FCFF is negative, it does not automatically mean the company is bad. It tells you the company is destroying cash rather than generating cash during the forecast period. Your job is to find why.
N23: Eg: | O23: Expected Growth:
O24: Reinvestment rate* ROIC
B25: What should a Financial Analyst check? | G25: Terminal Value Formula | O25: 12% × 30% = 3.6%
B27: If FCFF is negative, don't stop at the number. Investigate: | G27: Where:
N28: FCFF is:
B29: Is EBIT positive or negative? | G29: TV = Terminal Value
B30: Is CapEx unusually high? | G30: FCFₙ₊₁ = Free Cash Flow in the year after your last forecast | N30: Cash generated by operations after paying taxes and reinvesting in the business.
B31: Is working capital increasing significantly? | G31: WACC = Discount Rate
B32: Is this temporary or persistent? | G32: g = Terminal Growth Rate | N32: If FCFF is negative:
B33: Is management investing for future growth?
G34: Forecast Growth = Short-term growth 📈 | N34: The company is spending more cash than it is generating from operations.
B36: The company generated ₹100 Cr from operations but invested ₹150 Cr back into the business. | G36: Terminal Growth = Long-term sustainable growth forever
B38: Interpretation: Negative FCFF due to aggressive investment, not necessarily poor performance
A41: # | B41: Calculation of Terminal Value | E41: Calculation of Equity Value
B43: FCFF(n+1) | C43: =J11*(1+C17) -> -2133004.7 | E43: PV of FCFF | F43: =SUM(E15:J15) -> -7940316.5
B44: WACC | C44: =C19 -> 0.13 | E44: PV of Terminal Value | F44: =C47*J13 -> -26662201
B45: Terminal Value Rate | C45: =C18 -> 0.05 | E45: Value of Operating Assets | F45: =SUM(F43:F44) -> -34602518
B47: Terminal Growth | C47: =C43/(C44-C45) -> -26662558 | E47: Cash: | F47: 17618
E48: Debt: | F48: -
E49: Value of Equity

Sheet DCF Notes
B2: What if Forecast Free Cash Flow becomes Negative?
B4: Example
B6: Year | C6: Free Cash Flow
B7: 1 | C7: 100
B8: 2 | C8: 80
B9: 3 | C9: 40
B10: 4 | C10: -20
B11: 5 | C11: -50
B13: Your question is:
B15: Can I still calculate Terminal Value?
B17: Case 1: Negative because of temporary investment ✅
B19: Example:
B21: New factory
B22: New product launch
B23: Expansion
B24: Heavy CapEx
B26: Then yes, you can still assume positive long-term growth if your forecast supports a recovery.
B28: Example:
B30: Year | C30: FCF
B31: 1 | C31: 100
B32: 2 | C32: 80
B33: 3 | C33: -20
B34: 4 | C34: 40
B35: 5 | C35: 90
B37: This is normal.
B41: Case 2: Negative because the business is deteriorating ⚠️
B43: Example:
B45: Revenue declining every year
B46: Margins shrinking
B47: Debt increasing
B48: Continuous cash burn
B50: Year | C50: FCF
B51: 1 | C51: 50
B52: 2 | C52: 10
B53: 3 | C53: -20
B54: 4 | C54: -60
B55: 5 | C55: -90
B57: Now ask yourself:
B59: Does it make business sense to assume the company will grow forever?
B61: Usually, no.
B63: The model is telling you that your assumptions may be unrealistic or that the company may require restructuring, external financing, or could even fail if nothing changes.
B67: The Logic You Should Follow
B69: Never ask:
B71: "Which formula should I use?"
B73: Instead ask:
B75: "Does this business story make sense?"
B79: Think Like a CFO
B81: Observation | C81: CFO thinks
B82: Revenue down | C82: Why? Temporary or permanent?
B83: FCF negative | C83: Expansion or distress?
B84: CapEx high | C84: Investment or waste?
B85: Debt increasing | C85: Funding growth or covering losses?
B86: Terminal Growth | C86: Can this company realistically grow forever?
B89: Why You're Missing the Calculation Logic
B91: Right now you're learning like this:
B93: Formula → Calculation → Answer
B95: Professional analysts think like this:
B97: Business Story → Assumptions → Calculation → Interpretation
B99: The formula is just the last step.
B103: A Better Learning Method (This will solve your problem)
B105: Whenever you learn a finance formula, create this table:
B107: Step | C107: Question
B108: 1 | C108: What is this formula calculating?
B109: 2 | C109: Why do we need it?
B110: 3 | C110: Where do the numbers come from? (Income Statement, Balance Sheet, Cash Flow)
B111: 4 | C111: Why are we adding or subtracting each component?
B112: 5 | C112: What does a high value mean?
B113: 6 | C113: What does a low or negative value mean?
B114: 7 | C114: What business story would produce this result?
B116: If you can't answer all seven, don't move to the next formula.
B120: For example: Free Cash Flow
B122: Question | C122: Answer
B123: What? | C123: Cash left after running and investing in the business
B124: Why? | C124: To value the company and assess financial flexibility
B125: Source? | C125: Cash Flow Statement
B126: Why subtract CapEx? | C126: Because cash was spent on long-term assets
B127: High FCF? | C127: Strong cash generation
B128: Negative FCF? | C128: Could be growth investment or financial weakness
B129: Business story? | C129: "The company invested heavily in expansion, reducing FCF today but potentially increasing future cash flows."

Sheet DCF 
A7: Discounted Cash Flow
F8: {=_xlfn.SEQUENCE(,6,0)} -> 0 | G8: 1 | H8: 2 | I8: 3 | J8: 4 | K8: 5
A9: # | B9: Particulars | F9: 2026 | G9: =F9+1 -> 2027 | H9: =G9+1 -> 2028 | I9: =H9+1 -> 2029 | J9: =I9+1 -> 2030 | K9: =J9+1 -> 2031 | M9: Assumptions:
B10: Growth | F10: 0.14 | G10: 0.1 | H10: 0.1 | I10: 0.08 | J10: 0.08 | K10: 0.06
B11: Revenue | F11: ='Historical Analysis'!L11 -> 23154.6 | G11: =F11*(1+G10) -> 25470.06 | H11: =G11*(1+H10) -> 28017.066 | I11: =H11*(1+I10) -> 30258.431 | J11: =I11*(1+J10) -> 32679.106 | K11: =J11*(1+K10) -> 34639.852 | M11: Revenue Growth | N11: 0.1 | O11: 0.06
B12: COGS | F12: ='Historical Analysis'!L13 -> 13627.64 | G12: =G11*$N$12 -> 11461.527 | H12: =H11*$N$12 -> 12607.68 | I12: =I11*$O$12 -> 15129.216 | J12: =J11*$O$12 -> 16339.553 | K12: =K11*$O$12 -> 17319.926 | M12: COGS | N12: 0.45 | O12: 0.5
B13: Gross Profit | F13: =F11-F12 -> 9526.96 | G13: =G11-G12 -> 14008.533 | H13: =H11-H12 -> 15409.386 | I13: =I11-I12 -> 15129.216 | J13: =J11-J12 -> 16339.553 | K13: =K11-K12 -> 17319.926 | M13: Operating exp | N13: 0.18 | O13: 0.2
B14: Operating xp | F14: ='Historical Analysis'!L18 -> 4780.9 | G14: =G11*$N$13 -> 4584.6108 | H14: =H11*$N$13 -> 5043.0719 | I14: =I11*$O$13 -> 6051.6863 | J14: =J11*$O$13 -> 6535.8212 | K14: =K11*$O$13 -> 6927.9704 | M14: Dep | N14: 0.025 | O14: 0.03
B15: Operating exp % on sales | F15: =F14/F11 -> 0.20647733 | G15: =G14/G11 -> 0.18 | H15: =H14/H11 -> 0.18 | I15: =I14/I11 -> 0.2 | J15: =J14/J11 -> 0.2 | K15: =K14/K11 -> 0.2 | M15: TAX | N15: 0.25 | O15: 0.26
B16: EBIT | F16: =F13-F14 -> 4746.06 | G16: =G13-G14 -> 9423.9222 | H16: =H13-H14 -> 10366.314 | I16: =I13-I14 -> 9077.5294 | J16: =J13-J14 -> 9803.7317 | K16: =K13-K14 -> 10391.956 | M16: Capex | N16: 0.05 | O16: 0.035
B17: TAX | F17: 0.25 | G17: 0.26 | H17: =G17 -> 0.26 | I17: 0.3 | J17: 0.3 | K17: 0.3 | M17: WC | N17: 0.015 | O17: 0.005
B18: NOPAT | F18: =F16*(1-F17) -> 3559.545 | G18: =G16*(1-G17) -> 6973.7024 | H18: =H16*(1-H17) -> 7671.0727 | I18: =I16*(1-I17) -> 6354.2706 | J18: =J16*(1-J17) -> 6862.6122 | K18: =K16*(1-K17) -> 7274.3689 | M18: Terminal Rate | N18: 0.05 | O18: 0.02
B19: Depreciation | F19: ='Historical Analysis'!L28 -> 699.23 | G19: =G11*N14 -> 636.7515 | H19: =H11*O14 -> 840.51198 | I19: =I11*$O$14 -> 907.75294 | J19: =J11*$O$14 -> 980.37317 | K19: =K11*$O$14 -> 1039.1956
B20: Capex | F20: =SUM('Historical Analysis'!L99:L100)*-1 -> 2005 | G20: =G11*$N$16 -> 1273.503 | H20: =H11*$N$16 -> 1400.8533 | I20: =I11*$O$16 -> 1059.0451 | J20: =J11*$O$16 -> 1143.7687 | K20: =K11*$O$16 -> 1212.3948
B21: Working capital | F21: 2764.69
B22: Change in WC | G22: =G11*$N$17 -> 382.0509 | H22: =H11*$N$17 -> 420.25599 | I22: =I11*$O$17 -> 151.29216 | J22: =J11*$O$17 -> 163.39553 | K22: =K11*$O$17 -> 173.19926
B23: Reinvestment Amt | F23: =F20+F22 -> 2005 | G23: =G20+G22 -> 1655.5539 | H23: =H20+H22 -> 1821.1093 | I23: =I20+I22 -> 1210.3373 | J23: =J20+J22 -> 1307.1642 | K23: =K20+K22 -> 1385.5941
B24: Free cash flow | F24: =F18+F19-F23 -> 2253.775 | G24: =G18+G19-G23 -> 5954.9 | H24: =H18+H19-H23 -> 6690.4754 | I24: =I18+I19-I23 -> 6051.6863 | J24: =J18+J19-J23 -> 6535.8212 | K24: =K18+K19-K23 -> 6927.9704
B25: WACC (Discount Rate) | F25: =WACC!K48 -> 0.12109174
B26: PV of FCFF | F26: =F24/(1+$F$25)^F8 -> 2253.775 | G26: =G24/(1+$F$25)^G8 -> 5311.6973 | H26: =H24/(1+$F$25)^H8 -> 5323.2231 | I26: =I24/(1+$F$25)^I8 -> 4294.8989 | J26: =J24/(1+$F$25)^J8 -> 4137.4765 | K26: =K24/(1+$F$25)^K8 -> 3912.0127
B29: Calculation of Terminal Value: | H29: Calculation of Enterprise Value
B31: FCFF(n+1) | E31: =K26*(1+K8) -> 23472.076 | G31: PV of FCFF | I31: =SUM(G26:K26) -> 22979.308
B32: WACC | E32: =WACC!K48 -> 0.12109174 | G32: PV of Temrinal Value | I32: =E39 -> 163444.04
B33: Terminal Rate | E33: 0.04
G34: Enterprise Value | I34: =SUM(I31:I32) -> 186423.35
B35: Terminal Value | E35: =E31/(E32-E33) -> 289450.87 | M35: Senstivity Analysis
G36: Cash | I36: ='Historical Analysis'!L77 -> 1340.87 | K36: Terminal | M36: WACC
B37: Year | E37: =K8 -> 5 | G37: Debt | I37: ='Historical Analysis'!L65 -> 444.16 | K37: =I43 -> 971.41855 | L37: 0.105 | M37: 0.1211 | N37: 0.135 | O37: 0.14 | P37: 0.15
K38: 0.03 | L38: 939.93106 | M38: 878.33919 | N38: 829.19324 | O38: 812.36438 | P38: 779.97803
B39: PV of Terminal Value | E39: =E35/(1+E32)^E37 -> 163444.04 | G39: Equity Value | I39: =I34+I36-I37 -> 187320.06 | K39: 0.04 | L39: 1039.9556 | M39: 971.38486 | N39: 916.67926 | O39: 897.9486 | P39: 861.90535
K40: 0.05 | L40: 1168.1197 | M40: 1090.6068 | N40: 1028.7774 | O40: 1007.6099 | P40: 966.88101
G41: No.of Shares | I41: ='Data Sheet'!B6 -> 192.83146 | K41: 0.06 | L41: 1338.2417 | M41: 1248.8591 | N41: 1177.5739 | O41: 1153.1718 | P41: 1106.2232
K42: 0.07 | L42: 1574.9585 | M42: 1469.0598 | N42: 1384.6171 | O42: 1355.7143 | P42: 1300.1113
G43: Intrinsci Value per share | I43: =I39/I41 -> 971.41855
G45: Current Share Price | I45: ='Data Sheet'!B8 -> 1409
G46: Undervalued | I46: =I45/I43-1 -> 0.45045614

Sheet Sheet1
B2: Working capital
C3: 2015 | D3: =C3+1 -> 2016 | E3: =D3+1 -> 2017 | F3: =E3+1 -> 2018 | G3: =F3+1 -> 2019 | H3: =G3+1 -> 2020 | I3: =H3+1 -> 2021 | J3: =I3+1 -> 2022 | K3: =J3+1 -> 2023 | ... N3: =M3+1 -> 2026
B4: inventories | C4: 821 | D4: 940 | E4: 902 | F4: 966 | G4: 1283 | H4: 1416 | I4: 1593 | J4: 1929 | K4: 1929 | L4: 2089 | M4: 2850 | N4: 2569
B5: Trade receivables | C5: 78 | D5: 98 | E5: 89 | F5: 125 | G5: 124 | H5: 165 | I5: 166 | J5: 192 | K5: 192 | L5: 300 | M5: 363 | N5: 329
B6: Loans n Advances | C6: 61 | D6: 21 | E6: 43 | F6: 48 | G6: 35 | H6: 47 | I6: 93 | J6: 68 | K6: 66 | L6: 76 | M6: 81 | N6: 100
B8: Total current assets | C8: =SUM(C4:C6) -> 960 | D8: =SUM(D4:D6) -> 1059 | E8: =SUM(E4:E6) -> 1034 | F8: =SUM(F4:F6) -> 1139 | G8: =SUM(G4:G6) -> 1442 | H8: =SUM(H4:H6) -> 1628 | I8: =SUM(I4:I6) -> 1852 | J8: =SUM(J4:J6) -> 2189 | ... N8: =SUM(N4:N6) -> 2998
B10: current liabilities
B11: Trade Payables | C11: 749 | D11: 799 | E11: 985 | F11: 1240 | G11: 1492 | H11: 1517 | I11: 1748 | J11: 2121 | K11: 2121 | L11: 2812 | M11: 2624 | N11: 3160
B12: Advance from Customers | C12: 103 | D12: 25 | E12: 17 | F12: 41 | G12: 37 | H12: 53 | I12: 69 | J12: 114 | L12: 16 | M12: 27 | N12: 103
B14: Current liabilities | C14: =SUM(C11:C12) -> 852 | D14: =SUM(D11:D12) -> 824 | E14: =SUM(E11:E12) -> 1002 | F14: =SUM(F11:F12) -> 1281 | G14: =SUM(G11:G12) -> 1529 | H14: =SUM(H11:H12) -> 1570 | I14: =SUM(I11:I12) -> 1817 | J14: =SUM(J11:J12) -> 2235 | ... N14: =SUM(N11:N12) -> 3263
B16: Working capital | C16: =C8-C14 -> 108 | D16: =D8-D14 -> 235 | E16: =E8-E14 -> 32 | F16: =F8-F14 -> -142 | G16: =G8-G14 -> -87 | H16: =H8-H14 -> 58 | I16: =I8-I14 -> 35 | J16: =J8-J14 -> -46 | ... N16: =N8-N14 -> -265
B18: change in WC | D18: =D16-C16 -> 127 | E18: =E16-D16 -> -203 | F18: =F16-E16 -> -174 | G18: =G16-F16 -> 55 | H18: =H16-G16 -> 145 | I18: =I16-H16 -> -23 | J18: =J16-I16 -> -81 | K18: =K16-J16 -> 112 | ... N18: =N16-M16 -> -908
B19: Sales - | C19: 8175 | D19: 9141 | E19: 10010 | F19: 11292 | G19: 12369 | H19: 13350 | I19: 14741 | J19: 16897 | K19: 19126 | L19: 24394 | M19: 20202 | N19: 23155
B21: WC % on sales | D21: =D18/D19 -> 0.013893447 | E21: =E18/E19 -> -0.02027972 | F21: =F18/F19 -> -0.015409139 | G21: =G18/G19 -> 0.0044466004 | H21: =H18/H19 -> 0.010861423 | I21: =I18/I19 -> -0.0015602741 | J21: =J18/J19 -> -0.0047937504 | K21: =K18/K19 -> 0.005855903 | ... N21: =N18/N19 -> -0.039213993
